Workbook
Name adicional_noturno: Indiretos!$H$14
Name adm_central: 'Adm Central'!$L$79
Name administração_local: Indiretos!$V$67
Name ajuste_HE_mdo_direta: BDI!$M$10
Name alojamentos: Indiretos!$Q$200
Name alojamentos_valor: Indiretos!$P$200
Name bdi: BDI!$H$39
Name canteiro_de_obras: Indiretos!$Q$234
Name canteiro_de_obras_valor: Indiretos!$P$234
Name Consultorias: Indiretos!$V$101
Name Consultorias_Valor: Indiretos!$V$101
Name controle_técnológico: Indiretos!$Q$499
Name controle_técnológico_valor: Indiretos!$P$499
Name custo_direto: BDI!$J$8
Name custo_direto_com_desconto_eventual: BDI!$J$8
Name custo_indireto: BDI!$J$14
Name data_base_da_obra: BDI!$J$6
Name desoneração: BDI!$H$32
Name despesas_administrativas: Indiretos!$Q$309
Name despesas_administrativas_valor: Indiretos!$P$309
Name despesas_indiretas: BDI!$J$26
Name dias_úteis_trabalhados: Indiretos!$K$11
Name dissídio_coletivo: Indiretos!$E$15
Name domingos_trabalhados: Indiretos!$K$13
Name efetivo_médio_dia: Indiretos!$AW$29
Name efetivo_médio_mes: BDI!$L$20
Name encargos_mensalista: Indiretos!$N$16
Name epi: Indiretos!$Q$455
Name epi_valor: Indiretos!$P$455
Name equipamentos: Indiretos!$Q$358
Name equipamentos_valor: Indiretos!$P$358
Name faturamento_anual: 'Taxa de Comercialização'!$G$9
Name ferramentas: Indiretos!$Q$419
Name ferramentas_valor: Indiretos!$P$419
Name hora_extra_dias_úteis: '[6]MDO - Indiretos'!$K$9
Name hora_extra_dias_úteis: Indiretos!$H$11
Name hora_extra_domingos: '[6]MDO - Indiretos'!$K$11
Name hora_extra_domingos: Indiretos!$H$13
Name hora_extra_mdo_direta: '[6]MDO - Indiretos'!$AH$108
Name hora_extra_mdo_direta: Indiretos!$AV$108
Name hora_extra_mdo_indireta: '[6]MDO - Indiretos'!$AH$107
Name hora_extra_mdo_indireta: Indiretos!$AV$107
Name hora_extra_sábados: '[6]MDO - Indiretos'!$K$10
Name hora_extra_sábados: Indiretos!$H$12
Name incidência_do_dissídio: '[6]MDO - Indiretos'!$K$13
Name incidência_do_dissídio: Indiretos!$H$15
Name ISS: [6]BDI!$H$37
Name ISS: BDI!$H$33
Name juros_medio: '[6]Despesas Financeiras'!$D$16
Name juros_medio: 'Despesas Financeiras'!$D$17
Name lucro_liquido: [6]BDI!$H$40
Name lucro_liquido: BDI!$H$38
Name lucro_liquido_valor: [6]BDI!$J$40
Name lucro_liquido_valor: BDI!$J$38
Name materiais: BDI!$J$9
Name mdo: BDI!$J$10
Name mdo_direta_alojada: '[6]Refeições Transporte Alojamento'!$G$10
Name mdo_direta_alojada: Indiretos!$R$115
Name mdo_direta_não_alojada: Indiretos!$S$115
Name mdo_indireta: Indiretos!$V$107

Sheet BDI
D2: Bonificação e Despesas Indiretas
F3: FC ENGENHARIA E CONSULTORIA LTDA
F4: julho/19 - Com desoneração da Folha de Pagamento
C6: ARQUIVO: | D6: =MID(CELL("filename"),SEARCH("[",CELL("filename"))+1,SEARCH("]",CELL("filename"))-SEARCH("[",CELL("filename"))-1) -> BDI_747.xlsx | G6: =Indiretos!E12&" meses" -> 8 meses | H6: =108.68+1074.09+1013.97+855.37+1002.53+904.62+904.62+904.62+421.75+904.62+110.96+110.96 -> 8316.79 | I6: Data: | J6: =TODAY() -> 46093
C8: CD | D8: Custo Direto | I8: =custo_direto/$H$6 -> 685.234 | J8: =materiais+J13 -> 5698947.3
B9: CD-01 | C9: CD-01 | D9: Materiais | H9: =materiais/custo_direto -> 0.57301332 | I9: =J9/$H$6 -> 392.64821 | J9: 3265572.7
B10: CD-02 | C10: CD-02 | D10: MDO Direta | I10: =J10/$H$6 -> 277.56353 | J10: 2308437.6 | L10: H.E. (reajuste) = | M10: =SUM(J11:J12)/mdo -> 0.054121877
B11: CD-02.1 | C11: CD-02.1 | D11: Horas Extras | H11: =J11/custo_direto -> 0 | J11: =hora_extra_mdo_direta -> 0
B12: CD-02.2 | C12: CD-02.2 | D12: Transferência + Ociosidade + Dissídio | H12: =J12/custo_direto -> 0.021922817 | J12: =transf_diss_ocio_mdo_direta -> 124936.98
B13: CD-03 | C13: CD-03 | D13: Total MDO Direta Reajustada | H13: =J13/custo_direto -> 0.42698668 | J13: =SUM(J10:J12) -> 2433374.6
B14: CI | C14: CI | D14: Custo Indireto | H14: =custo_indireto/custo_direto -> 0.10368564 | I14: =custo_indireto/$H$6 -> 71.048923 | J14: =SUM($J$18:$J$25) -> 590898.97
B15: CI-01.1 | C15: CI-01.1 | D15: Administração de obra | H15: =J15/custo_direto -> 0.036030046 | J15: =mdo_indireta_valor -> 205333.33
B16: CI-01.2 | C16: CI-01.2 | D16: Horas Extras | H16: =J16/custo_direto -> 0 | J16: =hora_extra_mdo_indireta -> 0 | O16: Despesas Indiretas Sem NF
B17: CI-01.3 | C17: CI-01.3 | D17: Transferência + Ociosidade + Dissídio | H17: =J17/custo_direto -> 0.0013511267 | J17: =transf_diss_ocio_mdo_indireta -> 7700
B18: CI-01 | C18: =HYPERLINK("#"&"'Indiretos'!D"&MATCH(B18,Indiretos!D:D,0),B18) -> CI-01 | D18: Administração de obra | H18: =J18/custo_direto -> 0.037381173 | I18: =J18/$H$6 -> 25.614851 | J18: =SUM(J15:J17) -> 213033.33 | L18: Efetivo mensal | O18: =H28 -> 0.0065 | P18: =O18*valor_de_venda1*$H$57 -> 27019.291
B19: CI-02 | C19: =HYPERLINK("#"&"'Indiretos'!D"&MATCH(B19,Indiretos!D:D,0),B19) -> CI-02 | D19: Refeições, Transportes e Estadias | H19: =J19/custo_direto -> 0.028788475 | I19: =J19/$H$6 -> 19.726842 | J19: =refeições_valor+transportes_valor+alojamentos_valor -> 164064 | L19: M.D.O Direta | M19: M.D.O Terceirizada | O19: =H29 -> 0.03 | P19: =O19*valor_de_venda1*$H$57 -> 124704.42
B20: CI-03 | C20: =HYPERLINK("#"&"'Indiretos'!D"&MATCH(B20,Indiretos!D:D,0),B20) -> CI-03 | D20: Canteiro de obras conservação e manutenção | H20: =J20/custo_direto -> 0.0063169562 | I20: =J20/$H$6 -> 4.3285931 | J20: =canteiro_de_obras_valor -> 36000 | L20: 40 | M20: 40 | O20: =H30 -> 0.012 | P20: =O20*valor_de_venda1*$H$57 -> 49881.768
B21: CI-04 | C21: =HYPERLINK("#"&"'Indiretos'!D"&MATCH(B21,Indiretos!D:D,0),B21) -> CI-04 | D21: Despesas Administrativas da obra | H21: =J21/custo_direto -> 0 | I21: =J21/$H$6 -> 0 | J21: =despesas_administrativas_valor -> 0 | L21: Supervisão e Apoio | O21: =H31 -> 0.0108 | P21: =O21*valor_de_venda1*$H$57 -> 44893.591
B22: CI-05 | C22: =HYPERLINK("#"&"'Indiretos'!D"&MATCH(B22,Indiretos!D:D,0),B22) -> CI-05 | D22: Máquinas, Ferramentas e Equipamentos | H22: =J22/custo_direto -> 0.0182278 | I22: =J22/$H$6 -> 12.490308 | J22: =ferramentas_valor+equipamentos_valor -> 103879.27 | L22: 3 | O22: =H32 -> 0 | P22: =O22*valor_de_venda1*$H$57 -> 0
B23: CI-06 | C23: =HYPERLINK("#"&"'Indiretos'!D"&MATCH(B23,Indiretos!D:D,0),B23) -> CI-06 | D23: Saúde e segurança do trabalho - ASO, EPI's e EPC's, conforme NR-6 | H23: =J23/custo_direto -> 0.012971232 | I23: =J23/$H$6 -> 8.8883291 | J23: =epi_valor+treinamentos_valor -> 73922.367 | L23: Coordenação | O23: =H33 -> 0.05 | P23: =O23*valor_de_venda1*$H$57 -> 207840.7
A24: S | B24: CI-07 | C24: =HYPERLINK("#"&"'Indiretos'!D"&MATCH(B24,Indiretos!D:D,0),B24) -> CI-07 | D24: Projetos complementares e controle tecnológico | H24: =J24/custo_direto -> 0 | J24: =mobilização_terceiros_valor+serviços_técnicos_valor+controle_técnológico_valor+projetos_valor -> 0 | L24: 1
B25: CI-08 | C25: =HYPERLINK("#"&"'Despesas Financeiras'!D"&MATCH(B25,'Despesas Financeiras'!B:B,0),B25) -> CI-08 | D25: Custo Financeiros, seguros e garantia ( art.618 cód. Civil ) | H25: =J25/custo_direto -> 5.2641301e-11 | J25: =montante_do_juros -> 0.0003
B26: DI | C26: DI | D26: Despesas Indiretas sem FD | H26: =despesas_indiretas/custo_direto -> 0.19759873 | I26: =despesas_indiretas/$H$6 -> 135.40137 | J26: =SUM($J$27:$J$39) -> 1126104.8 | L26: IMPOSTOS | O26: IMPOSTOS FD
A27: S | B27: DI-01 | C27: DI-01 | D27: Taxa de Administração Central | H27: =adm_central -> 0.04 | J27: =H27*$J$45 -> 166272.56
B28: DI-02 | C28: DI-02 | D28: PIS - Programa de Integração Social | H28: =0.65% -> 0.0065 | J28: =H28*$J$45 -> 27019.291 | L28: =H28 -> 0.0065 | M28: =L28*$J$45 -> 27019.291 | O28: =H28 -> 0.0065 | P28: =O28*valor_de_venda2 -> 48750
B29: DI-03 | C29: DI-03 | D29: COFINS - Financiamento da Seguridade Social | G29: =SUM(J28:J33) -> 454339.77 | H29: =3% -> 0.03 | J29: =H29*$J$45 -> 124704.42 | L29: =H29 -> 0.03 | M29: =L29*$J$45 -> 124704.42 | O29: =H29 -> 0.03 | P29: =O29*valor_de_venda2 -> 225000
B30: DI-04 | C30: DI-04 | D30: IRPJ - Imposto de Renda de Pessoa Jurídica | H30: =1.2% -> 0.012 | J30: =H30*$J$45 -> 49881.768 | L30: =H30 -> 0.012 | M30: =L30*$J$45 -> 49881.768 | O30: =H30 -> 0.012 | P30: =O30*valor_de_venda2 -> 90000
B31: DI-05 | C31: DI-05 | D31: CSLL - Contribuição Social do Lucro Líquido | H31: =1.08% -> 0.0108 | J31: =H31*$J$45 -> 44893.591 | L31: =H31 -> 0.0108 | M31: =L31*$J$45 -> 44893.591 | O31: =H31 -> 0.0108 | P31: =O31*valor_de_venda2 -> 81000
B32: DI-06 | C32: DI-06 | D32: CPRB - Contribuição Previdenciária Receita Bruta ( Lei nº 12.546/11 ) | H32: 0 | J32: =H32*$J$45 -> 0 | L32: =H32 -> 0 | M32: =L32*$J$45 -> 0 | O32: =H32 -> 0 | P32: =O32*valor_de_venda2 -> 0
B33: DI-07 | C33: DI-07 | D33: ISS Municipal* | F33: Dedução ISS = | G33: 0 | H33: 0.05 | J33: =H33*$J$45*(1-$G$33) -> 207840.7 | L33: =H33 -> 0.05 | M33: =L33*$J$45 -> 207840.7 | O33: =H33 -> 0.05 | P33: =O33*valor_de_venda2 -> 375000
B34: DI-08 | C34: DI-08 | D34: Taxa de risco, Imprevistos e pós obra. | H34: 0.05 | J34: =$H$34*$J$45 -> 207840.7 | L34: Impostos
B35: DI-09 | C35: DI-09 | D35: Seguro de responsabilidade civil e risco de engenharia | H35: 0 | J35: =$H$35*$J$45 -> 0 | L35: =SUM(L28:L33) -> 0.1093
B36: DI-09 | C36: DI-10 | D36: Comissionamento | H36: 0.007 | J36: =valor_de_venda1*H36 -> 29097.698 | L36: Atenção adotar 18,25% | M36: =(1/(1-L35)-100%) -> 0.12271247
B37: B | C37: B | D37: Bonificações
B38: B-01 | C38: B-01 | D38: Lucro Bruto Arbitrário | H38: 0.064605738 | J38: =lucro_liquido*$J$45 -> 268554.04
B39: B-02 | C39: B-02 | D39: BDI | H39: =SUM($H$34:$H$38)+SUM($H$27:$H$32)+ISS*(1-$G$33) -> 0.27090574
B40: B-01 | C40: B-04 | D40: Comissionamento líquido | J40: =(H36*valor_de_venda2) -> 52500
B41: B-01 | C41: B-05 | D41: Lucro Liquido | H41: =J41/valor_de_venda2 -> 0.064605738 | J41: =lucro_liquido*valor_de_venda2 -> 484543.03
B42: B-01 | C42: B-03 | D42: Lucro Mensal liquido | H42: =lucro_liquido/meses_obra -> 0.0080757172 | J42: =J38/meses_obra -> 33569.255
C43: CD + CI = | D43: ABNT16.633/CEE-162 | J43: =custo_direto+custo_indireto-'F.D.'!H121-'Bdi CURVA ABC - MAT'!H210 -> 3030709.2 | K43: =J43/H6 -> 364.40853
A45: S | B45: V1 | C45: JF | D45: Valor com BDI | J45: =J43/(1-bdi) -> 4156814 | K45: =valor_de_venda1/H6 -> 499.8099
B46: V-1 | C46: V1 | D46: Valor curva ABC | H46: =J46/valor_de_venda1 -> 0 | J46: ='Bdi CURVA ABC - MAT'!H210 -> 0
C47: V2 | D47: Valor do BDI para curva ABC | H47: 0 | J47: =(J46*H47)/(1-H47-$L$35) -> 0
B48: V-1 | C48: V3 | D48: Valor Faturamento Direto | H48: =J48/valor_de_venda1 -> 0.78404686 | J48: ='F.D.'!H121 -> 3259137 | L48: VER. IMPOSTO | U48: 2947125.2 | V48: Mob.
C49: V4 | D49: Valor de BDI do FD | H49: 0.02 | J49: =(J48*H49)/(1-H49-$L$35) -> 74862.455 | L49: =(J55-J48)*L35 -> 463526.33 | U49: 330666.5 | V49: Equip. | X49: 25450540
C50: V5 | D50: Valor do com impostos da curva ABC | H50: =M36 -> 0.12271247 | J50: =H50*J46 -> 0 | L50: =J50+G29+J51 -> 463526.33
C51: V6 | D51: Impostos sobre do ADM (curva ABC e FD) | J51: =((J49+J47))*M36 -> 9186.557 | L51: ... | M51: Lucro | O51: INSTALAÇÕES | P51: Lucro | R51: ... | S51: Lucro | U51: ... | V51: Lucro | X51: VENDA
J52: =valor_de_venda1+J48+J46 -> 7415951
C53: PV -1 | D53: Valor venda com Faturamento Direto | G53: Fator multiplicativo = | H53: =valor_de_venda2/(custo_direto+custo_indireto) -> 1.192398 | J53: =J52+J49+J50+J51 -> 7500000 | K53: =valor_de_venda2/H6 -> 901.79023
C54: LOTUS | D54: BDI planilha Lotus | G54: Fator multiplicativo = | H54: =J54/(custo_direto+custo_indireto) -> 1.2490327 | J54: =valor_de_venda2+J48*L35 -> 7856223.7 | K54: =J54/H6 -> 944.6221
C55: PV - 2 | D55: Valor venda com FD Parcial + ADM curva ABC | G55: Fator multiplicativo = | H55: =J55/(custo_direto+custo_indireto) -> 1.192398 | J55: =J52+J49+J47+J50+J51 -> 7500000 | K55: =J55/H6 -> 901.79023 | L55: 0 | M55: 1 | O55: 2000000 | P55: 1 | R55: 0 | S55: 0 | U55: 0 | V55: 0 | X55: =((L55*M55)+(O55*P55)+(R55*S55)+(U55*V55))+J55 -> 9500000 | Z55: 9500000
C56: PV - 3 | D56: Valor venda sem Faturamento Direto | G56: Fator multiplicativo = | H56: =1/(1-bdi) -> 1.3715648 | J56: =(custo_direto+custo_indireto)/(1-bdi) -> 8626931.5 | K56: =J56/H6 -> 1037.291 | L56: 0 | M56: 1 | O56: =(O55*P55)-O55 -> 0 | P56: 0 | R56: 0 | S56: 0 | U56: 0 | V56: 0 | X56: =((L56*M56)+(O56*P56)+(R56*S56)+(U56*V56))+J56 -> 8626931.5 | Z56: =X55-Z55 -> 0.00043551996
B57: V-3 | C57: V7 | D57: Nota Fiscal | H57: 1 | J57: =H57*J53 -> 7500000
C58: V8 | D58: Desconto da Nota Fiscal | H58: =-$J$58/$J$45 -> 0 | J58: =SUM(M28:M33)-SUM(P18:P23) -> 0
B59: V-3 | C59: V10 | D59: ="Valor a ser Faturado pela "&$F$3 -> Valor a ser Faturado pela FC ENGENHARIA E CONSULTORIA LTDA | H59: =1-($J$57/valor_de_venda2) -> 0 | J59: =valor_de_venda2-J57 -> 0
B60: V2 | C60: PVN | D60: Valor venda nota | G60: Fator multiplicativo = | H60: =J60/(custo_direto+custo_indireto) -> 1.3715648 | J60: =J56-J58 -> 8626931.5 | K60: =J60/H6 -> 1037.291
B69: B | C69: L | D69: Bonificações - CONSIDERANDO O ( PV -2 )
B70: B-01 | C70: L-01 | D70: Lucro Bruto | H70: =J70/J55 -> 0.05140773 | J70: =J71+(J71*M36) -> 385557.98
B71: B-01 | C71: L-02 | D71: Lucro Liquido | H71: =J71/J55 -> 0.045788865 | J71: =lucro_liquido_valor+J49+J47 -> 343416.49
B72: B-01 | C72: L-03 | D72: Lucro Mensal Bruno | H72: =J72/J55 -> 0.0064259663 | J72: =J70/meses_obra -> 48194.747 | K72: =J72/J70 -> 0.125
B73: B-01 | C73: L-04 | D73: Lucro Mensal liquido | H73: =J73/J55 -> 0.0057236082 | J73: =J71/meses_obra -> 42927.061
C75: Itens | D75: Total geral A + B + C + D + E = | I75: BDI = | J75: =J104+J114 -> 0.27090574
C76: A | D76: Custo Direto | J76: =SUM(J77:J80) -> 1.0219228
C77: A1 | D77: Materiais | J77: =$J$9/custo_direto -> 0.57301332
C78: A2 | D78: Mão de obra Direta | J78: =H13 -> 0.42698668
C79: A3 | D79: Mão de obra Direta + H.Extras | J79: =hora_extra_mdo_direta/custo_direto -> 0
C80: A4 | D80: Mão de obra Direta + Transf. + Ocio + Dissídio | J80: =transf_diss_ocio_mdo_direta/custo_direto -> 0.021922817
C81: B | D81: Custo Indireto | J81: =SUM($J$82:$J$103) -> 0.10458839
C82: B1 | D82: Engenharia | J82: =$J$15/custo_direto -> 0.036030046
C83: B2 | D83: Medicina e segurança do trabalho | J83: =medicina_e_segurança_do_trabalho -> 0
C84: B3 | D84: Equipe de apoio / Administrativo | J84: =administração_local -> 0
C85: B4 | D85: Serviços topográficos | J85: =topografia -> 0
C86: B5 | D86: Mão de obra + H.Extras | J86: =(hora_extra_mdo_indireta)/custo_direto -> 0
C87: B6 | D87: Mão de obra + Transf. + Ocio + Dissídio | J87: =(transf_diss_ocio_mdo_indireta)/custo_direto -> 0.0013511267
C88: B7 | D88: Canteiro de obras conservação e manutenção | J88: =canteiro_de_obras -> 0.0063169562
C89: B8 | D89: Transporte | J89: =transportes -> 0.0030084101
C90: B9 | D90: Estadias | J90: =alojamentos -> 1.8950869e-14
C91: B10 | D91: Refeições | J91: =refeições -> 0.026682823
C92: B11 | D92: EPI's | J92: =epi -> 0.011945136
C93: B12 | D93: Ferramentas manuais | J93: =ferramentas -> 0.0044603445
C94: B13 | D94: Equipamentos | J94: =equipamentos -> 0.013767455
C95: B14 | D95: Segurança patrimonial | J95: =segurança_patrimonial -> 0
C96: B15 | D96: Serviços Técnicos Especilizados | J96: =serviços_técnicos -> 0
C97: B16 | D97: Transporte de materiais e equipamentos | J97: 0
C98: B17 | D98: Controle tecnológico e execução de ensaios de qualidade | J98: =controle_técnológico -> 0
C99: B18 | D99: Treinamentos e exames adminissionais de equipe | J99: =treinamentos -> 0.0010260959
C100: B19 | D100: Seguro de vida para funcionários | J100: 0
C101: B20 | D101: Taxa de Comercialização | J101: 0
C102: B21 | D102: Mobilização de terceiros | J102: =mobilização_terceiros -> 0
C103: B22 | D103: Despesas Financeiras | J103: =valor_total_financiamento -> 5.2641301e-11
C104: C | D104: Despesas Indiretas | J104: =SUM($J$105:$J$113) -> 0.2063
C105: C1 | D105: Taxa de Administração Central | J105: =H27 -> 0.04
C106: C2 | D106: PIS - Programa de Integração Social | J106: =H28 -> 0.0065 | K106: Perfil da empresa para menor valor de alíquota conforme § 5º-C do art. 18 - Anexo 4:
C107: C3 | D107: IRPJ - Imposto de Renda de Pessoa Jurídica | J107: =H29 -> 0.03 | K107: Empresa optante pelo Simples Nacional com faturamente Anual na 4ª Faixa 9,78%;
C108: C4 | D108: COFINS - Financiamento da Seguridade Social | J108: =H30 -> 0.012
C109: C5 | D109: CSLL - Contribuição Social do Lucro Líquido | J109: =H31 -> 0.0108
C110: C6 | D110: Desoneração de Folha de Pagamento | J110: =H32 -> 0
C111: C7 | D111: ISS Municipal* | J111: =H33 -> 0.05
C112: C8 | D112: Taxa de Risco do Empreendimento | J112: =H34 -> 0.05
C113: C9 | D113: Seguro de responsabilidade civil e risco de engenharia | J113: =$H$36 -> 0.007
...

Sheet Indiretos
F2: Mão de Obra Indireta | T2: Materiais = | U2: =materiais -> 3265572.7
F3: =BDI!F3 -> FC ENGENHARIA E CONSULTORIA LTDA | T3: Mão de Obra = | U3: =mdo+hora_extra_mdo_direta+transf_diss_ocio_mdo_direta -> 2433374.6
F4: =BDI!F4 -> julho/19 - Com desoneração da Folha de Pagamento | T4: Σ = | U4: =SUM(U2:U3) -> 5698947.3
D6: Obra: | E6: =nome_da_obra -> BDI_747.xlsx | T6: Data base: | U6: =data_base_da_obra -> 46093
Z7: Reincidência de Encargos sobre hora extra
D8: QUADRO 1 - | E8: MÃO DE OBRA | Z8: 13º salário | AA8: =1/12 -> 0.083333333 | AB8: (artigo 142, § 5º da CLT)
Z9: Férias | AA9: =(1+1/3)/12 -> 0.11111111 | AB9: (artigo 142, § 5º da CLT)
P10: % de presença de MDO para horas extras | S10: Parâmetros Mín ( NR-18 e NR-4 ) | U10: CLT | Z10: Aviso prévio | AA10: =7/30/12 -> 0.019444444 | AB10: (alíneas “a” e “b” do artigo 7º da Lei nº 605/49)
D11: Data de início = | E11: =TODAY()+20 -> 46113 | G11: Hora extra dias úteis = | H11: 0.6 | J11: D. úteis trabalhados/mês = | K11: 22 | M11: Hora Extra em dias úteis = | N11: 0 | P11: Em dias úteis diurno = | Q11: 0.05 | S11: média homem/mês = | T11: =efetivo_médio_mes+média_supervisão+média_coordenação -> 44 | U11: Contrato | Z11: FGTS | AA11: 0.08 | AB11: (súmula 63 do TST)
D12: Prazo de obra = | E12: 8 | F12: meses | G12: Hora extra sábados = | H12: 0.6 | J12: Sáb. trabalhados/mês = | K12: 0 | M12: Hora Extra em sábados = | N12: 0 | P12: Em sábados diurno = | Q12: 0 | S12: Qtd mín Bacia e mic = | T12: =IF($T$11/20<0,1,ROUNDUP(($T$11/20),0)) -> 3 | Z12: Multa FGTS | AA12: =0.4*0.08 -> 0.032 | AB12: (súmula 63 do TST)
D13: Eventual atraso = | E13: 0 | F13: meses | G13: Hora extra domingos = | H13: 1 | J13: Dom. trabalhados/mês = | K13: 0 | M13: Hora Extra em domingos = | N13: 0 | P13: Em domingos diurno = | Q13: 0 | S13: Qtd mín chuveiro = | T13: =IF($T$11/20<0,1,ROUNDUP(($T$11/10),0)) -> 5 | Z13: DSR | AA13: 0.16831683 | AB13: (alíneas “a” e “b” do artigo 7º da Lei nº 605/49),
D14: Meses da obra = | E14: 8 | F14: meses | G14: Adicional noturno = | H14: 0.2 | J14: D. úteis trab. noturno/mês = | K14: 0 | M14: Hora Extra adic.noturno = | N14: 0 | P14: Em dias úteis noturno = | Q14: 0 | S14: Necessário Ambulatorio = | T14: NÃO | AA14: =SUM(AA8:AA13) -> 0.49420572
D15: Dissídio coletivo = | E15: 0.05 | F15: 46143 | G15: Incidência do dissídio = | H15: =IF((E11-F15)>0,0,IF((-(F15-E16)/30)<0,0,ROUNDDOWN((-(F15-E16)/30),0))) -> 7 | J15: Sáb. trab. noturno/mês = | K15: 0 | M15: Ociosidade por dia (h) = | N15: 0 | P15: Em sábados noturno = | Q15: 0 | S15: Necessário Tec. Seg. = | T15: SIM | U15: full time
D16: Data de fim = | E16: =EDATE(E11,+meses_obra) -> 46357 | G16: % de MDO Local (h) = | H16: 1 | J16: Dom trab. noturno/mês = | K16: 0 | M16: Encargos Sociais = | N16: 1.1268768 | P16: Em domingos noturno = | Q16: 0 | S16: Necessário Eng. Seg. = | T16: NÃO | U16: *part time
S18: Valor base conforme Convenção coletiva de trabalho ( CCT ) | AO18: CONSIDERADO HORA EXTRA+20%
D19: CD-03 | E19: MÃO DE OBRA DIRETA | I19: MODALIDADE | J19: QUANTIDADE | K19: TX. TRANSF | L19: ΔT EM OBRA | M19: UN | N19: BONUS MENSAL | O19: 13º + FÉRIAS PARA PJ | P19: VALOR HORA (ajustada) | Q19: QTD DE H.E. PREVISTA | S19: VALORES TOTAIS H.E. | U19: Total c/ HE | V19: =$U$21/meses_obra -> 372579.91 | Z19: Valor hora | AE19: Qtd de hora extra | AH19: Qtd adicional noturno | AL19: Valores unitários de Hora Extra | AO19: Unit. Hora Extra + Adc. noturno | AV19: MENSAL | AX19: TOTAL
Q20: =$H$11 -> 0.6 | R20: =hora_extra_domingos -> 1 | S20: =Q20 -> 0.6 | T20: =R20 -> 1 | AE20: dia útil | AF20: sáb | AG20: dom | AH20: dia útil | AI20: sáb | AJ20: dom | AL20: dia útil | AM20: sáb | AN20: dom | AO20: dia útil | AP20: sáb | AQ20: dom | AV20: Total s/ H.E. | AW20: Total c/ H.E. | AX20: Total s/ HE
D21: 01 | E21: Equipe - Mão de obra direta | O21: Proporcional | U21: =SUMIF(A:A,D21,U:U) -> 2980639.3 | Z21: com L.S. | AA21: Transf | AB21: Dissidio | AC21: Ossiosidade | AE21: HE d.útil | AF21: Qtd sáb | AG21: Qtd dom | AH21: HE d.útil | AI21: Qtd sáb | AJ21: Qtd dom | AL21: VH.d.útil | AM21: VH.sáb | AN21: VH.dom | AO21: VH.d.útil | AP21: VH.sáb | AQ21: VH.dom | AX21: =SUMIF(A:A,D21,AX:AX) -> 2980639.3
A22: 1 | D22: 1.01 | E22: Ajudante (MDO Base salarial Local) | H22: mês | I22: CLT | J22: =ROUND(((((mdo/(média_salarial_ponderada/220)/220)*0.5)/meses_obra)/(1+encargos_mensalista)),10)*percentual_de_mdo_local -> 35.832925 | L22: =meses_obra -> 8 | M22: =(9.39*220) -> 2065.8 | N22: 0 | O22: =IF(I22="CLT","N/A",(L22*(M22/12)*2)) -> N/A | P22: =AC22 -> 20.845121 | Q22: =AE22+AF22 -> 0 | R22: =AG22 -> 0 | S22: =Q22*AL22 -> 0 | T22: =R22*AN22 -> 0 | U22: =AW22*L22*J22 -> 1314617.3 | Z22: =IF(I22="CLT",(M22/220)*(1+encargos_mensalista),(M22/220)) -> 19.971373 | AA22: =Z22*(1+K22) -> 19.971373 | AB22: =AA22*(1+((incidência_do_dissídio/meses_obra)*dissídio_coletivo)) -> 20.845121 | AC22: =AB22*(1+(ociosidade_por_dia/9)) -> 20.845121 | AE22: =IF(I22="contrato",0,$N$11*$Q$11*$K$11) -> 0 | AF22: =IF(I22="contrato",0,$N$12*$Q$12*$K$12) -> 0 | AG22: =IF(I22="contrato",0,$N$13*$Q$13*$K$13) -> 0 | AH22: =IF(I22="contrato",0,$N$14*$Q$14*$K$14) -> 0 | AI22: =IF(I22="contrato",0,$N$14*$Q$15*$K$15) -> 0 | AJ22: =IF(I22="contrato",0,$N$14*$Q$16*$K$16) -> 0 | AL22: =IF(I22="contrato",0,ROUNDUP((M22/220)*(1+$AA$14)*(1+hora_extra_dias_úteis),2)) -> 22.45 | AM22: =IF(I22="contrato",0,ROUNDUP((M22/220)*(1+$AA$14)*(1+hora_extra_sábados),2)) -> 22.45 | AN22: =IF(I22="contrato",0,ROUNDUP((M22/220)*(1+$AA$14)*(1+hora_extra_domingos),2)) -> 28.07 | AO22: =IF(I22="contrato",0,ROUNDUP(AL22*(1+adicional_noturno),2)) -> 26.94 | AP22: =IF(I22="contrato",0,ROUNDUP(AM22*(1+adicional_noturno),2)) -> 26.94 | AQ22: =IF(I22="contrato",0,ROUNDUP(AN22*(1+adicional_noturno),2)) -> 33.69 | AV22: =IF(I22="CLT",IF(L22=0,0,P22*220+N22),(P22*220+N22+(O22/meses_obra))) -> 4585.9266 | AW22: =IF(I22="CLT",IF(L22=0,0,((P22*220)+(AE22*AL22)+(AF22*AM22)+(AG22*AN22)+(AH22*AO22)+(AI22*AP22)+(AJ22*AQ22)+N22)),AV22) -> 4585.9266 | AX22: =AV22*L22*J22 -> 1314617.3
A23: 1 | D23: 1.02 | E23: Oficiais (MDO Base salarial Local) | H23: mês | I23: CLT | J23: =ROUND(((((mdo/(média_salarial_ponderada/220)/220)*0.5)/meses_obra)/(1+encargos_mensalista)),10)*percentual_de_mdo_local -> 35.832925 | L23: =meses_obra -> 8 | M23: =(11.9*220) -> 2618 | N23: 0 | O23: =IF(I23="CLT","N/A",(L23*(M23/12)*2)) -> N/A | P23: =AC23 -> 26.417139 | Q23: =AE23+AF23 -> 0 | R23: =AG23 -> 0 | S23: =Q23*AL23 -> 0 | T23: =R23*AN23 -> 0 | U23: =AW23*L23*J23 -> 1666021.9 | Z23: =IF(I23="CLT",(M23/220)*(1+encargos_mensalista),(M23/220)) -> 25.309834 | AA23: =Z23*(1+K23) -> 25.309834 | AB23: =AA23*(1+((incidência_do_dissídio/meses_obra)*dissídio_coletivo)) -> 26.417139 | AC23: =AB23*(1+(ociosidade_por_dia/9)) -> 26.417139 | AE23: =IF(I23="contrato",0,$N$11*$Q$11*$K$11) -> 0 | AF23: =IF(I23="contrato",0,$N$12*$Q$12*$K$12) -> 0 | AG23: =IF(I23="contrato",0,$N$13*$Q$13*$K$13) -> 0 | AH23: =IF(I23="contrato",0,$N$14*$Q$14*$K$14) -> 0 | AI23: =IF(I23="contrato",0,$N$14*$Q$15*$K$15) -> 0 | AJ23: =IF(I23="contrato",0,$N$14*$Q$16*$K$16) -> 0 | AL23: =IF(I23="contrato",0,ROUNDUP((M23/220)*(1+$AA$14)*(1+hora_extra_dias_úteis),2)) -> 28.45 | AM23: =IF(I23="contrato",0,ROUNDUP((M23/220)*(1+$AA$14)*(1+hora_extra_sábados),2)) -> 28.45 | AN23: =IF(I23="contrato",0,ROUNDUP((M23/220)*(1+$AA$14)*(1+hora_extra_domingos),2)) -> 35.57 | AO23: =IF(I23="contrato",0,ROUNDUP(AL23*(1+adicional_noturno),2)) -> 34.14 | AP23: =IF(I23="contrato",0,ROUNDUP(AM23*(1+adicional_noturno),2)) -> 34.14 | AQ23: =IF(I23="contrato",0,ROUNDUP(AN23*(1+adicional_noturno),2)) -> 42.69 | AV23: =IF(I23="CLT",IF(L23=0,0,P23*220+N23),(P23*220+N23+(O23/meses_obra))) -> 5811.7707 | AW23: =IF(I23="CLT",IF(L23=0,0,((P23*220)+(AE23*AL23)+(AF23*AM23)+(AG23*AN23)+(AH23*AO23)+(AI23*AP23)+(AJ23*AQ23)+N23)),AV23) -> 5811.7707 | AX23: =AV23*L23*J23 -> 1666021.9
A24: 1 | D24: 1.03 | E24: Ajudante (Transf.-Base do município de Origem) | H24: mês | I24: CLT | J24: =ROUND(((((mdo/(média_salarial_ponderada/220)/220)*0.4)/meses_obra)/(1+encargos_mensalista)),10)*(1-percentual_de_mdo_local) -> 0 | L24: =meses_obra -> 8 | M24: =M22 -> 2065.8 | N24: 0 | O24: =IF(I24="CLT","N/A",(L24*(M24/12)*2)) -> N/A | P24: =AC24 -> 20.845121 | Q24: =AE24+AF24 -> 0 | R24: =AG24 -> 0 | S24: =Q24*AL24 -> 0 | T24: =R24*AN24 -> 0 | U24: =AW24*L24*J24 -> 0 | Z24: =IF(I24="CLT",(M24/220)*(1+encargos_mensalista),(M24/220)) -> 19.971373 | AA24: =Z24*(1+K24) -> 19.971373 | AB24: =AA24*(1+((incidência_do_dissídio/meses_obra)*dissídio_coletivo)) -> 20.845121 | AC24: =AB24*(1+(ociosidade_por_dia/9)) -> 20.845121 | AE24: =IF(I24="contrato",0,$N$11*$Q$11*$K$11) -> 0 | AF24: =IF(I24="contrato",0,$N$12*$Q$12*$K$12) -> 0 | AG24: =IF(I24="contrato",0,$N$13*$Q$13*$K$13) -> 0 | AH24: =IF(I24="contrato",0,$N$14*$Q$14*$K$14) -> 0 | AI24: =IF(I24="contrato",0,$N$14*$Q$15*$K$15) -> 0 | AJ24: =IF(I24="contrato",0,$N$14*$Q$16*$K$16) -> 0 | AL24: =IF(I24="contrato",0,ROUNDUP((M24/220)*(1+$AA$14)*(1+hora_extra_dias_úteis),2)) -> 22.45 | AM24: =IF(I24="contrato",0,ROUNDUP((M24/220)*(1+$AA$14)*(1+hora_extra_sábados),2)) -> 22.45 | AN24: =IF(I24="contrato",0,ROUNDUP((M24/220)*(1+$AA$14)*(1+hora_extra_domingos),2)) -> 28.07 | AO24: =IF(I24="contrato",0,ROUNDUP(AL24*(1+adicional_noturno),2)) -> 26.94 | AP24: =IF(I24="contrato",0,ROUNDUP(AM24*(1+adicional_noturno),2)) -> 26.94 | AQ24: =IF(I24="contrato",0,ROUNDUP(AN24*(1+adicional_noturno),2)) -> 33.69 | AV24: =IF(I24="CLT",IF(L24=0,0,P24*220+N24),(P24*220+N24+(O24/meses_obra))) -> 4585.9266 | AW24: =IF(I24="CLT",IF(L24=0,0,((P24*220)+(AE24*AL24)+(AF24*AM24)+(AG24*AN24)+(AH24*AO24)+(AI24*AP24)+(AJ24*AQ24)+N24)),AV24) -> 4585.9266 | AX24: =AV24*L24*J24 -> 0
A25: 1 | D25: 1.04 | E25: Oficiais (Transf.-Base do município de Origem) | H25: mês | I25: CLT | J25: =ROUND(((((mdo/(média_salarial_ponderada/220)/220)*0.6)/meses_obra)/(1+encargos_mensalista)),10)*(1-percentual_de_mdo_local) -> 0 | L25: =meses_obra -> 8 | M25: =M23 -> 2618 | N25: 0 | O25: =IF(I25="CLT","N/A",(L25*(M25/12)*2)) -> N/A | P25: =AC25 -> 26.417139 | Q25: =AE25+AF25 -> 0 | R25: =AG25 -> 0 | S25: =Q25*AL25 -> 0 | T25: =R25*AN25 -> 0 | U25: =AW25*L25*J25 -> 0 | Z25: =IF(I25="CLT",(M25/220)*(1+encargos_mensalista),(M25/220)) -> 25.309834 | AA25: =Z25*(1+K25) -> 25.309834 | AB25: =AA25*(1+((incidência_do_dissídio/meses_obra)*dissídio_coletivo)) -> 26.417139 | AC25: =AB25*(1+(ociosidade_por_dia/9)) -> 26.417139 | AE25: =IF(I25="contrato",0,$N$11*$Q$11*$K$11) -> 0 | AF25: =IF(I25="contrato",0,$N$12*$Q$12*$K$12) -> 0 | AG25: =IF(I25="contrato",0,$N$13*$Q$13*$K$13) -> 0 | AH25: =IF(I25="contrato",0,$N$14*$Q$14*$K$14) -> 0 | AI25: =IF(I25="contrato",0,$N$14*$Q$15*$K$15) -> 0 | AJ25: =IF(I25="contrato",0,$N$14*$Q$16*$K$16) -> 0 | AL25: =IF(I25="contrato",0,ROUNDUP((M25/220)*(1+$AA$14)*(1+hora_extra_dias_úteis),2)) -> 28.45 | AM25: =IF(I25="contrato",0,ROUNDUP((M25/220)*(1+$AA$14)*(1+hora_extra_sábados),2)) -> 28.45 | AN25: =IF(I25="contrato",0,ROUNDUP((M25/220)*(1+$AA$14)*(1+hora_extra_domingos),2)) -> 35.57 | AO25: =IF(I25="contrato",0,ROUNDUP(AL25*(1+adicional_noturno),2)) -> 34.14 | AP25: =IF(I25="contrato",0,ROUNDUP(AM25*(1+adicional_noturno),2)) -> 34.14 | AQ25: =IF(I25="contrato",0,ROUNDUP(AN25*(1+adicional_noturno),2)) -> 42.69 | AV25: =IF(I25="CLT",IF(L25=0,0,P25*220+N25),(P25*220+N25+(O25/meses_obra))) -> 5811.7707 | AW25: =IF(I25="CLT",IF(L25=0,0,((P25*220)+(AE25*AL25)+(AF25*AM25)+(AG25*AN25)+(AH25*AO25)+(AI25*AP25)+(AJ25*AQ25)+N25)),AV25) -> 5811.7707 | AX25: =AV25*L25*J25 -> 0
A26: 1 | D26: 1.05 | H26: mês | I26: CLT | L26: =meses_obra -> 8 | N26: 0 | O26: =IF(I26="CLT","N/A",(L26*(M26/12)*2)) -> N/A | P26: =AC26 -> 0 | Q26: =AE26+AF26 -> 0 | R26: =AG26 -> 0 | S26: =Q26*AL26 -> 0 | T26: =R26*AN26 -> 0 | U26: =AW26*L26*J26 -> 0 | Z26: =IF(I26="CLT",(M26/220)*(1+encargos_mensalista),(M26/220)) -> 0 | AA26: =Z26*(1+K26) -> 0 | AB26: =AA26*(1+((incidência_do_dissídio/meses_obra)*dissídio_coletivo)) -> 0 | AC26: =AB26*(1+(ociosidade_por_dia/9)) -> 0 | AE26: =IF(I26="contrato",0,$N$11*$Q$11*$K$11) -> 0 | AF26: =IF(I26="contrato",0,$N$12*$Q$12*$K$12) -> 0 | AG26: =IF(I26="contrato",0,$N$13*$Q$13*$K$13) -> 0 | AH26: =IF(I26="contrato",0,$N$14*$Q$14*$K$14) -> 0 | AI26: =IF(I26="contrato",0,$N$14*$Q$15*$K$15) -> 0 | AJ26: =IF(I26="contrato",0,$N$14*$Q$16*$K$16) -> 0 | AL26: =IF(I26="contrato",0,ROUNDUP((M26/220)*(1+$AA$14)*(1+hora_extra_dias_úteis),2)) -> 0 | AM26: =IF(I26="contrato",0,ROUNDUP((M26/220)*(1+$AA$14)*(1+hora_extra_sábados),2)) -> 0 | AN26: =IF(I26="contrato",0,ROUNDUP((M26/220)*(1+$AA$14)*(1+hora_extra_domingos),2)) -> 0 | AO26: =IF(I26="contrato",0,ROUNDUP(AL26*(1+adicional_noturno),2)) -> 0 | AP26: =IF(I26="contrato",0,ROUNDUP(AM26*(1+adicional_noturno),2)) -> 0 | AQ26: =IF(I26="contrato",0,ROUNDUP(AN26*(1+adicional_noturno),2)) -> 0 | AV26: =IF(I26="CLT",IF(L26=0,0,P26*220+N26),(P26*220+N26+(O26/meses_obra))) -> 0 | AW26: =IF(I26="CLT",IF(L26=0,0,((P26*220)+(AE26*AL26)+(AF26*AM26)+(AG26*AN26)+(AH26*AO26)+(AI26*AP26)+(AJ26*AQ26)+N26)),AV26) -> 0 | AX26: =AV26*L26*J26 -> 0
A28: D | I28: Salario base (mês) média ponderada = | J28: 1893.1 | L28: média ponderada = | M28: =AVERAGE(M22:M25) -> 2341.9
D30: CI-01 | E30: ADMINISTRAÇÃO DA OBRA | I30: MODALIDADE | J30: QUANTIDADE | K30: TX. TRANSF | L30: ΔT EM OBRA | M30: SALÁRIO | N30: BONUS MENSAL | O30: 13º + FÉRIAS | P30: VALOR HORA | Q30: QTD DE H.E. PREVISTA | S30: VALORES TOTAIS H.E. | U30: Total c/ HE | V30: =$U$32/meses_obra -> 26629.167
Q31: =$H$11 -> 0.6 | R31: =hora_extra_domingos -> 1 | S31: =Q31 -> 0.6 | T31: =R31 -> 1
E32: TOTAL Administração da obra | U32: =SUMIF(A:A,"S",U:U) -> 213033.33 | Z32: Valor hora | AE32: Qtd de hora extra | AH32: Qtd adicional noturno | AL32: Valores unitários de Hora Extra | AO32: Unit. Hora Extra + Adc. noturno | AS32: Categoria | AV32: MENSAL | AX32: TOTAL
AE33: dia útil | AF33: sáb | AG33: dom | AH33: dia útil | AI33: sáb | AJ33: dom | AL33: =AE33 -> dia útil | AM33: =AF33 -> sáb | AN33: =AG33 -> dom | AO33: =AH33 -> dia útil | AP33: =AI33 -> sáb | AQ33: =AJ33 -> dom | AS33: Supervisão e apoio | AT33: Coordenação | AV33: Total s/ H.E. | AW33: Total c/ H.E. | AX33: Total s/ HE
A34: S | D34: 02 | E34: Equipe de Engenharia local | O34: Proporcional | U34: =SUMIF(A:A,D34,U:U) -> 213033.33 | Z34: com L.S. | AA34: Transf | AB34: Dissidio | AC34: Ossiosidade | AE34: HE d.útil | AF34: Qtd sáb | AG34: Qtd dom | AH34: HE d.útil | AI34: Qtd sáb | AJ34: Qtd dom | AL34: VH.d.útil | AM34: VH.sáb | AN34: VH.dom | AO34: VH.d.útil | AP34: VH.sáb | AQ34: VH.dom | AX34: =SUMIF(A:A,D34,AX:AX) -> 213033.33
A35: 2 | D35: 2.01 | E35: Engenheiro - Gerencia de Contrato | H35: Coordenação | I35: Contrato | L35: =meses_obra -> 8 | M35: 16585 | N35: 0 | O35: =IF(I35="CLT","N/A",(L35*(M35/12)*2)) -> 22113.333 | P35: =IF(I35="contrato",AB35,AB35) -> 78.684517 | Q35: =AE35+AF35 -> 0 | R35: =AG35 -> 0 | S35: =Q35*AL35 -> 0 | T35: =R35*AN35 -> 0 | U35: =AW35*L35*J35 -> 0 | Z35: =IF(I35="CLT",(M35/220)*(1+encargos_mensalista),(M35/220)) -> 75.386364 | AA35: =Z35*(1+K35) -> 75.386364 | AB35: =AA35*(1+((incidência_do_dissídio/meses_obra)*dissídio_coletivo)) -> 78.684517 | AC35: =AB35*(1+(ociosidade_por_dia/9)) -> 78.684517 | AE35: =IF(I35="contrato",0,$N$11*$Q$11*$K$11) -> 0 | AF35: =IF(I35="contrato",0,$N$12*$Q$12*$K$12) -> 0 | AG35: =IF(I35="contrato",0,$N$13*$Q$13*$K$13) -> 0 | AH35: =IF(I35="contrato",0,$N$14*$Q$14*$K$14) -> 0 | AI35: =IF(I35="contrato",0,$N$14*$Q$15*$K$15) -> 0 | AJ35: =IF(I35="contrato",0,$N$14*$Q$16*$K$16) -> 0 | AL35: =IF(I35="contrato",0,ROUNDUP((M35/220)*(1+$AA$14)*(1+hora_extra_dias_úteis),2)) -> 0 | AM35: =IF(I35="contrato",0,ROUNDUP((M35/220)*(1+$AA$14)*(1+hora_extra_sábados),2)) -> 0 | AN35: =IF(I35="contrato",0,ROUNDUP((M35/220)*(1+$AA$14)*(1+hora_extra_domingos),2)) -> 0 | AO35: =IF(I35="contrato",0,ROUNDUP(AL35*(1+adicional_noturno),2)) -> 0 | AP35: =IF(I35="contrato",0,ROUNDUP(AM35*(1+adicional_noturno),2)) -> 0 | AQ35: =IF(I35="contrato",0,ROUNDUP(AN35*(1+adicional_noturno),2)) -> 0 | AS35: =IF(H35="Coordenação",0,L35*J35) -> 0 | AT35: =IF(H35="Coordenação",L35*J35,0) -> 0 | AV35: =IF(I35="CLT",IF(L35=0,0,P35*220+N35),(P35*220+N35+(O35/meses_obra))) -> 20074.76 | AW35: =IF(I35="CLT",IF(L35=0,0,((P35*220)+(AE35*AL35)+(AF35*AM35)+(AG35*AN35)+(AH35*AO35)+(AI35*AP35)+(AJ35*AQ35)+N35)),AV35) -> 20074.76 | AX35: =AV35*L35*J35 -> 0
A36: 2 | D36: 2.02 | E36: Engenheiro - Planejamento I | H36: Coordenação | I36: Contrato | L36: =meses_obra -> 8 | M36: 10000 | N36: 0 | O36: =IF(I36="CLT","N/A",(L36*(M36/12)*2)) -> 13333.333 | P36: =IF(I36="contrato",AB36,AB36) -> 47.443182 | Q36: =AE36+AF36 -> 0 | R36: =AG36 -> 0 | S36: =Q36*AL36 -> 0 | T36: =R36*AN36 -> 0 | U36: =AW36*L36*J36 -> 0 | Z36: =IF(I36="CLT",(M36/220)*(1+encargos_mensalista),(M36/220)) -> 45.454545 | AA36: =Z36*(1+K36) -> 45.454545 | AB36: =AA36*(1+((incidência_do_dissídio/meses_obra)*dissídio_coletivo)) -> 47.443182 | AC36: =AB36*(1+(ociosidade_por_dia/9)) -> 47.443182 | AE36: =IF(I36="contrato",0,$N$11*$Q$11*$K$11) -> 0 | AF36: =IF(I36="contrato",0,$N$12*$Q$12*$K$12) -> 0 | AG36: =IF(I36="contrato",0,$N$13*$Q$13*$K$13) -> 0 | AH36: =IF(I36="contrato",0,$N$14*$Q$14*$K$14) -> 0 | AI36: =IF(I36="contrato",0,$N$14*$Q$15*$K$15) -> 0 | AJ36: =IF(I36="contrato",0,$N$14*$Q$16*$K$16) -> 0 | AL36: =IF(I36="contrato",0,ROUNDUP((M36/220)*(1+$AA$14)*(1+hora_extra_dias_úteis),2)) -> 0 | AM36: =IF(I36="contrato",0,ROUNDUP((M36/220)*(1+$AA$14)*(1+hora_extra_sábados),2)) -> 0 | AN36: =IF(I36="contrato",0,ROUNDUP((M36/220)*(1+$AA$14)*(1+hora_extra_domingos),2)) -> 0 | AO36: =IF(I36="contrato",0,ROUNDUP(AL36*(1+adicional_noturno),2)) -> 0 | AP36: =IF(I36="contrato",0,ROUNDUP(AM36*(1+adicional_noturno),2)) -> 0 | AQ36: =IF(I36="contrato",0,ROUNDUP(AN36*(1+adicional_noturno),2)) -> 0 | AS36: =IF(H36="Coordenação",0,L36*J36) -> 0 | AT36: =IF(H36="Coordenação",L36*J36,0) -> 0 | AV36: =IF(I36="CLT",IF(L36=0,0,P36*220+N36),(P36*220+N36+(O36/meses_obra))) -> 12104.167 | AW36: =IF(I36="CLT",IF(L36=0,0,((P36*220)+(AE36*AL36)+(AF36*AM36)+(AG36*AN36)+(AH36*AO36)+(AI36*AP36)+(AJ36*AQ36)+N36)),AV36) -> 12104.167 | AX36: =AV36*L36*J36 -> 0
A37: 2 | D37: 2.03 | E37: Engenheiro - Senior | H37: Coordenação | I37: Contrato | L37: =meses_obra -> 8 | M37: 10000 | N37: 0 | O37: =IF(I37="CLT","N/A",(L37*(M37/12)*2)) -> 13333.333 | P37: =IF(I37="contrato",AB37,AB37) -> 47.443182 | Q37: =AE37+AF37 -> 0 | R37: =AG37 -> 0 | S37: =Q37*AL37 -> 0 | T37: =R37*AN37 -> 0 | U37: =AW37*L37*J37 -> 0 | Z37: =IF(I37="CLT",(M37/220)*(1+encargos_mensalista),(M37/220)) -> 45.454545 | AA37: =Z37*(1+K37) -> 45.454545 | AB37: =AA37*(1+((incidência_do_dissídio/meses_obra)*dissídio_coletivo)) -> 47.443182 | AC37: =AB37*(1+(ociosidade_por_dia/9)) -> 47.443182 | AE37: =IF(I37="contrato",0,$N$11*$Q$11*$K$11) -> 0 | AF37: =IF(I37="contrato",0,$N$12*$Q$12*$K$12) -> 0 | AG37: =IF(I37="contrato",0,$N$13*$Q$13*$K$13) -> 0 | AH37: =IF(I37="contrato",0,$N$14*$Q$14*$K$14) -> 0 | AI37: =IF(I37="contrato",0,$N$14*$Q$15*$K$15) -> 0 | AJ37: =IF(I37="contrato",0,$N$14*$Q$16*$K$16) -> 0 | AL37: =IF(I37="contrato",0,ROUNDUP((M37/220)*(1+$AA$14)*(1+hora_extra_dias_úteis),2)) -> 0 | AM37: =IF(I37="contrato",0,ROUNDUP((M37/220)*(1+$AA$14)*(1+hora_extra_sábados),2)) -> 0 | AN37: =IF(I37="contrato",0,ROUNDUP((M37/220)*(1+$AA$14)*(1+hora_extra_domingos),2)) -> 0 | AO37: =IF(I37="contrato",0,ROUNDUP(AL37*(1+adicional_noturno),2)) -> 0 | AP37: =IF(I37="contrato",0,ROUNDUP(AM37*(1+adicional_noturno),2)) -> 0 | AQ37: =IF(I37="contrato",0,ROUNDUP(AN37*(1+adicional_noturno),2)) -> 0 | AS37: =IF(H37="Coordenação",0,L37*J37) -> 0 | AT37: =IF(H37="Coordenação",L37*J37,0) -> 0 | AV37: =IF(I37="CLT",IF(L37=0,0,P37*220+N37),(P37*220+N37+(O37/meses_obra))) -> 12104.167 | AW37: =IF(I37="CLT",IF(L37=0,0,((P37*220)+(AE37*AL37)+(AF37*AM37)+(AG37*AN37)+(AH37*AO37)+(AI37*AP37)+(AJ37*AQ37)+N37)),AV37) -> 12104.167 | AX37: =AV37*L37*J37 -> 0
A38: 2 | D38: 2.04 | E38: Engenheiro - Produção II | H38: Coordenação | I38: Contrato | J38: 1 | L38: =meses_obra -> 8 | M38: 8000 | N38: 0 | O38: =IF(I38="CLT","N/A",(L38*(M38/12)*2)) -> 10666.667 | P38: =IF(I38="contrato",AB38,AB38) -> 37.954545 | Q38: =AE38+AF38 -> 0 | R38: =AG38 -> 0 | S38: =Q38*AL38 -> 0 | T38: =R38*AN38 -> 0 | U38: =AW38*L38*J38 -> 77466.667 | Z38: =IF(I38="CLT",(M38/220)*(1+encargos_mensalista),(M38/220)) -> 36.363636 | AA38: =Z38*(1+K38) -> 36.363636 | AB38: =AA38*(1+((incidência_do_dissídio/meses_obra)*dissídio_coletivo)) -> 37.954545 | AC38: =AB38*(1+(ociosidade_por_dia/9)) -> 37.954545 | AE38: =IF(I38="contrato",0,$N$11*$Q$11*$K$11) -> 0 | AF38: =IF(I38="contrato",0,$N$12*$Q$12*$K$12) -> 0 | AG38: =IF(I38="contrato",0,$N$13*$Q$13*$K$13) -> 0 | AH38: =IF(I38="contrato",0,$N$14*$Q$14*$K$14) -> 0 | AI38: =IF(I38="contrato",0,$N$14*$Q$15*$K$15) -> 0 | AJ38: =IF(I38="contrato",0,$N$14*$Q$16*$K$16) -> 0 | AL38: =IF(I38="contrato",0,ROUNDUP((M38/220)*(1+$AA$14)*(1+hora_extra_dias_úteis),2)) -> 0 | AM38: =IF(I38="contrato",0,ROUNDUP((M38/220)*(1+$AA$14)*(1+hora_extra_sábados),2)) -> 0 | AN38: =IF(I38="contrato",0,ROUNDUP((M38/220)*(1+$AA$14)*(1+hora_extra_domingos),2)) -> 0 | AO38: =IF(I38="contrato",0,ROUNDUP(AL38*(1+adicional_noturno),2)) -> 0 | AP38: =IF(I38="contrato",0,ROUNDUP(AM38*(1+adicional_noturno),2)) -> 0 | AQ38: =IF(I38="contrato",0,ROUNDUP(AN38*(1+adicional_noturno),2)) -> 0 | AS38: =IF(H38="Coordenação",0,L38*J38) -> 0 | AT38: =IF(H38="Coordenação",L38*J38,0) -> 8 | AV38: =IF(I38="CLT",IF(L38=0,0,P38*220+N38),(P38*220+N38+(O38/meses_obra))) -> 9683.3333 | AW38: =IF(I38="CLT",IF(L38=0,0,((P38*220)+(AE38*AL38)+(AF38*AM38)+(AG38*AN38)+(AH38*AO38)+(AI38*AP38)+(AJ38*AQ38)+N38)),AV38) -> 9683.3333 | AX38: =AV38*L38*J38 -> 77466.667
A39: 2 | D39: 2.05 | E39: Engenheiro - Produção III | H39: Coordenação | I39: Contrato | L39: =meses_obra -> 8 | M39: 6000 | N39: 0 | O39: =IF(I39="CLT","N/A",(L39*(M39/12)*2)) -> 8000 | P39: =IF(I39="contrato",AB39,AB39) -> 28.465909 | Q39: =AE39+AF39 -> 0 | R39: =AG39 -> 0 | S39: =Q39*AL39 -> 0 | T39: =R39*AN39 -> 0 | U39: =AW39*L39*J39 -> 0 | Z39: =IF(I39="CLT",(M39/220)*(1+encargos_mensalista),(M39/220)) -> 27.272727 | AA39: =Z39*(1+K39) -> 27.272727 | AB39: =AA39*(1+((incidência_do_dissídio/meses_obra)*dissídio_coletivo)) -> 28.465909 | AC39: =AB39*(1+(ociosidade_por_dia/9)) -> 28.465909 | AE39: =IF(I39="contrato",0,$N$11*$Q$11*$K$11) -> 0 | AF39: =IF(I39="contrato",0,$N$12*$Q$12*$K$12) -> 0 | AG39: =IF(I39="contrato",0,$N$13*$Q$13*$K$13) -> 0 | AH39: =IF(I39="contrato",0,$N$14*$Q$14*$K$14) -> 0 | AI39: =IF(I39="contrato",0,$N$14*$Q$15*$K$15) -> 0 | AJ39: =IF(I39="contrato",0,$N$14*$Q$16*$K$16) -> 0 | AL39: =IF(I39="contrato",0,ROUNDUP((M39/220)*(1+$AA$14)*(1+hora_extra_dias_úteis),2)) -> 0 | AM39: =IF(I39="contrato",0,ROUNDUP((M39/220)*(1+$AA$14)*(1+hora_extra_sábados),2)) -> 0 | AN39: =IF(I39="contrato",0,ROUNDUP((M39/220)*(1+$AA$14)*(1+hora_extra_domingos),2)) -> 0 | AO39: =IF(I39="contrato",0,ROUNDUP(AL39*(1+adicional_noturno),2)) -> 0 | AP39: =IF(I39="contrato",0,ROUNDUP(AM39*(1+adicional_noturno),2)) -> 0 | AQ39: =IF(I39="contrato",0,ROUNDUP(AN39*(1+adicional_noturno),2)) -> 0 | AS39: =IF(H39="Coordenação",0,L39*J39) -> 0 | AT39: =IF(H39="Coordenação",L39*J39,0) -> 0 | AV39: =IF(I39="CLT",IF(L39=0,0,P39*220+N39),(P39*220+N39+(O39/meses_obra))) -> 7262.5 | AW39: =IF(I39="CLT",IF(L39=0,0,((P39*220)+(AE39*AL39)+(AF39*AM39)+(AG39*AN39)+(AH39*AO39)+(AI39*AP39)+(AJ39*AQ39)+N39)),AV39) -> 7262.5 | AX39: =AV39*L39*J39 -> 0
A40: 2 | D40: 2.06 | E40: Engenheiro - Qualidade | H40: Coordenação | I40: Contrato | L40: =meses_obra -> 8 | M40: 16050 | N40: 0 | O40: =IF(I40="CLT","N/A",(L40*(M40/12)*2)) -> 21400 | P40: =IF(I40="contrato",AB40,AB40) -> 76.146307 | Q40: =AE40+AF40 -> 0 | R40: =AG40 -> 0 | S40: =Q40*AL40 -> 0 | T40: =R40*AN40 -> 0 | U40: =AW40*L40*J40 -> 0 | Z40: =IF(I40="CLT",(M40/220)*(1+encargos_mensalista),(M40/220)) -> 72.954545 | AA40: =Z40*(1+K40) -> 72.954545 | AB40: =AA40*(1+((incidência_do_dissídio/meses_obra)*dissídio_coletivo)) -> 76.146307 | AC40: =AB40*(1+(ociosidade_por_dia/9)) -> 76.146307 | AE40: =IF(I40="contrato",0,$N$11*$Q$11*$K$11) -> 0 | AF40: =IF(I40="contrato",0,$N$12*$Q$12*$K$12) -> 0 | AG40: =IF(I40="contrato",0,$N$13*$Q$13*$K$13) -> 0 | AH40: =IF(I40="contrato",0,$N$14*$Q$14*$K$14) -> 0 | AI40: =IF(I40="contrato",0,$N$14*$Q$15*$K$15) -> 0 | AJ40: =IF(I40="contrato",0,$N$14*$Q$16*$K$16) -> 0 | AL40: =IF(I40="contrato",0,ROUNDUP((M40/220)*(1+$AA$14)*(1+hora_extra_dias_úteis),2)) -> 0 | AM40: =IF(I40="contrato",0,ROUNDUP((M40/220)*(1+$AA$14)*(1+hora_extra_sábados),2)) -> 0 | AN40: =IF(I40="contrato",0,ROUNDUP((M40/220)*(1+$AA$14)*(1+hora_extra_domingos),2)) -> 0 | AO40: =IF(I40="contrato",0,ROUNDUP(AL40*(1+adicional_noturno),2)) -> 0 | AP40: =IF(I40="contrato",0,ROUNDUP(AM40*(1+adicional_noturno),2)) -> 0 | AQ40: =IF(I40="contrato",0,ROUNDUP(AN40*(1+adicional_noturno),2)) -> 0 | AS40: =IF(H40="Coordenação",0,L40*J40) -> 0 | AT40: =IF(H40="Coordenação",L40*J40,0) -> 0 | AV40: =IF(I40="CLT",IF(L40=0,0,P40*220+N40),(P40*220+N40+(O40/meses_obra))) -> 19427.188 | AW40: =IF(I40="CLT",IF(L40=0,0,((P40*220)+(AE40*AL40)+(AF40*AM40)+(AG40*AN40)+(AH40*AO40)+(AI40*AP40)+(AJ40*AQ40)+N40)),AV40) -> 19427.188 | AX40: =AV40*L40*J40 -> 0
A41: 2 | D41: 2.07 | E41: Engenheiro / Arquiteto - Coordenação de Projetos | H41: Coordenação | I41: Contrato | L41: =meses_obra -> 8 | M41: 16050 | N41: 0 | O41: =IF(I41="CLT","N/A",(L41*(M41/12)*2)) -> 21400 | P41: =IF(I41="contrato",AB41,AB41) -> 76.146307 | Q41: =AE41+AF41 -> 0 | R41: =AG41 -> 0 | S41: =Q41*AL41 -> 0 | T41: =R41*AN41 -> 0 | U41: =AW41*L41*J41 -> 0 | Z41: =IF(I41="CLT",(M41/220)*(1+encargos_mensalista),(M41/220)) -> 72.954545 | AA41: =Z41*(1+K41) -> 72.954545 | AB41: =AA41*(1+((incidência_do_dissídio/meses_obra)*dissídio_coletivo)) -> 76.146307 | AC41: =AB41*(1+(ociosidade_por_dia/9)) -> 76.146307 | AE41: =IF(I41="contrato",0,$N$11*$Q$11*$K$11) -> 0 | AF41: =IF(I41="contrato",0,$N$12*$Q$12*$K$12) -> 0 | AG41: =IF(I41="contrato",0,$N$13*$Q$13*$K$13) -> 0 | AH41: =IF(I41="contrato",0,$N$14*$Q$14*$K$14) -> 0 | AI41: =IF(I41="contrato",0,$N$14*$Q$15*$K$15) -> 0 | AJ41: =IF(I41="contrato",0,$N$14*$Q$16*$K$16) -> 0 | AL41: =IF(I41="contrato",0,ROUNDUP((M41/220)*(1+$AA$14)*(1+hora_extra_dias_úteis),2)) -> 0 | AM41: =IF(I41="contrato",0,ROUNDUP((M41/220)*(1+$AA$14)*(1+hora_extra_sábados),2)) -> 0 | AN41: =IF(I41="contrato",0,ROUNDUP((M41/220)*(1+$AA$14)*(1+hora_extra_domingos),2)) -> 0 | AO41: =IF(I41="contrato",0,ROUNDUP(AL41*(1+adicional_noturno),2)) -> 0 | AP41: =IF(I41="contrato",0,ROUNDUP(AM41*(1+adicional_noturno),2)) -> 0 | AQ41: =IF(I41="contrato",0,ROUNDUP(AN41*(1+adicional_noturno),2)) -> 0 | AS41: =IF(H41="Coordenação",0,L41*J41) -> 0 | AT41: =IF(H41="Coordenação",L41*J41,0) -> 0 | AV41: =IF(I41="CLT",IF(L41=0,0,P41*220+N41),(P41*220+N41+(O41/meses_obra))) -> 19427.188 | AW41: =IF(I41="CLT",IF(L41=0,0,((P41*220)+(AE41*AL41)+(AF41*AM41)+(AG41*AN41)+(AH41*AO41)+(AI41*AP41)+(AJ41*AQ41)+N41)),AV41) -> 19427.188 | AX41: =AV41*L41*J41 -> 0
A42: 2 | D42: 2.08 | E42: Tecnológo Civil - Produção | H42: Supervisão | I42: Contrato | L42: =meses_obra -> 8 | M42: 12840 | N42: 0 | O42: =IF(I42="CLT","N/A",(L42*(M42/12)*2)) -> 17120 | P42: =IF(I42="contrato",AB42,AB42) -> 60.917045 | Q42: =AE42+AF42 -> 0 | R42: =AG42 -> 0 | S42: =Q42*AL42 -> 0 | T42: =R42*AN42 -> 0 | U42: =AW42*L42*J42 -> 0 | Z42: =IF(I42="CLT",(M42/220)*(1+encargos_mensalista),(M42/220)) -> 58.363636 | AA42: =Z42*(1+K42) -> 58.363636 | AB42: =AA42*(1+((incidência_do_dissídio/meses_obra)*dissídio_coletivo)) -> 60.917045 | AC42: =AB42*(1+(ociosidade_por_dia/9)) -> 60.917045 | AE42: =IF(I42="contrato",0,$N$11*$Q$11*$K$11) -> 0 | AF42: =IF(I42="contrato",0,$N$12*$Q$12*$K$12) -> 0 | AG42: =IF(I42="contrato",0,$N$13*$Q$13*$K$13) -> 0 | AH42: =IF(I42="contrato",0,$N$14*$Q$14*$K$14) -> 0 | AI42: =IF(I42="contrato",0,$N$14*$Q$15*$K$15) -> 0 | AJ42: =IF(I42="contrato",0,$N$14*$Q$16*$K$16) -> 0 | AL42: =IF(I42="contrato",0,ROUNDUP((M42/220)*(1+$AA$14)*(1+hora_extra_dias_úteis),2)) -> 0 | AM42: =IF(I42="contrato",0,ROUNDUP((M42/220)*(1+$AA$14)*(1+hora_extra_sábados),2)) -> 0 | AN42: =IF(I42="contrato",0,ROUNDUP((M42/220)*(1+$AA$14)*(1+hora_extra_domingos),2)) -> 0 | AO42: =IF(I42="contrato",0,ROUNDUP(AL42*(1+adicional_noturno),2)) -> 0 | AP42: =IF(I42="contrato",0,ROUNDUP(AM42*(1+adicional_noturno),2)) -> 0 | AQ42: =IF(I42="contrato",0,ROUNDUP(AN42*(1+adicional_noturno),2)) -> 0 | AS42: =IF(H42="Coordenação",0,L42*J42) -> 0 | AT42: =IF(H42="Coordenação",L42*J42,0) -> 0 | AV42: =IF(I42="CLT",IF(L42=0,0,P42*220+N42),(P42*220+N42+(O42/meses_obra))) -> 15541.75 | AW42: =IF(I42="CLT",IF(L42=0,0,((P42*220)+(AE42*AL42)+(AF42*AM42)+(AG42*AN42)+(AH42*AO42)+(AI42*AP42)+(AJ42*AQ42)+N42)),AV42) -> 15541.75 | AX42: =AV42*L42*J42 -> 0
A43: 2 | D43: 2.09 | E43: Tecnológo Civil - Planejamento | H43: Supervisão | I43: Contrato | L43: =meses_obra -> 8 | M43: 12840 | N43: 0 | O43: =IF(I43="CLT","N/A",(L43*(M43/12)*2)) -> 17120 | P43: =IF(I43="contrato",AB43,AB43) -> 60.917045 | Q43: =AE43+AF43 -> 0 | R43: =AG43 -> 0 | S43: =Q43*AL43 -> 0 | T43: =R43*AN43 -> 0 | U43: =AW43*L43*J43 -> 0 | Z43: =IF(I43="CLT",(M43/220)*(1+encargos_mensalista),(M43/220)) -> 58.363636 | AA43: =Z43*(1+K43) -> 58.363636 | AB43: =AA43*(1+((incidência_do_dissídio/meses_obra)*dissídio_coletivo)) -> 60.917045 | AC43: =AB43*(1+(ociosidade_por_dia/9)) -> 60.917045 | AE43: =IF(I43="contrato",0,$N$11*$Q$11*$K$11) -> 0 | AF43: =IF(I43="contrato",0,$N$12*$Q$12*$K$12) -> 0 | AG43: =IF(I43="contrato",0,$N$13*$Q$13*$K$13) -> 0 | AH43: =IF(I43="contrato",0,$N$14*$Q$14*$K$14) -> 0 | AI43: =IF(I43="contrato",0,$N$14*$Q$15*$K$15) -> 0 | AJ43: =IF(I43="contrato",0,$N$14*$Q$16*$K$16) -> 0 | AL43: =IF(I43="contrato",0,ROUNDUP((M43/220)*(1+$AA$14)*(1+hora_extra_dias_úteis),2)) -> 0 | AM43: =IF(I43="contrato",0,ROUNDUP((M43/220)*(1+$AA$14)*(1+hora_extra_sábados),2)) -> 0 | AN43: =IF(I43="contrato",0,ROUNDUP((M43/220)*(1+$AA$14)*(1+hora_extra_domingos),2)) -> 0 | AO43: =IF(I43="contrato",0,ROUNDUP(AL43*(1+adicional_noturno),2)) -> 0 | AP43: =IF(I43="contrato",0,ROUNDUP(AM43*(1+adicional_noturno),2)) -> 0 | AQ43: =IF(I43="contrato",0,ROUNDUP(AN43*(1+adicional_noturno),2)) -> 0 | AS43: =IF(H43="Coordenação",0,L43*J43) -> 0 | AT43: =IF(H43="Coordenação",L43*J43,0) -> 0 | AV43: =IF(I43="CLT",IF(L43=0,0,P43*220+N43),(P43*220+N43+(O43/meses_obra))) -> 15541.75 | AW43: =IF(I43="CLT",IF(L43=0,0,((P43*220)+(AE43*AL43)+(AF43*AM43)+(AG43*AN43)+(AH43*AO43)+(AI43*AP43)+(AJ43*AQ43)+N43)),AV43) -> 15541.75 | AX43: =AV43*L43*J43 -> 0
A44: 2 | D44: 2.10 | E44: Tecnológo Civil - Qualidade | H44: Supervisão | I44: Contrato | L44: =meses_obra -> 8 | M44: 12840 | N44: 0 | O44: =IF(I44="CLT","N/A",(L44*(M44/12)*2)) -> 17120 | P44: =IF(I44="contrato",AB44,AB44) -> 60.917045 | Q44: =AE44+AF44 -> 0 | R44: =AG44 -> 0 | S44: =Q44*AL44 -> 0 | T44: =R44*AN44 -> 0 | U44: =AW44*L44*J44 -> 0 | Z44: =IF(I44="CLT",(M44/220)*(1+encargos_mensalista),(M44/220)) -> 58.363636 | AA44: =Z44*(1+K44) -> 58.363636 | AB44: =AA44*(1+((incidência_do_dissídio/meses_obra)*dissídio_coletivo)) -> 60.917045 | AC44: =AB44*(1+(ociosidade_por_dia/9)) -> 60.917045 | AE44: =IF(I44="contrato",0,$N$11*$Q$11*$K$11) -> 0 | AF44: =IF(I44="contrato",0,$N$12*$Q$12*$K$12) -> 0 | AG44: =IF(I44="contrato",0,$N$13*$Q$13*$K$13) -> 0 | AH44: =IF(I44="contrato",0,$N$14*$Q$14*$K$14) -> 0 | AI44: =IF(I44="contrato",0,$N$14*$Q$15*$K$15) -> 0 | AJ44: =IF(I44="contrato",0,$N$14*$Q$16*$K$16) -> 0 | AL44: =IF(I44="contrato",0,ROUNDUP((M44/220)*(1+$AA$14)*(1+hora_extra_dias_úteis),2)) -> 0 | AM44: =IF(I44="contrato",0,ROUNDUP((M44/220)*(1+$AA$14)*(1+hora_extra_sábados),2)) -> 0 | AN44: =IF(I44="contrato",0,ROUNDUP((M44/220)*(1+$AA$14)*(1+hora_extra_domingos),2)) -> 0 | AO44: =IF(I44="contrato",0,ROUNDUP(AL44*(1+adicional_noturno),2)) -> 0 | AP44: =IF(I44="contrato",0,ROUNDUP(AM44*(1+adicional_noturno),2)) -> 0 | AQ44: =IF(I44="contrato",0,ROUNDUP(AN44*(1+adicional_noturno),2)) -> 0 | AS44: =IF(H44="Coordenação",0,L44*J44) -> 0 | AT44: =IF(H44="Coordenação",L44*J44,0) -> 0 | AV44: =IF(I44="CLT",IF(L44=0,0,P44*220+N44),(P44*220+N44+(O44/meses_obra))) -> 15541.75 | AW44: =IF(I44="CLT",IF(L44=0,0,((P44*220)+(AE44*AL44)+(AF44*AM44)+(AG44*AN44)+(AH44*AO44)+(AI44*AP44)+(AJ44*AQ44)+N44)),AV44) -> 15541.75 | AX44: =AV44*L44*J44 -> 0
A45: 2 | D45: 2.11 | E45: Técnico de Edificações - Produção | H45: Supervisão | I45: Contrato | L45: =meses_obra -> 8 | M45: 4000 | N45: 0 | O45: =IF(I45="CLT","N/A",(L45*(M45/12)*2)) -> 5333.3333 | P45: =IF(I45="contrato",AB45,AB45) -> 18.977273 | Q45: =AE45+AF45 -> 0 | R45: =AG45 -> 0 | S45: =Q45*AL45 -> 0 | T45: =R45*AN45 -> 0 | U45: =AW45*L45*J45 -> 0 | Z45: =IF(I45="CLT",(M45/220)*(1+encargos_mensalista),(M45/220)) -> 18.181818 | AA45: =Z45*(1+K45) -> 18.181818 | AB45: =AA45*(1+((incidência_do_dissídio/meses_obra)*dissídio_coletivo)) -> 18.977273 | AC45: =AB45*(1+(ociosidade_por_dia/9)) -> 18.977273 | AE45: =IF(I45="contrato",0,$N$11*$Q$11*$K$11) -> 0 | AF45: =IF(I45="contrato",0,$N$12*$Q$12*$K$12) -> 0 | AG45: =IF(I45="contrato",0,$N$13*$Q$13*$K$13) -> 0 | AH45: =IF(I45="contrato",0,$N$14*$Q$14*$K$14) -> 0 | AI45: =IF(I45="contrato",0,$N$14*$Q$15*$K$15) -> 0 | AJ45: =IF(I45="contrato",0,$N$14*$Q$16*$K$16) -> 0 | AL45: =IF(I45="contrato",0,ROUNDUP((M45/220)*(1+$AA$14)*(1+hora_extra_dias_úteis),2)) -> 0 | AM45: =IF(I45="contrato",0,ROUNDUP((M45/220)*(1+$AA$14)*(1+hora_extra_sábados),2)) -> 0 | AN45: =IF(I45="contrato",0,ROUNDUP((M45/220)*(1+$AA$14)*(1+hora_extra_domingos),2)) -> 0 | AO45: =IF(I45="contrato",0,ROUNDUP(AL45*(1+adicional_noturno),2)) -> 0 | AP45: =IF(I45="contrato",0,ROUNDUP(AM45*(1+adicional_noturno),2)) -> 0 | AQ45: =IF(I45="contrato",0,ROUNDUP(AN45*(1+adicional_noturno),2)) -> 0 | AS45: =IF(H45="Coordenação",0,L45*J45) -> 0 | AT45: =IF(H45="Coordenação",L45*J45,0) -> 0 | AV45: =IF(I45="CLT",IF(L45=0,0,P45*220+N45),(P45*220+N45+(O45/meses_obra))) -> 4841.6667 | AW45: =IF(I45="CLT",IF(L45=0,0,((P45*220)+(AE45*AL45)+(AF45*AM45)+(AG45*AN45)+(AH45*AO45)+(AI45*AP45)+(AJ45*AQ45)+N45)),AV45) -> 4841.6667 | AX45: =AV45*L45*J45 -> 0
A46: 2 | D46: 2.12 | E46: Técnico de Edificações - Planejamento | H46: Supervisão | I46: CLT | L46: =meses_obra -> 8 | M46: 5885 | N46: 0 | O46: =IF(I46="CLT","N/A",(L46*(M46/12)*2)) -> N/A | P46: =IF(I46="contrato",AB46,AB46) -> 59.383065 | Q46: =AE46+AF46 -> 0 | R46: =AG46 -> 0 | S46: =Q46*AL46 -> 0 | T46: =R46*AN46 -> 0 | U46: =AW46*L46*J46 -> 0 | Z46: =IF(I46="CLT",(M46/220)*(1+encargos_mensalista),(M46/220)) -> 56.893955 | AA46: =Z46*(1+K46) -> 56.893955 | AB46: =AA46*(1+((incidência_do_dissídio/meses_obra)*dissídio_coletivo)) -> 59.383065 | AC46: =AB46*(1+(ociosidade_por_dia/9)) -> 59.383065 | AE46: =IF(I46="contrato",0,$N$11*$Q$11*$K$11) -> 0 | AF46: =IF(I46="contrato",0,$N$12*$Q$12*$K$12) -> 0 | AG46: =IF(I46="contrato",0,$N$13*$Q$13*$K$13) -> 0 | AH46: =IF(I46="contrato",0,$N$14*$Q$14*$K$14) -> 0 | AI46: =IF(I46="contrato",0,$N$14*$Q$15*$K$15) -> 0 | AJ46: =IF(I46="contrato",0,$N$14*$Q$16*$K$16) -> 0 | AL46: =IF(I46="contrato",0,ROUNDUP((M46/220)*(1+$AA$14)*(1+hora_extra_dias_úteis),2)) -> 63.96 | AM46: =IF(I46="contrato",0,ROUNDUP((M46/220)*(1+$AA$14)*(1+hora_extra_sábados),2)) -> 63.96 | AN46: =IF(I46="contrato",0,ROUNDUP((M46/220)*(1+$AA$14)*(1+hora_extra_domingos),2)) -> 79.95 | AO46: =IF(I46="contrato",0,ROUNDUP(AL46*(1+adicional_noturno),2)) -> 76.76 | AP46: =IF(I46="contrato",0,ROUNDUP(AM46*(1+adicional_noturno),2)) -> 76.76 | AQ46: =IF(I46="contrato",0,ROUNDUP(AN46*(1+adicional_noturno),2)) -> 95.94 | AS46: =IF(H46="Coordenação",0,L46*J46) -> 0 | AT46: =IF(H46="Coordenação",L46*J46,0) -> 0 | AV46: =IF(I46="CLT",IF(L46=0,0,P46*220+N46),(P46*220+N46+(O46/meses_obra))) -> 13064.274 | AW46: =IF(I46="CLT",IF(L46=0,0,((P46*220)+(AE46*AL46)+(AF46*AM46)+(AG46*AN46)+(AH46*AO46)+(AI46*AP46)+(AJ46*AQ46)+N46)),AV46) -> 13064.274 | AX46: =AV46*L46*J46 -> 0
A47: 2 | D47: 2.13 | E47: Técnico de Edificações - Qualidade | H47: Supervisão | I47: CLT | L47: =meses_obra -> 8 | M47: 5885 | N47: 0 | O47: =IF(I47="CLT","N/A",(L47*(M47/12)*2)) -> N/A | P47: =IF(I47="contrato",AB47,AB47) -> 59.383065 | Q47: =AE47+AF47 -> 0 | R47: =AG47 -> 0 | S47: =Q47*AL47 -> 0 | T47: =R47*AN47 -> 0 | U47: =AW47*L47*J47 -> 0 | Z47: =IF(I47="CLT",(M47/220)*(1+encargos_mensalista),(M47/220)) -> 56.893955 | AA47: =Z47*(1+K47) -> 56.893955 | AB47: =AA47*(1+((incidência_do_dissídio/meses_obra)*dissídio_coletivo)) -> 59.383065 | AC47: =AB47*(1+(ociosidade_por_dia/9)) -> 59.383065 | AE47: =IF(I47="contrato",0,$N$11*$Q$11*$K$11) -> 0 | AF47: =IF(I47="contrato",0,$N$12*$Q$12*$K$12) -> 0 | AG47: =IF(I47="contrato",0,$N$13*$Q$13*$K$13) -> 0 | AH47: =IF(I47="contrato",0,$N$14*$Q$14*$K$14) -> 0 | AI47: =IF(I47="contrato",0,$N$14*$Q$15*$K$15) -> 0 | AJ47: =IF(I47="contrato",0,$N$14*$Q$16*$K$16) -> 0 | AL47: =IF(I47="contrato",0,ROUNDUP((M47/220)*(1+$AA$14)*(1+hora_extra_dias_úteis),2)) -> 63.96 | AM47: =IF(I47="contrato",0,ROUNDUP((M47/220)*(1+$AA$14)*(1+hora_extra_sábados),2)) -> 63.96 | AN47: =IF(I47="contrato",0,ROUNDUP((M47/220)*(1+$AA$14)*(1+hora_extra_domingos),2)) -> 79.95 | AO47: =IF(I47="contrato",0,ROUNDUP(AL47*(1+adicional_noturno),2)) -> 76.76 | AP47: =IF(I47="contrato",0,ROUNDUP(AM47*(1+adicional_noturno),2)) -> 76.76 | AQ47: =IF(I47="contrato",0,ROUNDUP(AN47*(1+adicional_noturno),2)) -> 95.94 | AS47: =IF(H47="Coordenação",0,L47*J47) -> 0 | AT47: =IF(H47="Coordenação",L47*J47,0) -> 0 | AV47: =IF(I47="CLT",IF(L47=0,0,P47*220+N47),(P47*220+N47+(O47/meses_obra))) -> 13064.274 | AW47: =IF(I47="CLT",IF(L47=0,0,((P47*220)+(AE47*AL47)+(AF47*AM47)+(AG47*AN47)+(AH47*AO47)+(AI47*AP47)+(AJ47*AQ47)+N47)),AV47) -> 13064.274 | AX47: =AV47*L47*J47 -> 0
A48: 2 | D48: 2.14 | E48: Mestre de Obra I | H48: Supervisão | I48: Contrato | J48: 1 | L48: =meses_obra -> 8 | M48: 4500 | N48: 0 | O48: =IF(I48="CLT","N/A",(L48*(M48/12)*2)) -> 6000 | P48: =IF(I48="contrato",AB48,AB48) -> 21.349432 | Q48: =AE48+AF48 -> 0 | R48: =AG48 -> 0 | S48: =Q48*AL48 -> 0 | T48: =R48*AN48 -> 0 | U48: =AW48*L48*J48 -> 43575 | Z48: =IF(I48="CLT",(M48/220)*(1+encargos_mensalista),(M48/220)) -> 20.454545 | AA48: =Z48*(1+K48) -> 20.454545 | AB48: =AA48*(1+((incidência_do_dissídio/meses_obra)*dissídio_coletivo)) -> 21.349432 | AC48: =AB48*(1+(ociosidade_por_dia/9)) -> 21.349432 | AE48: =IF(I48="contrato",0,$N$11*$Q$11*$K$11) -> 0 | AF48: =IF(I48="contrato",0,$N$12*$Q$12*$K$12) -> 0 | AG48: =IF(I48="contrato",0,$N$13*$Q$13*$K$13) -> 0 | AH48: =IF(I48="contrato",0,$N$14*$Q$14*$K$14) -> 0 | AI48: =IF(I48="contrato",0,$N$14*$Q$15*$K$15) -> 0 | AJ48: =IF(I48="contrato",0,$N$14*$Q$16*$K$16) -> 0 | AL48: =IF(I48="contrato",0,ROUNDUP((M48/220)*(1+$AA$14)*(1+hora_extra_dias_úteis),2)) -> 0 | AM48: =IF(I48="contrato",0,ROUNDUP((M48/220)*(1+$AA$14)*(1+hora_extra_sábados),2)) -> 0 | AN48: =IF(I48="contrato",0,ROUNDUP((M48/220)*(1+$AA$14)*(1+hora_extra_domingos),2)) -> 0 | AO48: =IF(I48="contrato",0,ROUNDUP(AL48*(1+adicional_noturno),2)) -> 0 | AP48: =IF(I48="contrato",0,ROUNDUP(AM48*(1+adicional_noturno),2)) -> 0 | AQ48: =IF(I48="contrato",0,ROUNDUP(AN48*(1+adicional_noturno),2)) -> 0 | AS48: =IF(H48="Coordenação",0,L48*J48) -> 8 | AT48: =IF(H48="Coordenação",L48*J48,0) -> 0 | AV48: =IF(I48="CLT",IF(L48=0,0,P48*220+N48),(P48*220+N48+(O48/meses_obra))) -> 5446.875 | AW48: =IF(I48="CLT",IF(L48=0,0,((P48*220)+(AE48*AL48)+(AF48*AM48)+(AG48*AN48)+(AH48*AO48)+(AI48*AP48)+(AJ48*AQ48)+N48)),AV48) -> 5446.875 | AX48: =AV48*L48*J48 -> 43575
A49: 2 | D49: 2.15 | E49: Mestre de Obra II | H49: Supervisão | I49: CLT | L49: =meses_obra -> 8 | M49: 4606.35 | N49: 0 | O49: =IF(I49="CLT","N/A",(L49*(M49/12)*2)) -> N/A | P49: =IF(I49="contrato",AB49,AB49) -> 46.480745 | Q49: =AE49+AF49 -> 0 | R49: =AG49 -> 0 | S49: =Q49*AL49 -> 0 | T49: =R49*AN49 -> 0 | U49: =AW49*L49*J49 -> 0 | Z49: =IF(I49="CLT",(M49/220)*(1+encargos_mensalista),(M49/220)) -> 44.53245 | AA49: =Z49*(1+K49) -> 44.53245 | AB49: =AA49*(1+((incidência_do_dissídio/meses_obra)*dissídio_coletivo)) -> 46.480745 | AC49: =AB49*(1+(ociosidade_por_dia/9)) -> 46.480745 | AE49: =IF(I49="contrato",0,$N$11*$Q$11*$K$11) -> 0 | AF49: =IF(I49="contrato",0,$N$12*$Q$12*$K$12) -> 0 | AG49: =IF(I49="contrato",0,$N$13*$Q$13*$K$13) -> 0 | AH49: =IF(I49="contrato",0,$N$14*$Q$14*$K$14) -> 0 | AI49: =IF(I49="contrato",0,$N$14*$Q$15*$K$15) -> 0 | AJ49: =IF(I49="contrato",0,$N$14*$Q$16*$K$16) -> 0 | AL49: =IF(I49="contrato",0,ROUNDUP((M49/220)*(1+$AA$14)*(1+hora_extra_dias_úteis),2)) -> 50.06 | AM49: =IF(I49="contrato",0,ROUNDUP((M49/220)*(1+$AA$14)*(1+hora_extra_sábados),2)) -> 50.06 | AN49: =IF(I49="contrato",0,ROUNDUP((M49/220)*(1+$AA$14)*(1+hora_extra_domingos),2)) -> 62.58 | AO49: =IF(I49="contrato",0,ROUNDUP(AL49*(1+adicional_noturno),2)) -> 60.08 | AP49: =IF(I49="contrato",0,ROUNDUP(AM49*(1+adicional_noturno),2)) -> 60.08 | AQ49: =IF(I49="contrato",0,ROUNDUP(AN49*(1+adicional_noturno),2)) -> 75.1 | AS49: =IF(H49="Coordenação",0,L49*J49) -> 0 | AT49: =IF(H49="Coordenação",L49*J49,0) -> 0 | AV49: =IF(I49="CLT",IF(L49=0,0,P49*220+N49),(P49*220+N49+(O49/meses_obra))) -> 10225.764 | AW49: =IF(I49="CLT",IF(L49=0,0,((P49*220)+(AE49*AL49)+(AF49*AM49)+(AG49*AN49)+(AH49*AO49)+(AI49*AP49)+(AJ49*AQ49)+N49)),AV49) -> 10225.764 | AX49: =AV49*L49*J49 -> 0
A50: 2 | D50: 2.16 | E50: Mestre de Obra II | H50: Supervisão | I50: CLT | L50: =meses_obra -> 8 | M50: 4606.35 | N50: 0 | O50: =IF(I50="CLT","N/A",(L50*(M50/12)*2)) -> N/A | P50: =IF(I50="contrato",AB50,AB50) -> 46.480745 | Q50: =AE50+AF50 -> 0 | R50: =AG50 -> 0 | S50: =Q50*AL50 -> 0 | T50: =R50*AN50 -> 0 | U50: =AW50*L50*J50 -> 0 | Z50: =IF(I50="CLT",(M50/220)*(1+encargos_mensalista),(M50/220)) -> 44.53245 | AA50: =Z50*(1+K50) -> 44.53245 | AB50: =AA50*(1+((incidência_do_dissídio/meses_obra)*dissídio_coletivo)) -> 46.480745 | AC50: =AB50*(1+(ociosidade_por_dia/9)) -> 46.480745 | AE50: =IF(I50="contrato",0,$N$11*$Q$11*$K$11) -> 0 | AF50: =IF(I50="contrato",0,$N$12*$Q$12*$K$12) -> 0 | AG50: =IF(I50="contrato",0,$N$13*$Q$13*$K$13) -> 0 | AH50: =IF(I50="contrato",0,$N$14*$Q$14*$K$14) -> 0 | AI50: =IF(I50="contrato",0,$N$14*$Q$15*$K$15) -> 0 | AJ50: =IF(I50="contrato",0,$N$14*$Q$16*$K$16) -> 0 | AL50: =IF(I50="contrato",0,ROUNDUP((M50/220)*(1+$AA$14)*(1+hora_extra_dias_úteis),2)) -> 50.06 | AM50: =IF(I50="contrato",0,ROUNDUP((M50/220)*(1+$AA$14)*(1+hora_extra_sábados),2)) -> 50.06 | AN50: =IF(I50="contrato",0,ROUNDUP((M50/220)*(1+$AA$14)*(1+hora_extra_domingos),2)) -> 62.58 | AO50: =IF(I50="contrato",0,ROUNDUP(AL50*(1+adicional_noturno),2)) -> 60.08 | AP50: =IF(I50="contrato",0,ROUNDUP(AM50*(1+adicional_noturno),2)) -> 60.08 | AQ50: =IF(I50="contrato",0,ROUNDUP(AN50*(1+adicional_noturno),2)) -> 75.1 | AS50: =IF(H50="Coordenação",0,L50*J50) -> 0 | AT50: =IF(H50="Coordenação",L50*J50,0) -> 0 | AV50: =IF(I50="CLT",IF(L50=0,0,P50*220+N50),(P50*220+N50+(O50/meses_obra))) -> 10225.764 | AW50: =IF(I50="CLT",IF(L50=0,0,((P50*220)+(AE50*AL50)+(AF50*AM50)+(AG50*AN50)+(AH50*AO50)+(AI50*AP50)+(AJ50*AQ50)+N50)),AV50) -> 10225.764 | AX50: =AV50*L50*J50 -> 0
A51: 2 | D51: 2.17 | E51: Contra Mestre I | H51: Supervisão | I51: CLT | L51: =meses_obra -> 8 | M51: 3531 | N51: 0 | O51: =IF(I51="CLT","N/A",(L51*(M51/12)*2)) -> N/A | P51: =IF(I51="contrato",AB51,AB51) -> 35.629839 | Q51: =AE51+AF51 -> 0 | R51: =AG51 -> 0 | S51: =Q51*AL51 -> 0 | T51: =R51*AN51 -> 0 | U51: =AW51*L51*J51 -> 0 | Z51: =IF(I51="CLT",(M51/220)*(1+encargos_mensalista),(M51/220)) -> 34.136373 | AA51: =Z51*(1+K51) -> 34.136373 | AB51: =AA51*(1+((incidência_do_dissídio/meses_obra)*dissídio_coletivo)) -> 35.629839 | AC51: =AB51*(1+(ociosidade_por_dia/9)) -> 35.629839 | AE51: =IF(I51="contrato",0,$N$11*$Q$11*$K$11) -> 0 | AF51: =IF(I51="contrato",0,$N$12*$Q$12*$K$12) -> 0 | AG51: =IF(I51="contrato",0,$N$13*$Q$13*$K$13) -> 0 | AH51: =IF(I51="contrato",0,$N$14*$Q$14*$K$14) -> 0 | AI51: =IF(I51="contrato",0,$N$14*$Q$15*$K$15) -> 0 | AJ51: =IF(I51="contrato",0,$N$14*$Q$16*$K$16) -> 0 | AL51: =IF(I51="contrato",0,ROUNDUP((M51/220)*(1+$AA$14)*(1+hora_extra_dias_úteis),2)) -> 38.38 | AM51: =IF(I51="contrato",0,ROUNDUP((M51/220)*(1+$AA$14)*(1+hora_extra_sábados),2)) -> 38.38 | AN51: =IF(I51="contrato",0,ROUNDUP((M51/220)*(1+$AA$14)*(1+hora_extra_domingos),2)) -> 47.97 | AO51: =IF(I51="contrato",0,ROUNDUP(AL51*(1+adicional_noturno),2)) -> 46.06 | AP51: =IF(I51="contrato",0,ROUNDUP(AM51*(1+adicional_noturno),2)) -> 46.06 | AQ51: =IF(I51="contrato",0,ROUNDUP(AN51*(1+adicional_noturno),2)) -> 57.57 | AS51: =IF(H51="Coordenação",0,L51*J51) -> 0 | AT51: =IF(H51="Coordenação",L51*J51,0) -> 0 | AV51: =IF(I51="CLT",IF(L51=0,0,P51*220+N51),(P51*220+N51+(O51/meses_obra))) -> 7838.5646 | AW51: =IF(I51="CLT",IF(L51=0,0,((P51*220)+(AE51*AL51)+(AF51*AM51)+(AG51*AN51)+(AH51*AO51)+(AI51*AP51)+(AJ51*AQ51)+N51)),AV51) -> 7838.5646 | AX51: =AV51*L51*J51 -> 0
A52: 2 | D52: 2.18 | E52: Contra Mestre II | H52: Supervisão | I52: CLT | L52: =meses_obra -> 8 | M52: 3531 | N52: 0 | O52: =IF(I52="CLT","N/A",(L52*(M52/12)*2)) -> N/A | P52: =IF(I52="contrato",AB52,AB52) -> 35.629839 | Q52: =AE52+AF52 -> 0 | R52: =AG52 -> 0 | S52: =Q52*AL52 -> 0 | T52: =R52*AN52 -> 0 | U52: =AW52*L52*J52 -> 0 | Z52: =IF(I52="CLT",(M52/220)*(1+encargos_mensalista),(M52/220)) -> 34.136373 | AA52: =Z52*(1+K52) -> 34.136373 | AB52: =AA52*(1+((incidência_do_dissídio/meses_obra)*dissídio_coletivo)) -> 35.629839 | AC52: =AB52*(1+(ociosidade_por_dia/9)) -> 35.629839 | AE52: =IF(I52="contrato",0,$N$11*$Q$11*$K$11) -> 0 | AF52: =IF(I52="contrato",0,$N$12*$Q$12*$K$12) -> 0 | AG52: =IF(I52="contrato",0,$N$13*$Q$13*$K$13) -> 0 | AH52: =IF(I52="contrato",0,$N$14*$Q$14*$K$14) -> 0 | AI52: =IF(I52="contrato",0,$N$14*$Q$15*$K$15) -> 0 | AJ52: =IF(I52="contrato",0,$N$14*$Q$16*$K$16) -> 0 | AL52: =IF(I52="contrato",0,ROUNDUP((M52/220)*(1+$AA$14)*(1+hora_extra_dias_úteis),2)) -> 38.38 | AM52: =IF(I52="contrato",0,ROUNDUP((M52/220)*(1+$AA$14)*(1+hora_extra_sábados),2)) -> 38.38 | AN52: =IF(I52="contrato",0,ROUNDUP((M52/220)*(1+$AA$14)*(1+hora_extra_domingos),2)) -> 47.97 | AO52: =IF(I52="contrato",0,ROUNDUP(AL52*(1+adicional_noturno),2)) -> 46.06 | AP52: =IF(I52="contrato",0,ROUNDUP(AM52*(1+adicional_noturno),2)) -> 46.06 | AQ52: =IF(I52="contrato",0,ROUNDUP(AN52*(1+adicional_noturno),2)) -> 57.57 | AS52: =IF(H52="Coordenação",0,L52*J52) -> 0 | AT52: =IF(H52="Coordenação",L52*J52,0) -> 0 | AV52: =IF(I52="CLT",IF(L52=0,0,P52*220+N52),(P52*220+N52+(O52/meses_obra))) -> 7838.5646 | AW52: =IF(I52="CLT",IF(L52=0,0,((P52*220)+(AE52*AL52)+(AF52*AM52)+(AG52*AN52)+(AH52*AO52)+(AI52*AP52)+(AJ52*AQ52)+N52)),AV52) -> 7838.5646 | AX52: =AV52*L52*J52 -> 0
A53: 2 | D53: 2.19 | E53: Encarregado de Obra I | H53: Supervisão | I53: Contrato | J53: 1 | L53: =meses_obra -> 8 | M53: 5500 | N53: 0 | O53: =IF(I53="CLT","N/A",(L53*(M53/12)*2)) -> 7333.3333 | P53: =IF(I53="contrato",AB53,AB53) -> 26.09375 | Q53: =AE53+AF53 -> 0 | R53: =AG53 -> 0 | S53: =Q53*AL53 -> 0 | T53: =R53*AN53 -> 0 | U53: =AW53*L53*J53 -> 53258.333 | Z53: =IF(I53="CLT",(M53/220)*(1+encargos_mensalista),(M53/220)) -> 25 | AA53: =Z53*(1+K53) -> 25 | AB53: =AA53*(1+((incidência_do_dissídio/meses_obra)*dissídio_coletivo)) -> 26.09375 | AC53: =AB53*(1+(ociosidade_por_dia/9)) -> 26.09375 | AE53: =IF(I53="contrato",0,$N$11*$Q$11*$K$11) -> 0 | AF53: =IF(I53="contrato",0,$N$12*$Q$12*$K$12) -> 0 | AG53: =IF(I53="contrato",0,$N$13*$Q$13*$K$13) -> 0 | AH53: =IF(I53="contrato",0,$N$14*$Q$14*$K$14) -> 0 | AI53: =IF(I53="contrato",0,$N$14*$Q$15*$K$15) -> 0 | AJ53: =IF(I53="contrato",0,$N$14*$Q$16*$K$16) -> 0 | AL53: =IF(I53="contrato",0,ROUNDUP((M53/220)*(1+$AA$14)*(1+hora_extra_dias_úteis),2)) -> 0 | AM53: =IF(I53="contrato",0,ROUNDUP((M53/220)*(1+$AA$14)*(1+hora_extra_sábados),2)) -> 0 | AN53: =IF(I53="contrato",0,ROUNDUP((M53/220)*(1+$AA$14)*(1+hora_extra_domingos),2)) -> 0 | AO53: =IF(I53="contrato",0,ROUNDUP(AL53*(1+adicional_noturno),2)) -> 0 | AP53: =IF(I53="contrato",0,ROUNDUP(AM53*(1+adicional_noturno),2)) -> 0 | AQ53: =IF(I53="contrato",0,ROUNDUP(AN53*(1+adicional_noturno),2)) -> 0 | AS53: =IF(H53="Coordenação",0,L53*J53) -> 8 | AT53: =IF(H53="Coordenação",L53*J53,0) -> 0 | AV53: =IF(I53="CLT",IF(L53=0,0,P53*220+N53),(P53*220+N53+(O53/meses_obra))) -> 6657.2917 | AW53: =IF(I53="CLT",IF(L53=0,0,((P53*220)+(AE53*AL53)+(AF53*AM53)+(AG53*AN53)+(AH53*AO53)+(AI53*AP53)+(AJ53*AQ53)+N53)),AV53) -> 6657.2917 | AX53: =AV53*L53*J53 -> 53258.333
A54: 2 | D54: 2.20 | E54: Encarregado de Obra II | H54: Supervisão | I54: Contrato | J54: 1 | L54: =meses_obra -> 8 | M54: 4000 | N54: 0 | O54: =IF(I54="CLT","N/A",(L54*(M54/12)*2)) -> 5333.3333 | P54: =IF(I54="contrato",AB54,AB54) -> 18.977273 | Q54: =AE54+AF54 -> 0 | R54: =AG54 -> 0 | S54: =Q54*AL54 -> 0 | T54: =R54*AN54 -> 0 | U54: =AW54*L54*J54 -> 38733.333 | Z54: =IF(I54="CLT",(M54/220)*(1+encargos_mensalista),(M54/220)) -> 18.181818 | AA54: =Z54*(1+K54) -> 18.181818 | AB54: =AA54*(1+((incidência_do_dissídio/meses_obra)*dissídio_coletivo)) -> 18.977273 | AC54: =AB54*(1+(ociosidade_por_dia/9)) -> 18.977273 | AE54: =IF(I54="contrato",0,$N$11*$Q$11*$K$11) -> 0 | AF54: =IF(I54="contrato",0,$N$12*$Q$12*$K$12) -> 0 | AG54: =IF(I54="contrato",0,$N$13*$Q$13*$K$13) -> 0 | AH54: =IF(I54="contrato",0,$N$14*$Q$14*$K$14) -> 0 | AI54: =IF(I54="contrato",0,$N$14*$Q$15*$K$15) -> 0 | AJ54: =IF(I54="contrato",0,$N$14*$Q$16*$K$16) -> 0 | AL54: =IF(I54="contrato",0,ROUNDUP((M54/220)*(1+$AA$14)*(1+hora_extra_dias_úteis),2)) -> 0 | AM54: =IF(I54="contrato",0,ROUNDUP((M54/220)*(1+$AA$14)*(1+hora_extra_sábados),2)) -> 0 | AN54: =IF(I54="contrato",0,ROUNDUP((M54/220)*(1+$AA$14)*(1+hora_extra_domingos),2)) -> 0 | AO54: =IF(I54="contrato",0,ROUNDUP(AL54*(1+adicional_noturno),2)) -> 0 | AP54: =IF(I54="contrato",0,ROUNDUP(AM54*(1+adicional_noturno),2)) -> 0 | AQ54: =IF(I54="contrato",0,ROUNDUP(AN54*(1+adicional_noturno),2)) -> 0 | AS54: =IF(H54="Coordenação",0,L54*J54) -> 8 | AT54: =IF(H54="Coordenação",L54*J54,0) -> 0 | AV54: =IF(I54="CLT",IF(L54=0,0,P54*220+N54),(P54*220+N54+(O54/meses_obra))) -> 4841.6667 | AW54: =IF(I54="CLT",IF(L54=0,0,((P54*220)+(AE54*AL54)+(AF54*AM54)+(AG54*AN54)+(AH54*AO54)+(AI54*AP54)+(AJ54*AQ54)+N54)),AV54) -> 4841.6667 | AX54: =AV54*L54*J54 -> 38733.333
A55: 2 | D55: 2.21 | E55: Feitor I | H55: Apoio | I55: CLT | L55: =meses_obra -> 8 | M55: 3707.55 | N55: 0 | O55: =IF(I55="CLT","N/A",(L55*(M55/12)*2)) -> N/A | P55: =IF(I55="contrato",AB55,AB55) -> 37.411331 | Q55: =AE55+AF55 -> 0 | R55: =AG55 -> 0 | S55: =Q55*AL55 -> 0 | T55: =R55*AN55 -> 0 | U55: =AW55*L55*J55 -> 0 | Z55: =IF(I55="CLT",(M55/220)*(1+encargos_mensalista),(M55/220)) -> 35.843192 | AA55: =Z55*(1+K55) -> 35.843192 | AB55: =AA55*(1+((incidência_do_dissídio/meses_obra)*dissídio_coletivo)) -> 37.411331 | AC55: =AB55*(1+(ociosidade_por_dia/9)) -> 37.411331 | AE55: =IF(I55="contrato",0,$N$11*$Q$11*$K$11) -> 0 | AF55: =IF(I55="contrato",0,$N$12*$Q$12*$K$12) -> 0 | AG55: =IF(I55="contrato",0,$N$13*$Q$13*$K$13) -> 0 | AH55: =IF(I55="contrato",0,$N$14*$Q$14*$K$14) -> 0 | AI55: =IF(I55="contrato",0,$N$14*$Q$15*$K$15) -> 0 | AJ55: =IF(I55="contrato",0,$N$14*$Q$16*$K$16) -> 0 | AL55: =IF(I55="contrato",0,ROUNDUP((M55/220)*(1+$AA$14)*(1+hora_extra_dias_úteis),2)) -> 40.29 | AM55: =IF(I55="contrato",0,ROUNDUP((M55/220)*(1+$AA$14)*(1+hora_extra_sábados),2)) -> 40.29 | AN55: =IF(I55="contrato",0,ROUNDUP((M55/220)*(1+$AA$14)*(1+hora_extra_domingos),2)) -> 50.37 | AO55: =IF(I55="contrato",0,ROUNDUP(AL55*(1+adicional_noturno),2)) -> 48.35 | AP55: =IF(I55="contrato",0,ROUNDUP(AM55*(1+adicional_noturno),2)) -> 48.35 | AQ55: =IF(I55="contrato",0,ROUNDUP(AN55*(1+adicional_noturno),2)) -> 60.45 | AS55: =IF(H55="Coordenação",0,L55*J55) -> 0 | AT55: =IF(H55="Coordenação",L55*J55,0) -> 0 | AV55: =IF(I55="CLT",IF(L55=0,0,P55*220+N55),(P55*220+N55+(O55/meses_obra))) -> 8230.4929 | AW55: =IF(I55="CLT",IF(L55=0,0,((P55*220)+(AE55*AL55)+(AF55*AM55)+(AG55*AN55)+(AH55*AO55)+(AI55*AP55)+(AJ55*AQ55)+N55)),AV55) -> 8230.4929 | AX55: =AV55*L55*J55 -> 0
A56: 2 | D56: 2.22 | E56: Estagiario | H56: Apoio | I56: Contrato | L56: =meses_obra -> 8 | M56: 1200 | N56: 0 | O56: =IF(I56="CLT","N/A",(L56*(M56/12)*2)) -> 1600 | P56: =IF(I56="contrato",AB56,AB56) -> 5.6931818 | Q56: =AE56+AF56 -> 0 | R56: =AG56 -> 0 | S56: =Q56*AL56 -> 0 | T56: =R56*AN56 -> 0 | U56: =AW56*L56*J56 -> 0 | Z56: =IF(I56="CLT",(M56/220)*(1+encargos_mensalista),(M56/220)) -> 5.4545455 | AA56: =Z56*(1+K56) -> 5.4545455 | AB56: =AA56*(1+((incidência_do_dissídio/meses_obra)*dissídio_coletivo)) -> 5.6931818 | AC56: =AB56*(1+(ociosidade_por_dia/9)) -> 5.6931818 | AE56: =IF(I56="contrato",0,$N$11*$Q$11*$K$11) -> 0 | AF56: =IF(I56="contrato",0,$N$12*$Q$12*$K$12) -> 0 | AG56: =IF(I56="contrato",0,$N$13*$Q$13*$K$13) -> 0 | AH56: =IF(I56="contrato",0,$N$14*$Q$14*$K$14) -> 0 | AI56: =IF(I56="contrato",0,$N$14*$Q$15*$K$15) -> 0 | AJ56: =IF(I56="contrato",0,$N$14*$Q$16*$K$16) -> 0 | AL56: =IF(I56="contrato",0,ROUNDUP((M56/220)*(1+$AA$14)*(1+hora_extra_dias_úteis),2)) -> 0 | AM56: =IF(I56="contrato",0,ROUNDUP((M56/220)*(1+$AA$14)*(1+hora_extra_sábados),2)) -> 0 | AN56: =IF(I56="contrato",0,ROUNDUP((M56/220)*(1+$AA$14)*(1+hora_extra_domingos),2)) -> 0 | AO56: =IF(I56="contrato",0,ROUNDUP(AL56*(1+adicional_noturno),2)) -> 0 | AP56: =IF(I56="contrato",0,ROUNDUP(AM56*(1+adicional_noturno),2)) -> 0 | AQ56: =IF(I56="contrato",0,ROUNDUP(AN56*(1+adicional_noturno),2)) -> 0 | AS56: =IF(H56="Coordenação",0,L56*J56) -> 0 | AT56: =IF(H56="Coordenação",L56*J56,0) -> 0 | AV56: =IF(I56="CLT",IF(L56=0,0,P56*220+N56),(P56*220+N56+(O56/meses_obra))) -> 1452.5 | AW56: =IF(I56="CLT",IF(L56=0,0,((P56*220)+(AE56*AL56)+(AF56*AM56)+(AG56*AN56)+(AH56*AO56)+(AI56*AP56)+(AJ56*AQ56)+N56)),AV56) -> 1452.5 | AX56: =AV56*L56*J56 -> 0
A57: 2 | D57: 2.23 | L57: =meses_obra -> 8 | O57: =IF(I57="CLT","N/A",(L57*(M57/12)*2)) -> 0 | P57: =IF(I57="contrato",AB57,AB57) -> 0 | Q57: =AE57+AF57 -> 0 | R57: =AG57 -> 0 | S57: =Q57*AL57 -> 0 | T57: =R57*AN57 -> 0 | U57: =AW57*L57*J57 -> 0 | Z57: =IF(I57="CLT",(M57/220)*(1+encargos_mensalista),(M57/220)) -> 0 | AA57: =Z57*(1+K57) -> 0 | AB57: =AA57*(1+((incidência_do_dissídio/meses_obra)*dissídio_coletivo)) -> 0 | AC57: =AB57*(1+(ociosidade_por_dia/9)) -> 0 | AE57: =IF(I57="contrato",0,$N$11*$Q$11*$K$11) -> 0 | AF57: =IF(I57="contrato",0,$N$12*$Q$12*$K$12) -> 0 | AG57: =IF(I57="contrato",0,$N$13*$Q$13*$K$13) -> 0 | AH57: =IF(I57="contrato",0,$N$14*$Q$14*$K$14) -> 0 | AI57: =IF(I57="contrato",0,$N$14*$Q$15*$K$15) -> 0 | AJ57: =IF(I57="contrato",0,$N$14*$Q$16*$K$16) -> 0 | AL57: =IF(I57="contrato",0,ROUNDUP((M57/220)*(1+$AA$14)*(1+hora_extra_dias_úteis),2)) -> 0 | AM57: =IF(I57="contrato",0,ROUNDUP((M57/220)*(1+$AA$14)*(1+hora_extra_sábados),2)) -> 0 | AN57: =IF(I57="contrato",0,ROUNDUP((M57/220)*(1+$AA$14)*(1+hora_extra_domingos),2)) -> 0 | AO57: =IF(I57="contrato",0,ROUNDUP(AL57*(1+adicional_noturno),2)) -> 0 | AP57: =IF(I57="contrato",0,ROUNDUP(AM57*(1+adicional_noturno),2)) -> 0 | AQ57: =IF(I57="contrato",0,ROUNDUP(AN57*(1+adicional_noturno),2)) -> 0 | AS57: =IF(H57="Coordenação",0,L57*J57) -> 0 | AT57: =IF(H57="Coordenação",L57*J57,0) -> 0 | AV57: =IF(I57="CLT",IF(L57=0,0,P57*220+N57),(P57*220+N57+(O57/meses_obra))) -> 0 | AW57: =IF(I57="CLT",IF(L57=0,0,((P57*220)+(AE57*AL57)+(AF57*AM57)+(AG57*AN57)+(AH57*AO57)+(AI57*AP57)+(AJ57*AQ57)+N57)),AV57) -> 0 | AX57: =AV57*L57*J57 -> 0
A59: S | D59: 03 | E59: Administração local | J59: Qtde | K59: Transferencia | L59: ΔT em obra | M59: Base | N59: Ajuda ou bonus | U59: =SUMIF(A:A,D59,U:U) -> 0 | Z59: com L.S. | AA59: Transf | AB59: Dissidio | AC59: Ossiosidade | AE59: HE d.útil | AF59: Qtd sáb | AG59: Qtd dom | AH59: HE d.útil | AI59: Qtd sáb | AJ59: Qtd dom | AL59: VH.d.útil | AM59: VH.sáb | AN59: VH.dom | AO59: VH.d.útil | AP59: VH.sáb | AQ59: VH.dom | AS59: Supervisão | AT59: Coordenação | AX59: =SUMIF(A:A,D59,AX:AX) -> 0
A60: 3 | D60: 3.01 | E60: Administrativo de Obra - RH | H60: Apoio | I60: CLT | L60: =meses_obra -> 8 | M60: 4785 | N60: 0 | O60: =IF(I60="CLT","N/A",(L60*(M60/12)*2)) -> N/A | P60: =IF(I60="contrato",AB60,AB60) -> 48.283427 | Q60: =AE60+AF60 -> 0 | R60: =AG60 -> 0 | S60: =Q60*AL60 -> 0 | T60: =R60*AN60 -> 0 | U60: =AW60*L60*J60 -> 0 | Z60: =IF(I60="CLT",(M60/220)*(1+encargos_mensalista),(M60/220)) -> 46.259571 | AA60: =Z60*(1+K60) -> 46.259571 | AB60: =AA60*(1+((incidência_do_dissídio/meses_obra)*dissídio_coletivo)) -> 48.283427 | AC60: =AB60*(1+(ociosidade_por_dia/9)) -> 48.283427 | AE60: =IF(I60="contrato",0,$N$11*$Q$11*$K$11) -> 0 | AF60: =IF(I60="contrato",0,$N$12*$Q$12*$K$12) -> 0 | AG60: =IF(I60="contrato",0,$N$13*$Q$13*$K$13) -> 0 | AH60: =IF(I60="contrato",0,$N$14*$Q$14*$K$14) -> 0 | AI60: =IF(I60="contrato",0,$N$14*$Q$15*$K$15) -> 0 | AJ60: =IF(I60="contrato",0,$N$14*$Q$16*$K$16) -> 0 | AL60: =IF(I60="contrato",0,ROUNDUP((M60/220)*(1+$AA$14)*(1+hora_extra_dias_úteis),2)) -> 52 | AM60: =IF(I60="contrato",0,ROUNDUP((M60/220)*(1+$AA$14)*(1+hora_extra_sábados),2)) -> 52 | AN60: =IF(I60="contrato",0,ROUNDUP((M60/220)*(1+$AA$14)*(1+hora_extra_domingos),2)) -> 65 | AO60: =IF(I60="contrato",0,ROUNDUP(AL60*(1+adicional_noturno),2)) -> 62.4 | AP60: =IF(I60="contrato",0,ROUNDUP(AM60*(1+adicional_noturno),2)) -> 62.4 | AQ60: =IF(I60="contrato",0,ROUNDUP(AN60*(1+adicional_noturno),2)) -> 78 | AS60: =IF(H60="Coordenação",0,L60*J60) -> 0 | AT60: =IF(H60="Coordenação",L60*J60,0) -> 0 | AV60: =IF(I60="CLT",IF(L60=0,0,P60*220+N60),(P60*220+N60+(O60/meses_obra))) -> 10622.354 | AW60: =IF(I60="CLT",IF(L60=0,0,((P60*220)+(AE60*AL60)+(AF60*AM60)+(AG60*AN60)+(AH60*AO60)+(AI60*AP60)+(AJ60*AQ60)+N60)),AV60) -> 10622.354 | AX60: =AV60*L60*J60 -> 0
A61: 3 | D61: 3.02 | E61: Administrativo de Obra - Financeiro | H61: Apoio | I61: CLT | L61: =meses_obra -> 8 | M61: 3500 | N61: 0 | O61: =IF(I61="CLT","N/A",(L61*(M61/12)*2)) -> N/A | P61: =IF(I61="contrato",AB61,AB61) -> 35.317031 | Q61: =AE61+AF61 -> 0 | R61: =AG61 -> 0 | S61: =Q61*AL61 -> 0 | T61: =R61*AN61 -> 0 | U61: =AW61*L61*J61 -> 0 | Z61: =IF(I61="CLT",(M61/220)*(1+encargos_mensalista),(M61/220)) -> 33.836677 | AA61: =Z61*(1+K61) -> 33.836677 | AB61: =AA61*(1+((incidência_do_dissídio/meses_obra)*dissídio_coletivo)) -> 35.317031 | AC61: =AB61*(1+(ociosidade_por_dia/9)) -> 35.317031 | AE61: =IF(I61="contrato",0,$N$11*$Q$11*$K$11) -> 0 | AF61: =IF(I61="contrato",0,$N$12*$Q$12*$K$12) -> 0 | AG61: =IF(I61="contrato",0,$N$13*$Q$13*$K$13) -> 0 | AH61: =IF(I61="contrato",0,$N$14*$Q$14*$K$14) -> 0 | AI61: =IF(I61="contrato",0,$N$14*$Q$15*$K$15) -> 0 | AJ61: =IF(I61="contrato",0,$N$14*$Q$16*$K$16) -> 0 | AL61: =IF(I61="contrato",0,ROUNDUP((M61/220)*(1+$AA$14)*(1+hora_extra_dias_úteis),2)) -> 38.04 | AM61: =IF(I61="contrato",0,ROUNDUP((M61/220)*(1+$AA$14)*(1+hora_extra_sábados),2)) -> 38.04 | AN61: =IF(I61="contrato",0,ROUNDUP((M61/220)*(1+$AA$14)*(1+hora_extra_domingos),2)) -> 47.55 | AO61: =IF(I61="contrato",0,ROUNDUP(AL61*(1+adicional_noturno),2)) -> 45.65 | AP61: =IF(I61="contrato",0,ROUNDUP(AM61*(1+adicional_noturno),2)) -> 45.65 | AQ61: =IF(I61="contrato",0,ROUNDUP(AN61*(1+adicional_noturno),2)) -> 57.06 | AS61: =IF(H61="Coordenação",0,L61*J61) -> 0 | AT61: =IF(H61="Coordenação",L61*J61,0) -> 0 | AV61: =IF(I61="CLT",IF(L61=0,0,P61*220+N61),(P61*220+N61+(O61/meses_obra))) -> 7769.7469 | AW61: =IF(I61="CLT",IF(L61=0,0,((P61*220)+(AE61*AL61)+(AF61*AM61)+(AG61*AN61)+(AH61*AO61)+(AI61*AP61)+(AJ61*AQ61)+N61)),AV61) -> 7769.7469 | AX61: =AV61*L61*J61 -> 0
A62: 3 | D62: 3.03 | E62: Auxiliar Administrativo - RH | H62: Apoio | I62: CLT | L62: =meses_obra -> 8 | M62: 2500 | O62: =IF(I62="CLT","N/A",(L62*(M62/12)*2)) -> N/A | P62: =IF(I62="contrato",AB62,AB62) -> 25.226451 | Q62: =AE62+AF62 -> 0 | R62: =AG62 -> 0 | S62: =Q62*AL62 -> 0 | T62: =R62*AN62 -> 0 | U62: =AW62*L62*J62 -> 0 | Z62: =IF(I62="CLT",(M62/220)*(1+encargos_mensalista),(M62/220)) -> 24.169055 | AA62: =Z62*(1+K62) -> 24.169055 | AB62: =AA62*(1+((incidência_do_dissídio/meses_obra)*dissídio_coletivo)) -> 25.226451 | AC62: =AB62*(1+(ociosidade_por_dia/9)) -> 25.226451 | AE62: =IF(I62="contrato",0,$N$11*$Q$11*$K$11) -> 0 | AF62: =IF(I62="contrato",0,$N$12*$Q$12*$K$12) -> 0 | AG62: =IF(I62="contrato",0,$N$13*$Q$13*$K$13) -> 0 | AH62: =IF(I62="contrato",0,$N$14*$Q$14*$K$14) -> 0 | AI62: =IF(I62="contrato",0,$N$14*$Q$15*$K$15) -> 0 | AJ62: =IF(I62="contrato",0,$N$14*$Q$16*$K$16) -> 0 | AL62: =IF(I62="contrato",0,ROUNDUP((M62/220)*(1+$AA$14)*(1+hora_extra_dias_úteis),2)) -> 27.17 | AM62: =IF(I62="contrato",0,ROUNDUP((M62/220)*(1+$AA$14)*(1+hora_extra_sábados),2)) -> 27.17 | AN62: =IF(I62="contrato",0,ROUNDUP((M62/220)*(1+$AA$14)*(1+hora_extra_domingos),2)) -> 33.96 | AO62: =IF(I62="contrato",0,ROUNDUP(AL62*(1+adicional_noturno),2)) -> 32.61 | AP62: =IF(I62="contrato",0,ROUNDUP(AM62*(1+adicional_noturno),2)) -> 32.61 | AQ62: =IF(I62="contrato",0,ROUNDUP(AN62*(1+adicional_noturno),2)) -> 40.76 | AS62: =IF(H62="Coordenação",0,L62*J62) -> 0 | AT62: =IF(H62="Coordenação",L62*J62,0) -> 0 | AV62: =IF(I62="CLT",IF(L62=0,0,P62*220+N62),(P62*220+N62+(O62/meses_obra))) -> 5549.8192 | AW62: =IF(I62="CLT",IF(L62=0,0,((P62*220)+(AE62*AL62)+(AF62*AM62)+(AG62*AN62)+(AH62*AO62)+(AI62*AP62)+(AJ62*AQ62)+N62)),AV62) -> 5549.8192 | AX62: =AV62*L62*J62 -> 0
A63: 3 | D63: 3.04 | E63: Auxiliar Administrativo - Financeiro | H63: Apoio | I63: CLT | L63: =meses_obra -> 8 | M63: 1957.32 | O63: =IF(I63="CLT","N/A",(L63*(M63/12)*2)) -> N/A | P63: =IF(I63="contrato",AB63,AB63) -> 19.750495 | Q63: =AE63+AF63 -> 0 | R63: =AG63 -> 0 | S63: =Q63*AL63 -> 0 | T63: =R63*AN63 -> 0 | U63: =AW63*L63*J63 -> 0 | Z63: =IF(I63="CLT",(M63/220)*(1+encargos_mensalista),(M63/220)) -> 18.92263 | AA63: =Z63*(1+K63) -> 18.92263 | AB63: =AA63*(1+((incidência_do_dissídio/meses_obra)*dissídio_coletivo)) -> 19.750495 | AC63: =AB63*(1+(ociosidade_por_dia/9)) -> 19.750495 | AE63: =IF(I63="contrato",0,$N$11*$Q$11*$K$11) -> 0 | AF63: =IF(I63="contrato",0,$N$12*$Q$12*$K$12) -> 0 | AG63: =IF(I63="contrato",0,$N$13*$Q$13*$K$13) -> 0 | AH63: =IF(I63="contrato",0,$N$14*$Q$14*$K$14) -> 0 | AI63: =IF(I63="contrato",0,$N$14*$Q$15*$K$15) -> 0 | AJ63: =IF(I63="contrato",0,$N$14*$Q$16*$K$16) -> 0 | AL63: =IF(I63="contrato",0,ROUNDUP((M63/220)*(1+$AA$14)*(1+hora_extra_dias_úteis),2)) -> 21.28 | AM63: =IF(I63="contrato",0,ROUNDUP((M63/220)*(1+$AA$14)*(1+hora_extra_sábados),2)) -> 21.28 | AN63: =IF(I63="contrato",0,ROUNDUP((M63/220)*(1+$AA$14)*(1+hora_extra_domingos),2)) -> 26.59 | AO63: =IF(I63="contrato",0,ROUNDUP(AL63*(1+adicional_noturno),2)) -> 25.54 | AP63: =IF(I63="contrato",0,ROUNDUP(AM63*(1+adicional_noturno),2)) -> 25.54 | AQ63: =IF(I63="contrato",0,ROUNDUP(AN63*(1+adicional_noturno),2)) -> 31.91 | AS63: =IF(H63="Coordenação",0,L63*J63) -> 0 | AT63: =IF(H63="Coordenação",L63*J63,0) -> 0 | AV63: =IF(I63="CLT",IF(L63=0,0,P63*220+N63),(P63*220+N63+(O63/meses_obra))) -> 4345.1088 | AW63: =IF(I63="CLT",IF(L63=0,0,((P63*220)+(AE63*AL63)+(AF63*AM63)+(AG63*AN63)+(AH63*AO63)+(AI63*AP63)+(AJ63*AQ63)+N63)),AV63) -> 4345.1088 | AX63: =AV63*L63*J63 -> 0
A64: 3 | D64: 3.05 | E64: Apontador | H64: Apoio | I64: CLT | L64: =meses_obra -> 8 | M64: 1957.32 | O64: =IF(I64="CLT","N/A",(L64*(M64/12)*2)) -> N/A | P64: =IF(I64="contrato",AB64,AB64) -> 19.750495 | Q64: =AE64+AF64 -> 0 | R64: =AG64 -> 0 | S64: =Q64*AL64 -> 0 | T64: =R64*AN64 -> 0 | U64: =AW64*L64*J64 -> 0 | Z64: =IF(I64="CLT",(M64/220)*(1+encargos_mensalista),(M64/220)) -> 18.92263 | AA64: =Z64*(1+K64) -> 18.92263 | AB64: =AA64*(1+((incidência_do_dissídio/meses_obra)*dissídio_coletivo)) -> 19.750495 | AC64: =AB64*(1+(ociosidade_por_dia/9)) -> 19.750495 | AE64: =IF(I64="contrato",0,$N$11*$Q$11*$K$11) -> 0 | AF64: =IF(I64="contrato",0,$N$12*$Q$12*$K$12) -> 0 | AG64: =IF(I64="contrato",0,$N$13*$Q$13*$K$13) -> 0 | AH64: =IF(I64="contrato",0,$N$14*$Q$14*$K$14) -> 0 | AI64: =IF(I64="contrato",0,$N$14*$Q$15*$K$15) -> 0 | AJ64: =IF(I64="contrato",0,$N$14*$Q$16*$K$16) -> 0 | AL64: =IF(I64="contrato",0,ROUNDUP((M64/220)*(1+$AA$14)*(1+hora_extra_dias_úteis),2)) -> 21.28 | AM64: =IF(I64="contrato",0,ROUNDUP((M64/220)*(1+$AA$14)*(1+hora_extra_sábados),2)) -> 21.28 | AN64: =IF(I64="contrato",0,ROUNDUP((M64/220)*(1+$AA$14)*(1+hora_extra_domingos),2)) -> 26.59 | AO64: =IF(I64="contrato",0,ROUNDUP(AL64*(1+adicional_noturno),2)) -> 25.54 | AP64: =IF(I64="contrato",0,ROUNDUP(AM64*(1+adicional_noturno),2)) -> 25.54 | AQ64: =IF(I64="contrato",0,ROUNDUP(AN64*(1+adicional_noturno),2)) -> 31.91 | AS64: =IF(H64="Coordenação",0,L64*J64) -> 0 | AT64: =IF(H64="Coordenação",L64*J64,0) -> 0 | AV64: =IF(I64="CLT",IF(L64=0,0,P64*220+N64),(P64*220+N64+(O64/meses_obra))) -> 4345.1088 | AW64: =IF(I64="CLT",IF(L64=0,0,((P64*220)+(AE64*AL64)+(AF64*AM64)+(AG64*AN64)+(AH64*AO64)+(AI64*AP64)+(AJ64*AQ64)+N64)),AV64) -> 4345.1088 | AX64: =AV64*L64*J64 -> 0
A65: 3 | D65: 3.06 | I65: CLT | L65: =meses_obra -> 8 | O65: =IF(I65="CLT","N/A",(L65*(M65/12)*2)) -> N/A | P65: =IF(I65="contrato",AB65,AB65) -> 0 | Q65: =AE65+AF65 -> 0 | R65: =AG65 -> 0 | S65: =Q65*AL65 -> 0 | T65: =R65*AN65 -> 0 | U65: =AW65*L65*J65 -> 0 | Z65: =IF(I65="CLT",(M65/220)*(1+encargos_mensalista),(M65/220)) -> 0 | AA65: =Z65*(1+K65) -> 0 | AB65: =AA65*(1+((incidência_do_dissídio/meses_obra)*dissídio_coletivo)) -> 0 | AC65: =AB65*(1+(ociosidade_por_dia/9)) -> 0 | AE65: =IF(I65="contrato",0,$N$11*$Q$11*$K$11) -> 0 | AF65: =IF(I65="contrato",0,$N$12*$Q$12*$K$12) -> 0 | AG65: =IF(I65="contrato",0,$N$13*$Q$13*$K$13) -> 0 | AH65: =IF(I65="contrato",0,$N$14*$Q$14*$K$14) -> 0 | AI65: =IF(I65="contrato",0,$N$14*$Q$15*$K$15) -> 0 | AJ65: =IF(I65="contrato",0,$N$14*$Q$16*$K$16) -> 0 | AL65: =IF(I65="contrato",0,ROUNDUP((M65/220)*(1+$AA$14)*(1+hora_extra_dias_úteis),2)) -> 0 | AM65: =IF(I65="contrato",0,ROUNDUP((M65/220)*(1+$AA$14)*(1+hora_extra_sábados),2)) -> 0 | AN65: =IF(I65="contrato",0,ROUNDUP((M65/220)*(1+$AA$14)*(1+hora_extra_domingos),2)) -> 0 | AO65: =IF(I65="contrato",0,ROUNDUP(AL65*(1+adicional_noturno),2)) -> 0 | AP65: =IF(I65="contrato",0,ROUNDUP(AM65*(1+adicional_noturno),2)) -> 0 | AQ65: =IF(I65="contrato",0,ROUNDUP(AN65*(1+adicional_noturno),2)) -> 0 | AS65: =IF(H65="Coordenação",0,L65*J65) -> 0 | AT65: =IF(H65="Coordenação",L65*J65,0) -> 0 | AV65: =IF(I65="CLT",IF(L65=0,0,P65*220+N65),(P65*220+N65+(O65/meses_obra))) -> 0 | AW65: =IF(I65="CLT",IF(L65=0,0,((P65*220)+(AE65*AL65)+(AF65*AM65)+(AG65*AN65)+(AH65*AO65)+(AI65*AP65)+(AJ65*AQ65)+N65)),AV65) -> 0 | AX65: =AV65*L65*J65 -> 0
A67: S | D67: 04 | E67: Equipe de poio / Almoxarifado local | J67: Qtde | K67: Transferencia | L67: ΔT em obra | M67: Base | N67: Ajuda ou bonus | U67: =SUMIF(A:A,D67,U:U) -> 0 | V67: =($AX$59+$AX$67)/custo_direto -> 0 | Z67: com L.S. | AA67: Transf | AB67: Dissidio | AC67: Ossiosidade | AE67: HE d.útil | AF67: Qtd sáb | AG67: Qtd dom | AH67: HE d.útil | AI67: Qtd sáb | AJ67: Qtd dom | AL67: VH.d.útil | AM67: VH.sáb | AN67: VH.dom | AO67: VH.d.útil | AP67: VH.sáb | AQ67: VH.dom | AS67: Supervisão | AT67: Coordenação | AX67: =SUMIF(A:A,D67,AX:AX) -> 0
A68: 4 | D68: 4.01 | E68: Técnico de Edificações - Suprimentos | H68: Apoio | I68: Contrato | L68: =meses_obra -> 8 | M68: 3000 | O68: =IF(I68="CLT","N/A",(L68*(M68/12)*2)) -> 4000 | P68: =IF(I68="contrato",AB68,AB68) -> 14.232955 | Q68: =AE68+AF68 -> 0 | R68: =AG68 -> 0 | S68: =Q68*AL68 -> 0 | T68: =R68*AN68 -> 0 | U68: =AW68*L68*J68 -> 0 | Z68: =IF(I68="CLT",(M68/220)*(1+encargos_mensalista),(M68/220)) -> 13.636364 | AA68: =Z68*(1+K68) -> 13.636364 | AB68: =AA68*(1+((incidência_do_dissídio/meses_obra)*dissídio_coletivo)) -> 14.232955 | AC68: =AB68*(1+(ociosidade_por_dia/9)) -> 14.232955 | AE68: =IF(I68="contrato",0,$N$11*$Q$11*$K$11) -> 0 | AF68: =IF(I68="contrato",0,$N$12*$Q$12*$K$12) -> 0 | AG68: =IF(I68="contrato",0,$N$13*$Q$13*$K$13) -> 0 | AH68: =IF(I68="contrato",0,$N$14*$Q$14*$K$14) -> 0 | AI68: =IF(I68="contrato",0,$N$14*$Q$15*$K$15) -> 0 | AJ68: =IF(I68="contrato",0,$N$14*$Q$16*$K$16) -> 0 | AL68: =IF(I68="contrato",0,ROUNDUP((M68/220)*(1+$AA$14)*(1+hora_extra_dias_úteis),2)) -> 0 | AM68: =IF(I68="contrato",0,ROUNDUP((M68/220)*(1+$AA$14)*(1+hora_extra_sábados),2)) -> 0 | AN68: =IF(I68="contrato",0,ROUNDUP((M68/220)*(1+$AA$14)*(1+hora_extra_domingos),2)) -> 0 | AO68: =IF(I68="contrato",0,ROUNDUP(AL68*(1+adicional_noturno),2)) -> 0 | AP68: =IF(I68="contrato",0,ROUNDUP(AM68*(1+adicional_noturno),2)) -> 0 | AQ68: =IF(I68="contrato",0,ROUNDUP(AN68*(1+adicional_noturno),2)) -> 0 | AS68: =IF(H68="Coordenação",0,L68*J68) -> 0 | AT68: =IF(H68="Coordenação",L68*J68,0) -> 0 | AV68: =IF(I68="CLT",IF(L68=0,0,P68*220+N68),(P68*220+N68+(O68/meses_obra))) -> 3631.25 | AW68: =IF(I68="CLT",IF(L68=0,0,((P68*220)+(AE68*AL68)+(AF68*AM68)+(AG68*AN68)+(AH68*AO68)+(AI68*AP68)+(AJ68*AQ68)+N68)),AV68) -> 3631.25 | AX68: =AV68*L68*J68 -> 0
A69: 4 | D69: 4.02 | E69: Almoxarife - central | H69: Apoio | I69: CLT | L69: =meses_obra -> 8 | M69: 1600 | O69: =IF(I69="CLT","N/A",(L69*(M69/12)*2)) -> N/A | P69: =IF(I69="contrato",AB69,AB69) -> 16.144929 | Q69: =AE69+AF69 -> 0 | R69: =AG69 -> 0 | S69: =Q69*AL69 -> 0 | T69: =R69*AN69 -> 0 | U69: =AW69*L69*J69 -> 0 | Z69: =IF(I69="CLT",(M69/220)*(1+encargos_mensalista),(M69/220)) -> 15.468195 | AA69: =Z69*(1+K69) -> 15.468195 | AB69: =AA69*(1+((incidência_do_dissídio/meses_obra)*dissídio_coletivo)) -> 16.144929 | AC69: =AB69*(1+(ociosidade_por_dia/9)) -> 16.144929 | AE69: =IF(I69="contrato",0,$N$11*$Q$11*$K$11) -> 0 | AF69: =IF(I69="contrato",0,$N$12*$Q$12*$K$12) -> 0 | AG69: =IF(I69="contrato",0,$N$13*$Q$13*$K$13) -> 0 | AH69: =IF(I69="contrato",0,$N$14*$Q$14*$K$14) -> 0 | AI69: =IF(I69="contrato",0,$N$14*$Q$15*$K$15) -> 0 | AJ69: =IF(I69="contrato",0,$N$14*$Q$16*$K$16) -> 0 | AL69: =IF(I69="contrato",0,ROUNDUP((M69/220)*(1+$AA$14)*(1+hora_extra_dias_úteis),2)) -> 17.39 | AM69: =IF(I69="contrato",0,ROUNDUP((M69/220)*(1+$AA$14)*(1+hora_extra_sábados),2)) -> 17.39 | AN69: =IF(I69="contrato",0,ROUNDUP((M69/220)*(1+$AA$14)*(1+hora_extra_domingos),2)) -> 21.74 | AO69: =IF(I69="contrato",0,ROUNDUP(AL69*(1+adicional_noturno),2)) -> 20.87 | AP69: =IF(I69="contrato",0,ROUNDUP(AM69*(1+adicional_noturno),2)) -> 20.87 | AQ69: =IF(I69="contrato",0,ROUNDUP(AN69*(1+adicional_noturno),2)) -> 26.09 | AS69: =IF(H69="Coordenação",0,L69*J69) -> 0 | AT69: =IF(H69="Coordenação",L69*J69,0) -> 0 | AV69: =IF(I69="CLT",IF(L69=0,0,P69*220+N69),(P69*220+N69+(O69/meses_obra))) -> 3551.8843 | AW69: =IF(I69="CLT",IF(L69=0,0,((P69*220)+(AE69*AL69)+(AF69*AM69)+(AG69*AN69)+(AH69*AO69)+(AI69*AP69)+(AJ69*AQ69)+N69)),AV69) -> 3551.8843 | AX69: =AV69*L69*J69 -> 0
A70: 4 | D70: 4.03 | E70: Auxiliar de almoxarifado | H70: Apoio | I70: CLT | L70: =meses_obra -> 8 | M70: 1100 | O70: =IF(I70="CLT","N/A",(L70*(M70/12)*2)) -> N/A | P70: =IF(I70="contrato",AB70,AB70) -> 11.099638 | Q70: =AE70+AF70 -> 0 | R70: =AG70 -> 0 | S70: =Q70*AL70 -> 0 | T70: =R70*AN70 -> 0 | U70: =AW70*L70*J70 -> 0 | Z70: =IF(I70="CLT",(M70/220)*(1+encargos_mensalista),(M70/220)) -> 10.634384 | AA70: =Z70*(1+K70) -> 10.634384 | AB70: =AA70*(1+((incidência_do_dissídio/meses_obra)*dissídio_coletivo)) -> 11.099638 | AC70: =AB70*(1+(ociosidade_por_dia/9)) -> 11.099638 | AE70: =IF(I70="contrato",0,$N$11*$Q$11*$K$11) -> 0 | AF70: =IF(I70="contrato",0,$N$12*$Q$12*$K$12) -> 0 | AG70: =IF(I70="contrato",0,$N$13*$Q$13*$K$13) -> 0 | AH70: =IF(I70="contrato",0,$N$14*$Q$14*$K$14) -> 0 | AI70: =IF(I70="contrato",0,$N$14*$Q$15*$K$15) -> 0 | AJ70: =IF(I70="contrato",0,$N$14*$Q$16*$K$16) -> 0 | AL70: =IF(I70="contrato",0,ROUNDUP((M70/220)*(1+$AA$14)*(1+hora_extra_dias_úteis),2)) -> 11.96 | AM70: =IF(I70="contrato",0,ROUNDUP((M70/220)*(1+$AA$14)*(1+hora_extra_sábados),2)) -> 11.96 | AN70: =IF(I70="contrato",0,ROUNDUP((M70/220)*(1+$AA$14)*(1+hora_extra_domingos),2)) -> 14.95 | AO70: =IF(I70="contrato",0,ROUNDUP(AL70*(1+adicional_noturno),2)) -> 14.36 | AP70: =IF(I70="contrato",0,ROUNDUP(AM70*(1+adicional_noturno),2)) -> 14.36 | AQ70: =IF(I70="contrato",0,ROUNDUP(AN70*(1+adicional_noturno),2)) -> 17.94 | AS70: =IF(H70="Coordenação",0,L70*J70) -> 0 | AT70: =IF(H70="Coordenação",L70*J70,0) -> 0 | AV70: =IF(I70="CLT",IF(L70=0,0,P70*220+N70),(P70*220+N70+(O70/meses_obra))) -> 2441.9204 | AW70: =IF(I70="CLT",IF(L70=0,0,((P70*220)+(AE70*AL70)+(AF70*AM70)+(AG70*AN70)+(AH70*AO70)+(AI70*AP70)+(AJ70*AQ70)+N70)),AV70) -> 2441.9204 | AX70: =AV70*L70*J70 -> 0
A71: 4 | D71: 4.04 | E71: Mecanico de equipamentos - geral | H71: Apoio | I71: CLT | L71: =meses_obra -> 8 | M71: 1400 | O71: =IF(I71="CLT","N/A",(L71*(M71/12)*2)) -> N/A | P71: =IF(I71="contrato",AB71,AB71) -> 14.126812 | Q71: =AE71+AF71 -> 0 | R71: =AG71 -> 0 | S71: =Q71*AL71 -> 0 | T71: =R71*AN71 -> 0 | U71: =AW71*L71*J71 -> 0 | Z71: =IF(I71="CLT",(M71/220)*(1+encargos_mensalista),(M71/220)) -> 13.534671 | AA71: =Z71*(1+K71) -> 13.534671 | AB71: =AA71*(1+((incidência_do_dissídio/meses_obra)*dissídio_coletivo)) -> 14.126812 | AC71: =AB71*(1+(ociosidade_por_dia/9)) -> 14.126812 | AE71: =IF(I71="contrato",0,$N$11*$Q$11*$K$11) -> 0 | AF71: =IF(I71="contrato",0,$N$12*$Q$12*$K$12) -> 0 | AG71: =IF(I71="contrato",0,$N$13*$Q$13*$K$13) -> 0 | AH71: =IF(I71="contrato",0,$N$14*$Q$14*$K$14) -> 0 | AI71: =IF(I71="contrato",0,$N$14*$Q$15*$K$15) -> 0 | AJ71: =IF(I71="contrato",0,$N$14*$Q$16*$K$16) -> 0 | AL71: =IF(I71="contrato",0,ROUNDUP((M71/220)*(1+$AA$14)*(1+hora_extra_dias_úteis),2)) -> 15.22 | AM71: =IF(I71="contrato",0,ROUNDUP((M71/220)*(1+$AA$14)*(1+hora_extra_sábados),2)) -> 15.22 | AN71: =IF(I71="contrato",0,ROUNDUP((M71/220)*(1+$AA$14)*(1+hora_extra_domingos),2)) -> 19.02 | AO71: =IF(I71="contrato",0,ROUNDUP(AL71*(1+adicional_noturno),2)) -> 18.27 | AP71: =IF(I71="contrato",0,ROUNDUP(AM71*(1+adicional_noturno),2)) -> 18.27 | AQ71: =IF(I71="contrato",0,ROUNDUP(AN71*(1+adicional_noturno),2)) -> 22.83 | AS71: =IF(H71="Coordenação",0,L71*J71) -> 0 | AT71: =IF(H71="Coordenação",L71*J71,0) -> 0 | AV71: =IF(I71="CLT",IF(L71=0,0,P71*220+N71),(P71*220+N71+(O71/meses_obra))) -> 3107.8987 | AW71: =IF(I71="CLT",IF(L71=0,0,((P71*220)+(AE71*AL71)+(AF71*AM71)+(AG71*AN71)+(AH71*AO71)+(AI71*AP71)+(AJ71*AQ71)+N71)),AV71) -> 3107.8987 | AX71: =AV71*L71*J71 -> 0
A72: 4 | D72: 4.05 | E72: Motorista - operador de caminhão munk | H72: Apoio | I72: CLT | L72: =meses_obra -> 8 | M72: 2000 | O72: =IF(I72="CLT","N/A",(L72*(M72/12)*2)) -> N/A | P72: =IF(I72="contrato",AB72,AB72) -> 20.181161 | Q72: =AE72+AF72 -> 0 | R72: =AG72 -> 0 | S72: =Q72*AL72 -> 0 | T72: =R72*AN72 -> 0 | U72: =AW72*L72*J72 -> 0 | Z72: =IF(I72="CLT",(M72/220)*(1+encargos_mensalista),(M72/220)) -> 19.335244 | AA72: =Z72*(1+K72) -> 19.335244 | AB72: =AA72*(1+((incidência_do_dissídio/meses_obra)*dissídio_coletivo)) -> 20.181161 | AC72: =AB72*(1+(ociosidade_por_dia/9)) -> 20.181161 | AE72: =IF(I72="contrato",0,$N$11*$Q$11*$K$11) -> 0 | AF72: =IF(I72="contrato",0,$N$12*$Q$12*$K$12) -> 0 | AG72: =IF(I72="contrato",0,$N$13*$Q$13*$K$13) -> 0 | AH72: =IF(I72="contrato",0,$N$14*$Q$14*$K$14) -> 0 | AI72: =IF(I72="contrato",0,$N$14*$Q$15*$K$15) -> 0 | AJ72: =IF(I72="contrato",0,$N$14*$Q$16*$K$16) -> 0 | AL72: =IF(I72="contrato",0,ROUNDUP((M72/220)*(1+$AA$14)*(1+hora_extra_dias_úteis),2)) -> 21.74 | AM72: =IF(I72="contrato",0,ROUNDUP((M72/220)*(1+$AA$14)*(1+hora_extra_sábados),2)) -> 21.74 | AN72: =IF(I72="contrato",0,ROUNDUP((M72/220)*(1+$AA$14)*(1+hora_extra_domingos),2)) -> 27.17 | AO72: =IF(I72="contrato",0,ROUNDUP(AL72*(1+adicional_noturno),2)) -> 26.09 | AP72: =IF(I72="contrato",0,ROUNDUP(AM72*(1+adicional_noturno),2)) -> 26.09 | AQ72: =IF(I72="contrato",0,ROUNDUP(AN72*(1+adicional_noturno),2)) -> 32.61 | AS72: =IF(H72="Coordenação",0,L72*J72) -> 0 | AT72: =IF(H72="Coordenação",L72*J72,0) -> 0 | AV72: =IF(I72="CLT",IF(L72=0,0,P72*220+N72),(P72*220+N72+(O72/meses_obra))) -> 4439.8553 | AW72: =IF(I72="CLT",IF(L72=0,0,((P72*220)+(AE72*AL72)+(AF72*AM72)+(AG72*AN72)+(AH72*AO72)+(AI72*AP72)+(AJ72*AQ72)+N72)),AV72) -> 4439.8553 | AX72: =AV72*L72*J72 -> 0
A73: 4 | D73: 4.06 | E73: Motorista - operador de HR | H73: Apoio | I73: CLT | L73: =meses_obra -> 8 | M73: 1900 | O73: =IF(I73="CLT","N/A",(L73*(M73/12)*2)) -> N/A | P73: =IF(I73="contrato",AB73,AB73) -> 19.172103 | Q73: =AE73+AF73 -> 0 | R73: =AG73 -> 0 | S73: =Q73*AL73 -> 0 | T73: =R73*AN73 -> 0 | U73: =AW73*L73*J73 -> 0 | Z73: =IF(I73="CLT",(M73/220)*(1+encargos_mensalista),(M73/220)) -> 18.368482 | AA73: =Z73*(1+K73) -> 18.368482 | AB73: =AA73*(1+((incidência_do_dissídio/meses_obra)*dissídio_coletivo)) -> 19.172103 | AC73: =AB73*(1+(ociosidade_por_dia/9)) -> 19.172103 | AE73: =IF(I73="contrato",0,$N$11*$Q$11*$K$11) -> 0 | AF73: =IF(I73="contrato",0,$N$12*$Q$12*$K$12) -> 0 | AG73: =IF(I73="contrato",0,$N$13*$Q$13*$K$13) -> 0 | AH73: =IF(I73="contrato",0,$N$14*$Q$14*$K$14) -> 0 | AI73: =IF(I73="contrato",0,$N$14*$Q$15*$K$15) -> 0 | AJ73: =IF(I73="contrato",0,$N$14*$Q$16*$K$16) -> 0 | AL73: =IF(I73="contrato",0,ROUNDUP((M73/220)*(1+$AA$14)*(1+hora_extra_dias_úteis),2)) -> 20.65 | AM73: =IF(I73="contrato",0,ROUNDUP((M73/220)*(1+$AA$14)*(1+hora_extra_sábados),2)) -> 20.65 | AN73: =IF(I73="contrato",0,ROUNDUP((M73/220)*(1+$AA$14)*(1+hora_extra_domingos),2)) -> 25.81 | AO73: =IF(I73="contrato",0,ROUNDUP(AL73*(1+adicional_noturno),2)) -> 24.78 | AP73: =IF(I73="contrato",0,ROUNDUP(AM73*(1+adicional_noturno),2)) -> 24.78 | AQ73: =IF(I73="contrato",0,ROUNDUP(AN73*(1+adicional_noturno),2)) -> 30.98 | AS73: =IF(H73="Coordenação",0,L73*J73) -> 0 | AT73: =IF(H73="Coordenação",L73*J73,0) -> 0 | AV73: =IF(I73="CLT",IF(L73=0,0,P73*220+N73),(P73*220+N73+(O73/meses_obra))) -> 4217.8626 | AW73: =IF(I73="CLT",IF(L73=0,0,((P73*220)+(AE73*AL73)+(AF73*AM73)+(AG73*AN73)+(AH73*AO73)+(AI73*AP73)+(AJ73*AQ73)+N73)),AV73) -> 4217.8626 | AX73: =AV73*L73*J73 -> 0
A74: 4 | D74: 4.07 | E74: Motorista - veículos | H74: Apoio | I74: CLT | L74: =meses_obra -> 8 | M74: 1900 | O74: =IF(I74="CLT","N/A",(L74*(M74/12)*2)) -> N/A | P74: =IF(I74="contrato",AB74,AB74) -> 19.172103 | Q74: =AE74+AF74 -> 0 | R74: =AG74 -> 0 | S74: =Q74*AL74 -> 0 | T74: =R74*AN74 -> 0 | U74: =AW74*L74*J74 -> 0 | Z74: =IF(I74="CLT",(M74/220)*(1+encargos_mensalista),(M74/220)) -> 18.368482 | AA74: =Z74*(1+K74) -> 18.368482 | AB74: =AA74*(1+((incidência_do_dissídio/meses_obra)*dissídio_coletivo)) -> 19.172103 | AC74: =AB74*(1+(ociosidade_por_dia/9)) -> 19.172103 | AE74: =IF(I74="contrato",0,$N$11*$Q$11*$K$11) -> 0 | AF74: =IF(I74="contrato",0,$N$12*$Q$12*$K$12) -> 0 | AG74: =IF(I74="contrato",0,$N$13*$Q$13*$K$13) -> 0 | AH74: =IF(I74="contrato",0,$N$14*$Q$14*$K$14) -> 0 | AI74: =IF(I74="contrato",0,$N$14*$Q$15*$K$15) -> 0 | AJ74: =IF(I74="contrato",0,$N$14*$Q$16*$K$16) -> 0 | AL74: =IF(I74="contrato",0,ROUNDUP((M74/220)*(1+$AA$14)*(1+hora_extra_dias_úteis),2)) -> 20.65 | AM74: =IF(I74="contrato",0,ROUNDUP((M74/220)*(1+$AA$14)*(1+hora_extra_sábados),2)) -> 20.65 | AN74: =IF(I74="contrato",0,ROUNDUP((M74/220)*(1+$AA$14)*(1+hora_extra_domingos),2)) -> 25.81 | AO74: =IF(I74="contrato",0,ROUNDUP(AL74*(1+adicional_noturno),2)) -> 24.78 | AP74: =IF(I74="contrato",0,ROUNDUP(AM74*(1+adicional_noturno),2)) -> 24.78 | AQ74: =IF(I74="contrato",0,ROUNDUP(AN74*(1+adicional_noturno),2)) -> 30.98 | AS74: =IF(H74="Coordenação",0,L74*J74) -> 0 | AT74: =IF(H74="Coordenação",L74*J74,0) -> 0 | AV74: =IF(I74="CLT",IF(L74=0,0,P74*220+N74),(P74*220+N74+(O74/meses_obra))) -> 4217.8626 | AW74: =IF(I74="CLT",IF(L74=0,0,((P74*220)+(AE74*AL74)+(AF74*AM74)+(AG74*AN74)+(AH74*AO74)+(AI74*AP74)+(AJ74*AQ74)+N74)),AV74) -> 4217.8626 | AX74: =AV74*L74*J74 -> 0
A75: 4 | D75: 4.08 | E75: Servente - faxina de canteiro de obra - escritório | H75: Apoio | I75: CLT | L75: =meses_obra -> 8 | M75: 1364 | O75: =IF(I75="CLT","N/A",(L75*(M75/12)*2)) -> N/A | P75: =IF(I75="contrato",AB75,AB75) -> 13.763552 | Q75: =AE75+AF75 -> 0 | R75: =AG75 -> 0 | S75: =Q75*AL75 -> 0 | T75: =R75*AN75 -> 0 | U75: =AW75*L75*J75 -> 0 | Z75: =IF(I75="CLT",(M75/220)*(1+encargos_mensalista),(M75/220)) -> 13.186636 | AA75: =Z75*(1+K75) -> 13.186636 | AB75: =AA75*(1+((incidência_do_dissídio/meses_obra)*dissídio_coletivo)) -> 13.763552 | AC75: =AB75*(1+(ociosidade_por_dia/9)) -> 13.763552 | AE75: =IF(I75="contrato",0,$N$11*$Q$11*$K$11) -> 0 | AF75: =IF(I75="contrato",0,$N$12*$Q$12*$K$12) -> 0 | AG75: =IF(I75="contrato",0,$N$13*$Q$13*$K$13) -> 0 | AH75: =IF(I75="contrato",0,$N$14*$Q$14*$K$14) -> 0 | AI75: =IF(I75="contrato",0,$N$14*$Q$15*$K$15) -> 0 | AJ75: =IF(I75="contrato",0,$N$14*$Q$16*$K$16) -> 0 | AL75: =IF(I75="contrato",0,ROUNDUP((M75/220)*(1+$AA$14)*(1+hora_extra_dias_úteis),2)) -> 14.83 | AM75: =IF(I75="contrato",0,ROUNDUP((M75/220)*(1+$AA$14)*(1+hora_extra_sábados),2)) -> 14.83 | AN75: =IF(I75="contrato",0,ROUNDUP((M75/220)*(1+$AA$14)*(1+hora_extra_domingos),2)) -> 18.53 | AO75: =IF(I75="contrato",0,ROUNDUP(AL75*(1+adicional_noturno),2)) -> 17.8 | AP75: =IF(I75="contrato",0,ROUNDUP(AM75*(1+adicional_noturno),2)) -> 17.8 | AQ75: =IF(I75="contrato",0,ROUNDUP(AN75*(1+adicional_noturno),2)) -> 22.24 | AS75: =IF(H75="Coordenação",0,L75*J75) -> 0 | AT75: =IF(H75="Coordenação",L75*J75,0) -> 0 | AV75: =IF(I75="CLT",IF(L75=0,0,P75*220+N75),(P75*220+N75+(O75/meses_obra))) -> 3027.9813 | AW75: =IF(I75="CLT",IF(L75=0,0,((P75*220)+(AE75*AL75)+(AF75*AM75)+(AG75*AN75)+(AH75*AO75)+(AI75*AP75)+(AJ75*AQ75)+N75)),AV75) -> 3027.9813 | AX75: =AV75*L75*J75 -> 0
A76: 4 | D76: 4.09 | E76: Servente - faxina de canteiro de obra / sanitários | H76: Apoio | I76: CLT | L76: =meses_obra -> 8 | M76: 1364 | O76: =IF(I76="CLT","N/A",(L76*(M76/12)*2)) -> N/A | P76: =IF(I76="contrato",AB76,AB76) -> 13.763552 | Q76: =AE76+AF76 -> 0 | R76: =AG76 -> 0 | S76: =Q76*AL76 -> 0 | T76: =R76*AN76 -> 0 | U76: =AW76*L76*J76 -> 0 | Z76: =IF(I76="CLT",(M76/220)*(1+encargos_mensalista),(M76/220)) -> 13.186636 | AA76: =Z76*(1+K76) -> 13.186636 | AB76: =AA76*(1+((incidência_do_dissídio/meses_obra)*dissídio_coletivo)) -> 13.763552 | AC76: =AB76*(1+(ociosidade_por_dia/9)) -> 13.763552 | AE76: =IF(I76="contrato",0,$N$11*$Q$11*$K$11) -> 0 | AF76: =IF(I76="contrato",0,$N$12*$Q$12*$K$12) -> 0 | AG76: =IF(I76="contrato",0,$N$13*$Q$13*$K$13) -> 0 | AH76: =IF(I76="contrato",0,$N$14*$Q$14*$K$14) -> 0 | AI76: =IF(I76="contrato",0,$N$14*$Q$15*$K$15) -> 0 | AJ76: =IF(I76="contrato",0,$N$14*$Q$16*$K$16) -> 0 | AL76: =IF(I76="contrato",0,ROUNDUP((M76/220)*(1+$AA$14)*(1+hora_extra_dias_úteis),2)) -> 14.83 | AM76: =IF(I76="contrato",0,ROUNDUP((M76/220)*(1+$AA$14)*(1+hora_extra_sábados),2)) -> 14.83 | AN76: =IF(I76="contrato",0,ROUNDUP((M76/220)*(1+$AA$14)*(1+hora_extra_domingos),2)) -> 18.53 | AO76: =IF(I76="contrato",0,ROUNDUP(AL76*(1+adicional_noturno),2)) -> 17.8 | AP76: =IF(I76="contrato",0,ROUNDUP(AM76*(1+adicional_noturno),2)) -> 17.8 | AQ76: =IF(I76="contrato",0,ROUNDUP(AN76*(1+adicional_noturno),2)) -> 22.24 | AS76: =IF(H76="Coordenação",0,L76*J76) -> 0 | AT76: =IF(H76="Coordenação",L76*J76,0) -> 0 | AV76: =IF(I76="CLT",IF(L76=0,0,P76*220+N76),(P76*220+N76+(O76/meses_obra))) -> 3027.9813 | AW76: =IF(I76="CLT",IF(L76=0,0,((P76*220)+(AE76*AL76)+(AF76*AM76)+(AG76*AN76)+(AH76*AO76)+(AI76*AP76)+(AJ76*AQ76)+N76)),AV76) -> 3027.9813 | AX76: =AV76*L76*J76 -> 0
A77: 4 | D77: 4.10 | E77: Servente - faxina de canteiro de obra - refeitório | H77: Apoio | I77: CLT | L77: =meses_obra -> 8 | M77: 1364 | O77: =IF(I77="CLT","N/A",(L77*(M77/12)*2)) -> N/A | P77: =IF(I77="contrato",AB77,AB77) -> 13.763552 | Q77: =AE77+AF77 -> 0 | R77: =AG77 -> 0 | S77: =Q77*AL77 -> 0 | T77: =R77*AN77 -> 0 | U77: =AW77*L77*J77 -> 0 | Z77: =IF(I77="CLT",(M77/220)*(1+encargos_mensalista),(M77/220)) -> 13.186636 | AA77: =Z77*(1+K77) -> 13.186636 | AB77: =AA77*(1+((incidência_do_dissídio/meses_obra)*dissídio_coletivo)) -> 13.763552 | AC77: =AB77*(1+(ociosidade_por_dia/9)) -> 13.763552 | AE77: =IF(I77="contrato",0,$N$11*$Q$11*$K$11) -> 0 | AF77: =IF(I77="contrato",0,$N$12*$Q$12*$K$12) -> 0 | AG77: =IF(I77="contrato",0,$N$13*$Q$13*$K$13) -> 0 | AH77: =IF(I77="contrato",0,$N$14*$Q$14*$K$14) -> 0 | AI77: =IF(I77="contrato",0,$N$14*$Q$15*$K$15) -> 0 | AJ77: =IF(I77="contrato",0,$N$14*$Q$16*$K$16) -> 0 | AL77: =IF(I77="contrato",0,ROUNDUP((M77/220)*(1+$AA$14)*(1+hora_extra_dias_úteis),2)) -> 14.83 | AM77: =IF(I77="contrato",0,ROUNDUP((M77/220)*(1+$AA$14)*(1+hora_extra_sábados),2)) -> 14.83 | AN77: =IF(I77="contrato",0,ROUNDUP((M77/220)*(1+$AA$14)*(1+hora_extra_domingos),2)) -> 18.53 | AO77: =IF(I77="contrato",0,ROUNDUP(AL77*(1+adicional_noturno),2)) -> 17.8 | AP77: =IF(I77="contrato",0,ROUNDUP(AM77*(1+adicional_noturno),2)) -> 17.8 | AQ77: =IF(I77="contrato",0,ROUNDUP(AN77*(1+adicional_noturno),2)) -> 22.24 | AS77: =IF(H77="Coordenação",0,L77*J77) -> 0 | AT77: =IF(H77="Coordenação",L77*J77,0) -> 0 | AV77: =IF(I77="CLT",IF(L77=0,0,P77*220+N77),(P77*220+N77+(O77/meses_obra))) -> 3027.9813 | AW77: =IF(I77="CLT",IF(L77=0,0,((P77*220)+(AE77*AL77)+(AF77*AM77)+(AG77*AN77)+(AH77*AO77)+(AI77*AP77)+(AJ77*AQ77)+N77)),AV77) -> 3027.9813 | AX77: =AV77*L77*J77 -> 0
A78: 4 | D78: 4.11 | E78: Portaria - Controle de acesso à obra | H78: Apoio | I78: CLT | L78: =meses_obra -> 8 | M78: 1364 | O78: =IF(I78="CLT","N/A",(L78*(M78/12)*2)) -> N/A | P78: =IF(I78="contrato",AB78,AB78) -> 13.763552 | Q78: =AE78+AF78 -> 0 | R78: =AG78 -> 0 | S78: =Q78*AL78 -> 0 | T78: =R78*AN78 -> 0 | U78: =AW78*L78*J78 -> 0 | Z78: =IF(I78="CLT",(M78/220)*(1+encargos_mensalista),(M78/220)) -> 13.186636 | AA78: =Z78*(1+K78) -> 13.186636 | AB78: =AA78*(1+((incidência_do_dissídio/meses_obra)*dissídio_coletivo)) -> 13.763552 | AC78: =AB78*(1+(ociosidade_por_dia/9)) -> 13.763552 | AE78: =IF(I78="contrato",0,$N$11*$Q$11*$K$11) -> 0 | AF78: =IF(I78="contrato",0,$N$12*$Q$12*$K$12) -> 0 | AG78: =IF(I78="contrato",0,$N$13*$Q$13*$K$13) -> 0 | AH78: =IF(I78="contrato",0,$N$14*$Q$14*$K$14) -> 0 | AI78: =IF(I78="contrato",0,$N$14*$Q$15*$K$15) -> 0 | AJ78: =IF(I78="contrato",0,$N$14*$Q$16*$K$16) -> 0 | AL78: =IF(I78="contrato",0,ROUNDUP((M78/220)*(1+$AA$14)*(1+hora_extra_dias_úteis),2)) -> 14.83 | AM78: =IF(I78="contrato",0,ROUNDUP((M78/220)*(1+$AA$14)*(1+hora_extra_sábados),2)) -> 14.83 | AN78: =IF(I78="contrato",0,ROUNDUP((M78/220)*(1+$AA$14)*(1+hora_extra_domingos),2)) -> 18.53 | AO78: =IF(I78="contrato",0,ROUNDUP(AL78*(1+adicional_noturno),2)) -> 17.8 | AP78: =IF(I78="contrato",0,ROUNDUP(AM78*(1+adicional_noturno),2)) -> 17.8 | AQ78: =IF(I78="contrato",0,ROUNDUP(AN78*(1+adicional_noturno),2)) -> 22.24 | AS78: =IF(H78="Coordenação",0,L78*J78) -> 0 | AT78: =IF(H78="Coordenação",L78*J78,0) -> 0 | AV78: =IF(I78="CLT",IF(L78=0,0,P78*220+N78),(P78*220+N78+(O78/meses_obra))) -> 3027.9813 | AW78: =IF(I78="CLT",IF(L78=0,0,((P78*220)+(AE78*AL78)+(AF78*AM78)+(AG78*AN78)+(AH78*AO78)+(AI78*AP78)+(AJ78*AQ78)+N78)),AV78) -> 3027.9813 | AX78: =AV78*L78*J78 -> 0
A79: 4 | D79: 4.12 | E79: Eletricista - apoio | H79: Apoio | I79: CLT | L79: =meses_obra -> 8 | M79: 2500 | N79: 0 | O79: =IF(I79="CLT","N/A",(L79*(M79/12)*2)) -> N/A | P79: =IF(I79="contrato",AB79,AB79) -> 25.226451 | Q79: =AE79+AF79 -> 0 | R79: =AG79 -> 0 | S79: =Q79*AL79 -> 0 | T79: =R79*AN79 -> 0 | U79: =AW79*L79*J79 -> 0 | Z79: =IF(I79="CLT",(M79/220)*(1+encargos_mensalista),(M79/220)) -> 24.169055 | AA79: =Z79*(1+K79) -> 24.169055 | AB79: =AA79*(1+((incidência_do_dissídio/meses_obra)*dissídio_coletivo)) -> 25.226451 | AC79: =AB79*(1+(ociosidade_por_dia/9)) -> 25.226451 | AE79: =IF(I79="contrato",0,$N$11*$Q$11*$K$11) -> 0 | AF79: =IF(I79="contrato",0,$N$12*$Q$12*$K$12) -> 0 | AG79: =IF(I79="contrato",0,$N$13*$Q$13*$K$13) -> 0 | AH79: =IF(I79="contrato",0,$N$14*$Q$14*$K$14) -> 0 | AI79: =IF(I79="contrato",0,$N$14*$Q$15*$K$15) -> 0 | AJ79: =IF(I79="contrato",0,$N$14*$Q$16*$K$16) -> 0 | AL79: =IF(I79="contrato",0,ROUNDUP((M79/220)*(1+$AA$14)*(1+hora_extra_dias_úteis),2)) -> 27.17 | AM79: =IF(I79="contrato",0,ROUNDUP((M79/220)*(1+$AA$14)*(1+hora_extra_sábados),2)) -> 27.17 | AN79: =IF(I79="contrato",0,ROUNDUP((M79/220)*(1+$AA$14)*(1+hora_extra_domingos),2)) -> 33.96 | AO79: =IF(I79="contrato",0,ROUNDUP(AL79*(1+adicional_noturno),2)) -> 32.61 | AP79: =IF(I79="contrato",0,ROUNDUP(AM79*(1+adicional_noturno),2)) -> 32.61 | AQ79: =IF(I79="contrato",0,ROUNDUP(AN79*(1+adicional_noturno),2)) -> 40.76 | AS79: =IF(H79="Coordenação",0,L79*J79) -> 0 | AT79: =IF(H79="Coordenação",L79*J79,0) -> 0 | AV79: =IF(I79="CLT",IF(L79=0,0,P79*220+N79),(P79*220+N79+(O79/meses_obra))) -> 5549.8192 | AW79: =IF(I79="CLT",IF(L79=0,0,((P79*220)+(AE79*AL79)+(AF79*AM79)+(AG79*AN79)+(AH79*AO79)+(AI79*AP79)+(AJ79*AQ79)+N79)),AV79) -> 5549.8192 | AX79: =AV79*L79*J79 -> 0
A80: 4 | D80: 4.13 | E80: Encanador - apoio | H80: Apoio | I80: CLT | L80: =meses_obra -> 8 | M80: 2500 | N80: 0 | O80: =IF(I80="CLT","N/A",(L80*(M80/12)*2)) -> N/A | P80: =IF(I80="contrato",AB80,AB80) -> 25.226451 | Q80: =AE80+AF80 -> 0 | R80: =AG80 -> 0 | S80: =Q80*AL80 -> 0 | T80: =R80*AN80 -> 0 | U80: =AW80*L80*J80 -> 0 | Z80: =IF(I80="CLT",(M80/220)*(1+encargos_mensalista),(M80/220)) -> 24.169055 | AA80: =Z80*(1+K80) -> 24.169055 | AB80: =AA80*(1+((incidência_do_dissídio/meses_obra)*dissídio_coletivo)) -> 25.226451 | AC80: =AB80*(1+(ociosidade_por_dia/9)) -> 25.226451 | AE80: =IF(I80="contrato",0,$N$11*$Q$11*$K$11) -> 0 | AF80: =IF(I80="contrato",0,$N$12*$Q$12*$K$12) -> 0 | AG80: =IF(I80="contrato",0,$N$13*$Q$13*$K$13) -> 0 | AH80: =IF(I80="contrato",0,$N$14*$Q$14*$K$14) -> 0 | AI80: =IF(I80="contrato",0,$N$14*$Q$15*$K$15) -> 0 | AJ80: =IF(I80="contrato",0,$N$14*$Q$16*$K$16) -> 0 | AL80: =IF(I80="contrato",0,ROUNDUP((M80/220)*(1+$AA$14)*(1+hora_extra_dias_úteis),2)) -> 27.17 | AM80: =IF(I80="contrato",0,ROUNDUP((M80/220)*(1+$AA$14)*(1+hora_extra_sábados),2)) -> 27.17 | AN80: =IF(I80="contrato",0,ROUNDUP((M80/220)*(1+$AA$14)*(1+hora_extra_domingos),2)) -> 33.96 | AO80: =IF(I80="contrato",0,ROUNDUP(AL80*(1+adicional_noturno),2)) -> 32.61 | AP80: =IF(I80="contrato",0,ROUNDUP(AM80*(1+adicional_noturno),2)) -> 32.61 | AQ80: =IF(I80="contrato",0,ROUNDUP(AN80*(1+adicional_noturno),2)) -> 40.76 | AS80: =IF(H80="Coordenação",0,L80*J80) -> 0 | AT80: =IF(H80="Coordenação",L80*J80,0) -> 0 | AV80: =IF(I80="CLT",IF(L80=0,0,P80*220+N80),(P80*220+N80+(O80/meses_obra))) -> 5549.8192 | AW80: =IF(I80="CLT",IF(L80=0,0,((P80*220)+(AE80*AL80)+(AF80*AM80)+(AG80*AN80)+(AH80*AO80)+(AI80*AP80)+(AJ80*AQ80)+N80)),AV80) -> 5549.8192 | AX80: =AV80*L80*J80 -> 0
A81: 4 | D81: 4.14 | E81: Zelador - administração de repúblicas | H81: Apoio | I81: CLT | L81: =meses_obra -> 8 | O81: =IF(I81="CLT","N/A",(L81*(M81/12)*2)) -> N/A | P81: =IF(I81="contrato",AB81,AB81) -> 0 | Q81: =AE81+AF81 -> 0 | R81: =AG81 -> 0 | S81: =Q81*AL81 -> 0 | T81: =R81*AN81 -> 0 | U81: =AW81*L81*J81 -> 0 | Z81: =IF(I81="CLT",(M81/220)*(1+encargos_mensalista),(M81/220)) -> 0 | AA81: =Z81*(1+K81) -> 0 | AB81: =AA81*(1+((incidência_do_dissídio/meses_obra)*dissídio_coletivo)) -> 0 | AC81: =AB81*(1+(ociosidade_por_dia/9)) -> 0 | AE81: =IF(I81="contrato",0,$N$11*$Q$11*$K$11) -> 0 | AF81: =IF(I81="contrato",0,$N$12*$Q$12*$K$12) -> 0 | AG81: =IF(I81="contrato",0,$N$13*$Q$13*$K$13) -> 0 | AH81: =IF(I81="contrato",0,$N$14*$Q$14*$K$14) -> 0 | AI81: =IF(I81="contrato",0,$N$14*$Q$15*$K$15) -> 0 | AJ81: =IF(I81="contrato",0,$N$14*$Q$16*$K$16) -> 0 | AL81: =IF(I81="contrato",0,ROUNDUP((M81/220)*(1+$AA$14)*(1+hora_extra_dias_úteis),2)) -> 0 | AM81: =IF(I81="contrato",0,ROUNDUP((M81/220)*(1+$AA$14)*(1+hora_extra_sábados),2)) -> 0 | AN81: =IF(I81="contrato",0,ROUNDUP((M81/220)*(1+$AA$14)*(1+hora_extra_domingos),2)) -> 0 | AO81: =IF(I81="contrato",0,ROUNDUP(AL81*(1+adicional_noturno),2)) -> 0 | AP81: =IF(I81="contrato",0,ROUNDUP(AM81*(1+adicional_noturno),2)) -> 0 | AQ81: =IF(I81="contrato",0,ROUNDUP(AN81*(1+adicional_noturno),2)) -> 0 | AS81: =IF(H81="Coordenação",0,L81*J81) -> 0 | AT81: =IF(H81="Coordenação",L81*J81,0) -> 0 | AV81: =IF(I81="CLT",IF(L81=0,0,P81*220+N81),(P81*220+N81+(O81/meses_obra))) -> 0 | AW81: =IF(I81="CLT",IF(L81=0,0,((P81*220)+(AE81*AL81)+(AF81*AM81)+(AG81*AN81)+(AH81*AO81)+(AI81*AP81)+(AJ81*AQ81)+N81)),AV81) -> 0 | AX81: =AV81*L81*J81 -> 0
A82: 4 | D82: 4.15 | E82: Servente - faxina de repúblicas | H82: Apoio | I82: CLT | L82: =meses_obra -> 8 | O82: =IF(I82="CLT","N/A",(L82*(M82/12)*2)) -> N/A | P82: =IF(I82="contrato",AB82,AB82) -> 0 | Q82: =AE82+AF82 -> 0 | R82: =AG82 -> 0 | S82: =Q82*AL82 -> 0 | T82: =R82*AN82 -> 0 | U82: =AW82*L82*J82 -> 0 | Z82: =IF(I82="CLT",(M82/220)*(1+encargos_mensalista),(M82/220)) -> 0 | AA82: =Z82*(1+K82) -> 0 | AB82: =AA82*(1+((incidência_do_dissídio/meses_obra)*dissídio_coletivo)) -> 0 | AC82: =AB82*(1+(ociosidade_por_dia/9)) -> 0 | AE82: =IF(I82="contrato",0,$N$11*$Q$11*$K$11) -> 0 | AF82: =IF(I82="contrato",0,$N$12*$Q$12*$K$12) -> 0 | AG82: =IF(I82="contrato",0,$N$13*$Q$13*$K$13) -> 0 | AH82: =IF(I82="contrato",0,$N$14*$Q$14*$K$14) -> 0 | AI82: =IF(I82="contrato",0,$N$14*$Q$15*$K$15) -> 0 | AJ82: =IF(I82="contrato",0,$N$14*$Q$16*$K$16) -> 0 | AL82: =IF(I82="contrato",0,ROUNDUP((M82/220)*(1+$AA$14)*(1+hora_extra_dias_úteis),2)) -> 0 | AM82: =IF(I82="contrato",0,ROUNDUP((M82/220)*(1+$AA$14)*(1+hora_extra_sábados),2)) -> 0 | AN82: =IF(I82="contrato",0,ROUNDUP((M82/220)*(1+$AA$14)*(1+hora_extra_domingos),2)) -> 0 | AO82: =IF(I82="contrato",0,ROUNDUP(AL82*(1+adicional_noturno),2)) -> 0 | AP82: =IF(I82="contrato",0,ROUNDUP(AM82*(1+adicional_noturno),2)) -> 0 | AQ82: =IF(I82="contrato",0,ROUNDUP(AN82*(1+adicional_noturno),2)) -> 0 | AS82: =IF(H82="Coordenação",0,L82*J82) -> 0 | AT82: =IF(H82="Coordenação",L82*J82,0) -> 0 | AV82: =IF(I82="CLT",IF(L82=0,0,P82*220+N82),(P82*220+N82+(O82/meses_obra))) -> 0 | AW82: =IF(I82="CLT",IF(L82=0,0,((P82*220)+(AE82*AL82)+(AF82*AM82)+(AG82*AN82)+(AH82*AO82)+(AI82*AP82)+(AJ82*AQ82)+N82)),AV82) -> 0 | AX82: =AV82*L82*J82 -> 0
A83: 4 | D83: 4.16 | I83: CLT | L83: =meses_obra -> 8 | O83: =IF(I83="CLT","N/A",(L83*(M83/12)*2)) -> N/A | P83: =IF(I83="contrato",AB83,AB83) -> 0 | Q83: =AE83+AF83 -> 0 | R83: =AG83 -> 0 | S83: =Q83*AL83 -> 0 | T83: =R83*AN83 -> 0 | U83: =AW83*L83*J83 -> 0 | Z83: =IF(I83="CLT",(M83/220)*(1+encargos_mensalista),(M83/220)) -> 0 | AA83: =Z83*(1+K83) -> 0 | AB83: =AA83*(1+((incidência_do_dissídio/meses_obra)*dissídio_coletivo)) -> 0 | AC83: =AB83*(1+(ociosidade_por_dia/9)) -> 0 | AE83: =IF(I83="contrato",0,$N$11*$Q$11*$K$11) -> 0 | AF83: =IF(I83="contrato",0,$N$12*$Q$12*$K$12) -> 0 | AG83: =IF(I83="contrato",0,$N$13*$Q$13*$K$13) -> 0 | AH83: =IF(I83="contrato",0,$N$14*$Q$14*$K$14) -> 0 | AI83: =IF(I83="contrato",0,$N$14*$Q$15*$K$15) -> 0 | AJ83: =IF(I83="contrato",0,$N$14*$Q$16*$K$16) -> 0 | AL83: =IF(I83="contrato",0,ROUNDUP((M83/220)*(1+$AA$14)*(1+hora_extra_dias_úteis),2)) -> 0 | AM83: =IF(I83="contrato",0,ROUNDUP((M83/220)*(1+$AA$14)*(1+hora_extra_sábados),2)) -> 0 | AN83: =IF(I83="contrato",0,ROUNDUP((M83/220)*(1+$AA$14)*(1+hora_extra_domingos),2)) -> 0 | AO83: =IF(I83="contrato",0,ROUNDUP(AL83*(1+adicional_noturno),2)) -> 0 | AP83: =IF(I83="contrato",0,ROUNDUP(AM83*(1+adicional_noturno),2)) -> 0 | AQ83: =IF(I83="contrato",0,ROUNDUP(AN83*(1+adicional_noturno),2)) -> 0 | AS83: =IF(H83="Coordenação",0,L83*J83) -> 0 | AT83: =IF(H83="Coordenação",L83*J83,0) -> 0 | AV83: =IF(I83="CLT",IF(L83=0,0,P83*220+N83),(P83*220+N83+(O83/meses_obra))) -> 0 | AW83: =IF(I83="CLT",IF(L83=0,0,((P83*220)+(AE83*AL83)+(AF83*AM83)+(AG83*AN83)+(AH83*AO83)+(AI83*AP83)+(AJ83*AQ83)+N83)),AV83) -> 0 | AX83: =AV83*L83*J83 -> 0
A85: S | D85: 05 | E85: Medicina e segurança do trabalho | J85: Qtde | K85: Transferencia | L85: ΔT em obra | M85: Base | N85: Ajuda ou bonus | U85: =SUMIF(A:A,D85,U:U) -> 0 | V85: =$AX$85/custo_direto -> 0 | Z85: com L.S. | AA85: Transf | AB85: Dissidio | AC85: Ossiosidade | AE85: HE d.útil | AF85: Qtd sáb | AG85: Qtd dom | AH85: HE d.útil | AI85: Qtd sáb | AJ85: Qtd dom | AL85: VH.d.útil | AM85: VH.sáb | AN85: VH.dom | AO85: VH.d.útil | AP85: VH.sáb | AQ85: VH.dom | AS85: Supervisão | AT85: Coordenação | AX85: =SUMIF(A:A,D85,AX:AX) -> 0
A86: 5 | D86: 5.01 | E86: Engenheiro de Segurança | H86: Coordenação | I86: Contrato | L86: =meses_obra -> 8 | M86: 8500 | N86: 2000 | O86: =IF(I86="CLT","N/A",(L86*(M86/12)*2)) -> 11333.333 | P86: =IF(I86="contrato",AB86,AB86) -> 40.326705 | Q86: =AE86+AF86 -> 0 | R86: =AG86 -> 0 | S86: =Q86*AL86 -> 0 | T86: =R86*AN86 -> 0 | U86: =AW86*L86*J86 -> 0 | Z86: =IF(I86="CLT",(M86/220)*(1+encargos_mensalista),(M86/220)) -> 38.636364 | AA86: =Z86*(1+K86) -> 38.636364 | AB86: =AA86*(1+((incidência_do_dissídio/meses_obra)*dissídio_coletivo)) -> 40.326705 | AC86: =AB86*(1+(ociosidade_por_dia/9)) -> 40.326705 | AE86: =IF(I86="contrato",0,$N$11*$Q$11*$K$11) -> 0 | AF86: =IF(I86="contrato",0,$N$12*$Q$12*$K$12) -> 0 | AG86: =IF(I86="contrato",0,$N$13*$Q$13*$K$13) -> 0 | AH86: =IF(I86="contrato",0,$N$14*$Q$14*$K$14) -> 0 | AI86: =IF(I86="contrato",0,$N$14*$Q$15*$K$15) -> 0 | AJ86: =IF(I86="contrato",0,$N$14*$Q$16*$K$16) -> 0 | AL86: =IF(I86="contrato",0,ROUNDUP((M86/220)*(1+$AA$14)*(1+hora_extra_dias_úteis),2)) -> 0 | AM86: =IF(I86="contrato",0,ROUNDUP((M86/220)*(1+$AA$14)*(1+hora_extra_sábados),2)) -> 0 | AN86: =IF(I86="contrato",0,ROUNDUP((M86/220)*(1+$AA$14)*(1+hora_extra_domingos),2)) -> 0 | AO86: =IF(I86="contrato",0,ROUNDUP(AL86*(1+adicional_noturno),2)) -> 0 | AP86: =IF(I86="contrato",0,ROUNDUP(AM86*(1+adicional_noturno),2)) -> 0 | AQ86: =IF(I86="contrato",0,ROUNDUP(AN86*(1+adicional_noturno),2)) -> 0 | AS86: =IF(H86="Coordenação",0,L86*J86) -> 0 | AT86: =IF(H86="Coordenação",L86*J86,0) -> 0 | AV86: =IF(I86="CLT",IF(L86=0,0,P86*220+N86),(P86*220+N86+(O86/meses_obra))) -> 12288.542 | AW86: =IF(I86="CLT",IF(L86=0,0,((P86*220)+(AE86*AL86)+(AF86*AM86)+(AG86*AN86)+(AH86*AO86)+(AI86*AP86)+(AJ86*AQ86)+N86)),AV86) -> 12288.542 | AX86: =AV86*L86*J86 -> 0
A87: 5 | D87: 5.02 | E87: Médico do Trabalho | H87: SST | I87: Contrato | L87: =meses_obra -> 8 | M87: 6000 | N87: 2000 | O87: =IF(I87="CLT","N/A",(L87*(M87/12)*2)) -> 8000 | P87: =IF(I87="contrato",AB87,AB87) -> 28.465909 | Q87: =AE87+AF87 -> 0 | R87: =AG87 -> 0 | S87: =Q87*AL87 -> 0 | T87: =R87*AN87 -> 0 | U87: =AW87*L87*J87 -> 0 | Z87: =IF(I87="CLT",(M87/220)*(1+encargos_mensalista),(M87/220)) -> 27.272727 | AA87: =Z87*(1+K87) -> 27.272727 | AB87: =AA87*(1+((incidência_do_dissídio/meses_obra)*dissídio_coletivo)) -> 28.465909 | AC87: =AB87*(1+(ociosidade_por_dia/9)) -> 28.465909 | AE87: =IF(I87="contrato",0,$N$11*$Q$11*$K$11) -> 0 | AF87: =IF(I87="contrato",0,$N$12*$Q$12*$K$12) -> 0 | AG87: =IF(I87="contrato",0,$N$13*$Q$13*$K$13) -> 0 | AH87: =IF(I87="contrato",0,$N$14*$Q$14*$K$14) -> 0 | AI87: =IF(I87="contrato",0,$N$14*$Q$15*$K$15) -> 0 | AJ87: =IF(I87="contrato",0,$N$14*$Q$16*$K$16) -> 0 | AL87: =IF(I87="contrato",0,ROUNDUP((M87/220)*(1+$AA$14)*(1+hora_extra_dias_úteis),2)) -> 0 | AM87: =IF(I87="contrato",0,ROUNDUP((M87/220)*(1+$AA$14)*(1+hora_extra_sábados),2)) -> 0 | AN87: =IF(I87="contrato",0,ROUNDUP((M87/220)*(1+$AA$14)*(1+hora_extra_domingos),2)) -> 0 | AO87: =IF(I87="contrato",0,ROUNDUP(AL87*(1+adicional_noturno),2)) -> 0 | AP87: =IF(I87="contrato",0,ROUNDUP(AM87*(1+adicional_noturno),2)) -> 0 | AQ87: =IF(I87="contrato",0,ROUNDUP(AN87*(1+adicional_noturno),2)) -> 0 | AS87: =IF(H87="Coordenação",0,L87*J87) -> 0 | AT87: =IF(H87="Coordenação",L87*J87,0) -> 0 | AV87: =IF(I87="CLT",IF(L87=0,0,P87*220+N87),(P87*220+N87+(O87/meses_obra))) -> 9262.5 | AW87: =IF(I87="CLT",IF(L87=0,0,((P87*220)+(AE87*AL87)+(AF87*AM87)+(AG87*AN87)+(AH87*AO87)+(AI87*AP87)+(AJ87*AQ87)+N87)),AV87) -> 9262.5 | AX87: =AV87*L87*J87 -> 0
A88: 5 | D88: 5.03 | E88: Técnico de Segurança - I | H88: SST | I88: Contrato | L88: =meses_obra -> 8 | M88: 5000 | N88: 2000 | O88: =IF(I88="CLT","N/A",(L88*(M88/12)*2)) -> 6666.6667 | P88: =IF(I88="contrato",AB88,AB88) -> 23.721591 | Q88: =AE88+AF88 -> 0 | R88: =AG88 -> 0 | S88: =Q88*AL88 -> 0 | T88: =R88*AN88 -> 0 | U88: =AW88*L88*J88 -> 0 | Z88: =IF(I88="CLT",(M88/220)*(1+encargos_mensalista),(M88/220)) -> 22.727273 | AA88: =Z88*(1+K88) -> 22.727273 | AB88: =AA88*(1+((incidência_do_dissídio/meses_obra)*dissídio_coletivo)) -> 23.721591 | AC88: =AB88*(1+(ociosidade_por_dia/9)) -> 23.721591 | AE88: =IF(I88="contrato",0,$N$11*$Q$11*$K$11) -> 0 | AF88: =IF(I88="contrato",0,$N$12*$Q$12*$K$12) -> 0 | AG88: =IF(I88="contrato",0,$N$13*$Q$13*$K$13) -> 0 | AH88: =IF(I88="contrato",0,$N$14*$Q$14*$K$14) -> 0 | AI88: =IF(I88="contrato",0,$N$14*$Q$15*$K$15) -> 0 | AJ88: =IF(I88="contrato",0,$N$14*$Q$16*$K$16) -> 0 | AL88: =IF(I88="contrato",0,ROUNDUP((M88/220)*(1+$AA$14)*(1+hora_extra_dias_úteis),2)) -> 0 | AM88: =IF(I88="contrato",0,ROUNDUP((M88/220)*(1+$AA$14)*(1+hora_extra_sábados),2)) -> 0 | AN88: =IF(I88="contrato",0,ROUNDUP((M88/220)*(1+$AA$14)*(1+hora_extra_domingos),2)) -> 0 | AO88: =IF(I88="contrato",0,ROUNDUP(AL88*(1+adicional_noturno),2)) -> 0 | AP88: =IF(I88="contrato",0,ROUNDUP(AM88*(1+adicional_noturno),2)) -> 0 | AQ88: =IF(I88="contrato",0,ROUNDUP(AN88*(1+adicional_noturno),2)) -> 0 | AS88: =IF(H88="Coordenação",0,L88*J88) -> 0 | AT88: =IF(H88="Coordenação",L88*J88,0) -> 0 | AV88: =IF(I88="CLT",IF(L88=0,0,P88*220+N88),(P88*220+N88+(O88/meses_obra))) -> 8052.0833 | AW88: =IF(I88="CLT",IF(L88=0,0,((P88*220)+(AE88*AL88)+(AF88*AM88)+(AG88*AN88)+(AH88*AO88)+(AI88*AP88)+(AJ88*AQ88)+N88)),AV88) -> 8052.0833 | AX88: =AV88*L88*J88 -> 0
A89: 5 | D89: 5.04 | E89: Técnico de Segurança auxiliar | H89: SST | I89: Contrato | L89: =meses_obra -> 8 | M89: 4000 | O89: =IF(I89="CLT","N/A",(L89*(M89/12)*2)) -> 5333.3333 | P89: =IF(I89="contrato",AB89,AB89) -> 18.977273 | Q89: =AE89+AF89 -> 0 | R89: =AG89 -> 0 | S89: =Q89*AL89 -> 0 | T89: =R89*AN89 -> 0 | U89: =AW89*L89*J89 -> 0 | Z89: =IF(I89="CLT",(M89/220)*(1+encargos_mensalista),(M89/220)) -> 18.181818 | AA89: =Z89*(1+K89) -> 18.181818 | AB89: =AA89*(1+((incidência_do_dissídio/meses_obra)*dissídio_coletivo)) -> 18.977273 | AC89: =AB89*(1+(ociosidade_por_dia/9)) -> 18.977273 | AE89: =IF(I89="contrato",0,$N$11*$Q$11*$K$11) -> 0 | AF89: =IF(I89="contrato",0,$N$12*$Q$12*$K$12) -> 0 | AG89: =IF(I89="contrato",0,$N$13*$Q$13*$K$13) -> 0 | AH89: =IF(I89="contrato",0,$N$14*$Q$14*$K$14) -> 0 | AI89: =IF(I89="contrato",0,$N$14*$Q$15*$K$15) -> 0 | AJ89: =IF(I89="contrato",0,$N$14*$Q$16*$K$16) -> 0 | AL89: =IF(I89="contrato",0,ROUNDUP((M89/220)*(1+$AA$14)*(1+hora_extra_dias_úteis),2)) -> 0 | AM89: =IF(I89="contrato",0,ROUNDUP((M89/220)*(1+$AA$14)*(1+hora_extra_sábados),2)) -> 0 | AN89: =IF(I89="contrato",0,ROUNDUP((M89/220)*(1+$AA$14)*(1+hora_extra_domingos),2)) -> 0 | AO89: =IF(I89="contrato",0,ROUNDUP(AL89*(1+adicional_noturno),2)) -> 0 | AP89: =IF(I89="contrato",0,ROUNDUP(AM89*(1+adicional_noturno),2)) -> 0 | AQ89: =IF(I89="contrato",0,ROUNDUP(AN89*(1+adicional_noturno),2)) -> 0 | AS89: =IF(H89="Coordenação",0,L89*J89) -> 0 | AT89: =IF(H89="Coordenação",L89*J89,0) -> 0 | AV89: =IF(I89="CLT",IF(L89=0,0,P89*220+N89),(P89*220+N89+(O89/meses_obra))) -> 4841.6667 | AW89: =IF(I89="CLT",IF(L89=0,0,((P89*220)+(AE89*AL89)+(AF89*AM89)+(AG89*AN89)+(AH89*AO89)+(AI89*AP89)+(AJ89*AQ89)+N89)),AV89) -> 4841.6667 | AX89: =AV89*L89*J89 -> 0
A90: 5 | D90: 5.05 | E90: Aux de Enfermaria | H90: SST | I90: CLT | L90: =meses_obra -> 8 | M90: 1600 | O90: =IF(I90="CLT","N/A",(L90*(M90/12)*2)) -> N/A | P90: =IF(I90="contrato",AB90,AB90) -> 16.144929 | Q90: =AE90+AF90 -> 0 | R90: =AG90 -> 0 | S90: =Q90*AL90 -> 0 | T90: =R90*AN90 -> 0 | U90: =AW90*L90*J90 -> 0 | Z90: =IF(I90="CLT",(M90/220)*(1+encargos_mensalista),(M90/220)) -> 15.468195 | AA90: =Z90*(1+K90) -> 15.468195 | AB90: =AA90*(1+((incidência_do_dissídio/meses_obra)*dissídio_coletivo)) -> 16.144929 | AC90: =AB90*(1+(ociosidade_por_dia/9)) -> 16.144929 | AE90: =IF(I90="contrato",0,$N$11*$Q$11*$K$11) -> 0 | AF90: =IF(I90="contrato",0,$N$12*$Q$12*$K$12) -> 0 | AG90: =IF(I90="contrato",0,$N$13*$Q$13*$K$13) -> 0 | AH90: =IF(I90="contrato",0,$N$14*$Q$14*$K$14) -> 0 | AI90: =IF(I90="contrato",0,$N$14*$Q$15*$K$15) -> 0 | AJ90: =IF(I90="contrato",0,$N$14*$Q$16*$K$16) -> 0 | AL90: =IF(I90="contrato",0,ROUNDUP((M90/220)*(1+$AA$14)*(1+hora_extra_dias_úteis),2)) -> 17.39 | AM90: =IF(I90="contrato",0,ROUNDUP((M90/220)*(1+$AA$14)*(1+hora_extra_sábados),2)) -> 17.39 | AN90: =IF(I90="contrato",0,ROUNDUP((M90/220)*(1+$AA$14)*(1+hora_extra_domingos),2)) -> 21.74 | AO90: =IF(I90="contrato",0,ROUNDUP(AL90*(1+adicional_noturno),2)) -> 20.87 | AP90: =IF(I90="contrato",0,ROUNDUP(AM90*(1+adicional_noturno),2)) -> 20.87 | AQ90: =IF(I90="contrato",0,ROUNDUP(AN90*(1+adicional_noturno),2)) -> 26.09 | AS90: =IF(H90="Coordenação",0,L90*J90) -> 0 | AT90: =IF(H90="Coordenação",L90*J90,0) -> 0 | AV90: =IF(I90="CLT",IF(L90=0,0,P90*220+N90),(P90*220+N90+(O90/meses_obra))) -> 3551.8843 | AW90: =IF(I90="CLT",IF(L90=0,0,((P90*220)+(AE90*AL90)+(AF90*AM90)+(AG90*AN90)+(AH90*AO90)+(AI90*AP90)+(AJ90*AQ90)+N90)),AV90) -> 3551.8843 | AX90: =AV90*L90*J90 -> 0
A91: 5 | D91: 5.06 | E91: Bombeiro | H91: SST | I91: CLT | L91: =meses_obra -> 8 | M91: 3000 | O91: =IF(I91="CLT","N/A",(L91*(M91/12)*2)) -> N/A | P91: =IF(I91="contrato",AB91,AB91) -> 30.271741 | Q91: =AE91+AF91 -> 0 | R91: =AG91 -> 0 | S91: =Q91*AL91 -> 0 | T91: =R91*AN91 -> 0 | U91: =AW91*L91*J91 -> 0 | Z91: =IF(I91="CLT",(M91/220)*(1+encargos_mensalista),(M91/220)) -> 29.002866 | AA91: =Z91*(1+K91) -> 29.002866 | AB91: =AA91*(1+((incidência_do_dissídio/meses_obra)*dissídio_coletivo)) -> 30.271741 | AC91: =AB91*(1+(ociosidade_por_dia/9)) -> 30.271741 | AE91: =IF(I91="contrato",0,$N$11*$Q$11*$K$11) -> 0 | AF91: =IF(I91="contrato",0,$N$12*$Q$12*$K$12) -> 0 | AG91: =IF(I91="contrato",0,$N$13*$Q$13*$K$13) -> 0 | AH91: =IF(I91="contrato",0,$N$14*$Q$14*$K$14) -> 0 | AI91: =IF(I91="contrato",0,$N$14*$Q$15*$K$15) -> 0 | AJ91: =IF(I91="contrato",0,$N$14*$Q$16*$K$16) -> 0 | AL91: =IF(I91="contrato",0,ROUNDUP((M91/220)*(1+$AA$14)*(1+hora_extra_dias_úteis),2)) -> 32.61 | AM91: =IF(I91="contrato",0,ROUNDUP((M91/220)*(1+$AA$14)*(1+hora_extra_sábados),2)) -> 32.61 | AN91: =IF(I91="contrato",0,ROUNDUP((M91/220)*(1+$AA$14)*(1+hora_extra_domingos),2)) -> 40.76 | AO91: =IF(I91="contrato",0,ROUNDUP(AL91*(1+adicional_noturno),2)) -> 39.14 | AP91: =IF(I91="contrato",0,ROUNDUP(AM91*(1+adicional_noturno),2)) -> 39.14 | AQ91: =IF(I91="contrato",0,ROUNDUP(AN91*(1+adicional_noturno),2)) -> 48.92 | AS91: =IF(H91="Coordenação",0,L91*J91) -> 0 | AT91: =IF(H91="Coordenação",L91*J91,0) -> 0 | AV91: =IF(I91="CLT",IF(L91=0,0,P91*220+N91),(P91*220+N91+(O91/meses_obra))) -> 6659.783 | AW91: =IF(I91="CLT",IF(L91=0,0,((P91*220)+(AE91*AL91)+(AF91*AM91)+(AG91*AN91)+(AH91*AO91)+(AI91*AP91)+(AJ91*AQ91)+N91)),AV91) -> 6659.783 | AX91: =AV91*L91*J91 -> 0
A92: 5 | D92: 5.07 | E92: Técnico Ambiental | H92: SST | I92: CLT | L92: =meses_obra -> 8 | M92: 3500 | O92: =IF(I92="CLT","N/A",(L92*(M92/12)*2)) -> N/A | P92: =IF(I92="contrato",AB92,AB92) -> 35.317031 | Q92: =AE92+AF92 -> 0 | R92: =AG92 -> 0 | S92: =Q92*AL92 -> 0 | T92: =R92*AN92 -> 0 | U92: =AW92*L92*J92 -> 0 | Z92: =IF(I92="CLT",(M92/220)*(1+encargos_mensalista),(M92/220)) -> 33.836677 | AA92: =Z92*(1+K92) -> 33.836677 | AB92: =AA92*(1+((incidência_do_dissídio/meses_obra)*dissídio_coletivo)) -> 35.317031 | AC92: =AB92*(1+(ociosidade_por_dia/9)) -> 35.317031 | AE92: =IF(I92="contrato",0,$N$11*$Q$11*$K$11) -> 0 | AF92: =IF(I92="contrato",0,$N$12*$Q$12*$K$12) -> 0 | AG92: =IF(I92="contrato",0,$N$13*$Q$13*$K$13) -> 0 | AH92: =IF(I92="contrato",0,$N$14*$Q$14*$K$14) -> 0 | AI92: =IF(I92="contrato",0,$N$14*$Q$15*$K$15) -> 0 | AJ92: =IF(I92="contrato",0,$N$14*$Q$16*$K$16) -> 0 | AL92: =IF(I92="contrato",0,ROUNDUP((M92/220)*(1+$AA$14)*(1+hora_extra_dias_úteis),2)) -> 38.04 | AM92: =IF(I92="contrato",0,ROUNDUP((M92/220)*(1+$AA$14)*(1+hora_extra_sábados),2)) -> 38.04 | AN92: =IF(I92="contrato",0,ROUNDUP((M92/220)*(1+$AA$14)*(1+hora_extra_domingos),2)) -> 47.55 | AO92: =IF(I92="contrato",0,ROUNDUP(AL92*(1+adicional_noturno),2)) -> 45.65 | AP92: =IF(I92="contrato",0,ROUNDUP(AM92*(1+adicional_noturno),2)) -> 45.65 | AQ92: =IF(I92="contrato",0,ROUNDUP(AN92*(1+adicional_noturno),2)) -> 57.06 | AS92: =IF(H92="Coordenação",0,L92*J92) -> 0 | AT92: =IF(H92="Coordenação",L92*J92,0) -> 0 | AV92: =IF(I92="CLT",IF(L92=0,0,P92*220+N92),(P92*220+N92+(O92/meses_obra))) -> 7769.7469 | AW92: =IF(I92="CLT",IF(L92=0,0,((P92*220)+(AE92*AL92)+(AF92*AM92)+(AG92*AN92)+(AH92*AO92)+(AI92*AP92)+(AJ92*AQ92)+N92)),AV92) -> 7769.7469 | AX92: =AV92*L92*J92 -> 0
A94: S | D94: 06 | E94: Segurança patrimonial | J94: Qtde | K94: Transferencia | L94: ΔT em obra | M94: Base | N94: Ajuda ou bonus | U94: =SUMIF(A:A,D94,U:U) -> 0 | V94: =$AX$94/custo_direto -> 0 | Z94: com L.S. | AA94: Transf | AB94: Dissidio | AC94: Ossiosidade | AE94: HE d.útil | AF94: Qtd sáb | AG94: Qtd dom | AH94: HE d.útil | AI94: Qtd sáb | AJ94: Qtd dom | AL94: VH.d.útil | AM94: VH.sáb | AN94: VH.dom | AO94: VH.d.útil | AP94: VH.sáb | AQ94: VH.dom | AS94: Supervisão | AT94: Coordenação | AX94: =SUMIF(A:A,D94,AX:AX) -> 0
A95: 6 | D95: 6.01 | E95: Vigilância armada da obra - equipe diuturno | H95: Segurança | I95: Contrato | L95: =meses_obra -> 8 | M95: 19000 | O95: =IF(I95="CLT","N/A",(L95*(M95/12)*2)) -> 25333.333 | P95: =IF(I95="contrato",AB95,AB95) -> 90.142045 | Q95: =AE95+AF95 -> 0 | R95: =AG95 -> 0 | S95: =Q95*AL95 -> 0 | T95: =R95*AN95 -> 0 | U95: =AW95*L95*J95 -> 0 | Z95: =IF(I95="CLT",(M95/220)*(1+encargos_mensalista),(M95/220)) -> 86.363636 | AA95: =Z95*(1+K95) -> 86.363636 | AB95: =AA95*(1+((incidência_do_dissídio/meses_obra)*dissídio_coletivo)) -> 90.142045 | AC95: =AB95*(1+(ociosidade_por_dia/9)) -> 90.142045 | AE95: =IF(I95="contrato",0,$N$11*$Q$11*$K$11) -> 0 | AF95: =IF(I95="contrato",0,$N$12*$Q$12*$K$12) -> 0 | AG95: =IF(I95="contrato",0,$N$13*$Q$13*$K$13) -> 0 | AH95: =IF(I95="contrato",0,$N$14*$Q$14*$K$14) -> 0 | AI95: =IF(I95="contrato",0,$N$14*$Q$15*$K$15) -> 0 | AJ95: =IF(I95="contrato",0,$N$14*$Q$16*$K$16) -> 0 | AL95: =IF(I95="contrato",0,ROUNDUP((M95/220)*(1+$AA$14)*(1+hora_extra_dias_úteis),2)) -> 0 | AM95: =IF(I95="contrato",0,ROUNDUP((M95/220)*(1+$AA$14)*(1+hora_extra_sábados),2)) -> 0 | AN95: =IF(I95="contrato",0,ROUNDUP((M95/220)*(1+$AA$14)*(1+hora_extra_domingos),2)) -> 0 | AO95: =IF(I95="contrato",0,ROUNDUP(AL95*(1+adicional_noturno),2)) -> 0 | AP95: =IF(I95="contrato",0,ROUNDUP(AM95*(1+adicional_noturno),2)) -> 0 | AQ95: =IF(I95="contrato",0,ROUNDUP(AN95*(1+adicional_noturno),2)) -> 0 | AS95: =IF(H95="Coordenação",0,L95*J95) -> 0 | AT95: =IF(H95="Coordenação",L95*J95,0) -> 0 | AV95: =IF(I95="CLT",IF(L95=0,0,P95*220+N95),(P95*220+N95+(O95/meses_obra))) -> 22997.917 | AW95: =IF(I95="CLT",IF(L95=0,0,((P95*220)+(AE95*AL95)+(AF95*AM95)+(AG95*AN95)+(AH95*AO95)+(AI95*AP95)+(AJ95*AQ95)+N95)),AV95) -> 22997.917 | AX95: =AV95*L95*J95 -> 0
A96: 6 | D96: 6.02 | E96: Vigilância armada da obra - equipe noturno | H96: Segurança | I96: Contrato | L96: =meses_obra -> 8 | M96: 1816.32 | O96: =IF(I96="CLT","N/A",(L96*(M96/12)*2)) -> 2421.76 | P96: =IF(I96="contrato",AB96,AB96) -> 8.6172 | Q96: =AE96+AF96 -> 0 | R96: =AG96 -> 0 | S96: =Q96*AL96 -> 0 | T96: =R96*AN96 -> 0 | U96: =AW96*L96*J96 -> 0 | Z96: =IF(I96="CLT",(M96/220)*(1+encargos_mensalista),(M96/220)) -> 8.256 | AA96: =Z96*(1+K96) -> 8.256 | AB96: =AA96*(1+((incidência_do_dissídio/meses_obra)*dissídio_coletivo)) -> 8.6172 | AC96: =AB96*(1+(ociosidade_por_dia/9)) -> 8.6172 | AE96: =IF(I96="contrato",0,$N$11*$Q$11*$K$11) -> 0 | AF96: =IF(I96="contrato",0,$N$12*$Q$12*$K$12) -> 0 | AG96: =IF(I96="contrato",0,$N$13*$Q$13*$K$13) -> 0 | AH96: =IF(I96="contrato",0,$N$14*$Q$14*$K$14) -> 0 | AI96: =IF(I96="contrato",0,$N$14*$Q$15*$K$15) -> 0 | AJ96: =IF(I96="contrato",0,$N$14*$Q$16*$K$16) -> 0 | AL96: =IF(I96="contrato",0,ROUNDUP((M96/220)*(1+$AA$14)*(1+hora_extra_dias_úteis),2)) -> 0 | AM96: =IF(I96="contrato",0,ROUNDUP((M96/220)*(1+$AA$14)*(1+hora_extra_sábados),2)) -> 0 | AN96: =IF(I96="contrato",0,ROUNDUP((M96/220)*(1+$AA$14)*(1+hora_extra_domingos),2)) -> 0 | AO96: =IF(I96="contrato",0,ROUNDUP(AL96*(1+adicional_noturno),2)) -> 0 | AP96: =IF(I96="contrato",0,ROUNDUP(AM96*(1+adicional_noturno),2)) -> 0 | AQ96: =IF(I96="contrato",0,ROUNDUP(AN96*(1+adicional_noturno),2)) -> 0 | AS96: =IF(H96="Coordenação",0,L96*J96) -> 0 | AT96: =IF(H96="Coordenação",L96*J96,0) -> 0 | AV96: =IF(I96="CLT",IF(L96=0,0,P96*220+N96),(P96*220+N96+(O96/meses_obra))) -> 2198.504 | AW96: =IF(I96="CLT",IF(L96=0,0,((P96*220)+(AE96*AL96)+(AF96*AM96)+(AG96*AN96)+(AH96*AO96)+(AI96*AP96)+(AJ96*AQ96)+N96)),AV96) -> 2198.504 | AX96: =AV96*L96*J96 -> 0
A97: 6 | D97: 6.03 | E97: Portaria - Controle de acesso à obra diurno | H97: Segurança | I97: Contrato | L97: =meses_obra -> 8 | M97: 1900 | O97: =IF(I97="CLT","N/A",(L97*(M97/12)*2)) -> 2533.3333 | P97: =IF(I97="contrato",AB97,AB97) -> 9.0142045 | Q97: =AE97+AF97 -> 0 | R97: =AG97 -> 0 | S97: =Q97*AL97 -> 0 | T97: =R97*AN97 -> 0 | U97: =AW97*L97*J97 -> 0 | Z97: =IF(I97="CLT",(M97/220)*(1+encargos_mensalista),(M97/220)) -> 8.6363636 | AA97: =Z97*(1+K97) -> 8.6363636 | AB97: =AA97*(1+((incidência_do_dissídio/meses_obra)*dissídio_coletivo)) -> 9.0142045 | AC97: =AB97*(1+(ociosidade_por_dia/9)) -> 9.0142045 | AE97: =IF(I97="contrato",0,$N$11*$Q$11*$K$11) -> 0 | AF97: =IF(I97="contrato",0,$N$12*$Q$12*$K$12) -> 0 | AG97: =IF(I97="contrato",0,$N$13*$Q$13*$K$13) -> 0 | AH97: =IF(I97="contrato",0,$N$14*$Q$14*$K$14) -> 0 | AI97: =IF(I97="contrato",0,$N$14*$Q$15*$K$15) -> 0 | AJ97: =IF(I97="contrato",0,$N$14*$Q$16*$K$16) -> 0 | AL97: =IF(I97="contrato",0,ROUNDUP((M97/220)*(1+$AA$14)*(1+hora_extra_dias_úteis),2)) -> 0 | AM97: =IF(I97="contrato",0,ROUNDUP((M97/220)*(1+$AA$14)*(1+hora_extra_sábados),2)) -> 0 | AN97: =IF(I97="contrato",0,ROUNDUP((M97/220)*(1+$AA$14)*(1+hora_extra_domingos),2)) -> 0 | AO97: =IF(I97="contrato",0,ROUNDUP(AL97*(1+adicional_noturno),2)) -> 0 | AP97: =IF(I97="contrato",0,ROUNDUP(AM97*(1+adicional_noturno),2)) -> 0 | AQ97: =IF(I97="contrato",0,ROUNDUP(AN97*(1+adicional_noturno),2)) -> 0 | AS97: =IF(H97="Coordenação",0,L97*J97) -> 0 | AT97: =IF(H97="Coordenação",L97*J97,0) -> 0 | AV97: =IF(I97="CLT",IF(L97=0,0,P97*220+N97),(P97*220+N97+(O97/meses_obra))) -> 2299.7917 | AW97: =IF(I97="CLT",IF(L97=0,0,((P97*220)+(AE97*AL97)+(AF97*AM97)+(AG97*AN97)+(AH97*AO97)+(AI97*AP97)+(AJ97*AQ97)+N97)),AV97) -> 2299.7917 | AX97: =AV97*L97*J97 -> 0
A98: 6 | D98: 6.04 | E98: Portaria - Controle de acesso à obra noturno | H98: Segurança | I98: Contrato | L98: =meses_obra -> 8 | M98: 1900 | O98: =IF(I98="CLT","N/A",(L98*(M98/12)*2)) -> 2533.3333 | P98: =IF(I98="contrato",AB98,AB98) -> 9.0142045 | Q98: =AE98+AF98 -> 0 | R98: =AG98 -> 0 | S98: =Q98*AL98 -> 0 | T98: =R98*AN98 -> 0 | U98: =AW98*L98*J98 -> 0 | Z98: =IF(I98="CLT",(M98/220)*(1+encargos_mensalista),(M98/220)) -> 8.6363636 | AA98: =Z98*(1+K98) -> 8.6363636 | AB98: =AA98*(1+((incidência_do_dissídio/meses_obra)*dissídio_coletivo)) -> 9.0142045 | AC98: =AB98*(1+(ociosidade_por_dia/9)) -> 9.0142045 | AE98: =IF(I98="contrato",0,$N$11*$Q$11*$K$11) -> 0 | AF98: =IF(I98="contrato",0,$N$12*$Q$12*$K$12) -> 0 | AG98: =IF(I98="contrato",0,$N$13*$Q$13*$K$13) -> 0 | AH98: =IF(I98="contrato",0,$N$14*$Q$14*$K$14) -> 0 | AI98: =IF(I98="contrato",0,$N$14*$Q$15*$K$15) -> 0 | AJ98: =IF(I98="contrato",0,$N$14*$Q$16*$K$16) -> 0 | AL98: =IF(I98="contrato",0,ROUNDUP((M98/220)*(1+$AA$14)*(1+hora_extra_dias_úteis),2)) -> 0 | AM98: =IF(I98="contrato",0,ROUNDUP((M98/220)*(1+$AA$14)*(1+hora_extra_sábados),2)) -> 0 | AN98: =IF(I98="contrato",0,ROUNDUP((M98/220)*(1+$AA$14)*(1+hora_extra_domingos),2)) -> 0 | AO98: =IF(I98="contrato",0,ROUNDUP(AL98*(1+adicional_noturno),2)) -> 0 | AP98: =IF(I98="contrato",0,ROUNDUP(AM98*(1+adicional_noturno),2)) -> 0 | AQ98: =IF(I98="contrato",0,ROUNDUP(AN98*(1+adicional_noturno),2)) -> 0 | AS98: =IF(H98="Coordenação",0,L98*J98) -> 0 | AT98: =IF(H98="Coordenação",L98*J98,0) -> 0 | AV98: =IF(I98="CLT",IF(L98=0,0,P98*220+N98),(P98*220+N98+(O98/meses_obra))) -> 2299.7917 | AW98: =IF(I98="CLT",IF(L98=0,0,((P98*220)+(AE98*AL98)+(AF98*AM98)+(AG98*AN98)+(AH98*AO98)+(AI98*AP98)+(AJ98*AQ98)+N98)),AV98) -> 2299.7917 | AX98: =AV98*L98*J98 -> 0
A99: 6 | D99: 6.05 | H99: Segurança | I99: Contrato | L99: =meses_obra -> 8 | M99: 1364 | O99: =IF(I99="CLT","N/A",(L99*(M99/12)*2)) -> 1818.6667 | P99: =IF(I99="contrato",AB99,AB99) -> 6.47125 | Q99: =AE99+AF99 -> 0 | R99: =AG99 -> 0 | S99: =Q99*AL99 -> 0 | T99: =R99*AN99 -> 0 | U99: =AW99*L99*J99 -> 0 | Z99: =IF(I99="CLT",(M99/220)*(1+encargos_mensalista),(M99/220)) -> 6.2 | AA99: =Z99*(1+K99) -> 6.2 | AB99: =AA99*(1+((incidência_do_dissídio/meses_obra)*dissídio_coletivo)) -> 6.47125 | AC99: =AB99*(1+(ociosidade_por_dia/9)) -> 6.47125 | AE99: =IF(I99="contrato",0,$N$11*$Q$11*$K$11) -> 0 | AF99: =IF(I99="contrato",0,$N$12*$Q$12*$K$12) -> 0 | AG99: =IF(I99="contrato",0,$N$13*$Q$13*$K$13) -> 0 | AH99: =IF(I99="contrato",0,$N$14*$Q$14*$K$14) -> 0 | AI99: =IF(I99="contrato",0,$N$14*$Q$15*$K$15) -> 0 | AJ99: =IF(I99="contrato",0,$N$14*$Q$16*$K$16) -> 0 | AL99: =IF(I99="contrato",0,ROUNDUP((M99/220)*(1+$AA$14)*(1+hora_extra_dias_úteis),2)) -> 0 | AM99: =IF(I99="contrato",0,ROUNDUP((M99/220)*(1+$AA$14)*(1+hora_extra_sábados),2)) -> 0 | AN99: =IF(I99="contrato",0,ROUNDUP((M99/220)*(1+$AA$14)*(1+hora_extra_domingos),2)) -> 0 | AO99: =IF(I99="contrato",0,ROUNDUP(AL99*(1+adicional_noturno),2)) -> 0 | AP99: =IF(I99="contrato",0,ROUNDUP(AM99*(1+adicional_noturno),2)) -> 0 | AQ99: =IF(I99="contrato",0,ROUNDUP(AN99*(1+adicional_noturno),2)) -> 0 | AS99: =IF(H99="Coordenação",0,L99*J99) -> 0 | AT99: =IF(H99="Coordenação",L99*J99,0) -> 0 | AV99: =IF(I99="CLT",IF(L99=0,0,P99*220+N99),(P99*220+N99+(O99/meses_obra))) -> 1651.0083 | AW99: =IF(I99="CLT",IF(L99=0,0,((P99*220)+(AE99*AL99)+(AF99*AM99)+(AG99*AN99)+(AH99*AO99)+(AI99*AP99)+(AJ99*AQ99)+N99)),AV99) -> 1651.0083 | AX99: =AV99*L99*J99 -> 0
A101: S | D101: 07 | E101: Consultorias | J101: Qtde | K101: Transferencia | L101: ΔT em obra | M101: Base | N101: Ajuda ou bonus | U101: =SUMIF(A:A,D101,U:U) -> 0 | V101: =$AX$101/custo_direto -> 0 | Z101: com L.S. | AA101: Transf | AB101: Dissidio | AC101: Ossiosidade | AE101: HE d.útil | AF101: Qtd sáb | AG101: Qtd dom | AH101: HE d.útil | AI101: Qtd sáb | AJ101: Qtd dom | AL101: VH.d.útil | AM101: VH.sáb | AN101: VH.dom | AO101: VH.d.útil | AP101: VH.sáb | AQ101: VH.dom | AS101: Supervisão | AT101: Coordenação | AX101: =SUMIF(A:A,D101,AX:AX) -> 0
A102: 7 | D102: 7.01 | E102: Topografo + equipamento | H102: mês | I102: Contrato | L102: =meses_obra -> 8 | M102: 20000 | O102: =IF(I102="CLT","N/A",(L102*(M102/12)*2)) -> 26666.667 | P102: =IF(I102="contrato",AB102,AB102) -> 94.886364 | Q102: =AE102+AF102 -> 0 | R102: =AG102 -> 0 | S102: =Q102*AL102 -> 0 | T102: =R102*AN102 -> 0 | U102: =AW102*L102*J102 -> 0 | Z102: =IF(I102="CLT",(M102/220)*(1+encargos_mensalista),(M102/220)) -> 90.909091 | AA102: =Z102*(1+K102) -> 90.909091 | AB102: =AA102*(1+((incidência_do_dissídio/meses_obra)*dissídio_coletivo)) -> 94.886364 | AC102: =AB102*(1+(ociosidade_por_dia/9)) -> 94.886364 | AE102: =IF(I102="contrato",0,$N$11*$Q$11*$K$11) -> 0 | AF102: =IF(I102="contrato",0,$N$12*$Q$12*$K$12) -> 0 | AG102: =IF(I102="contrato",0,$N$13*$Q$13*$K$13) -> 0 | AH102: =IF(I102="contrato",0,$N$14*$Q$14*$K$14) -> 0 | AI102: =IF(I102="contrato",0,$N$14*$Q$15*$K$15) -> 0 | AJ102: =IF(I102="contrato",0,$N$14*$Q$16*$K$16) -> 0 | AL102: =IF(I102="contrato",0,ROUNDUP((M102/220)*(1+$AA$14)*(1+hora_extra_dias_úteis),2)) -> 0 | AM102: =IF(I102="contrato",0,ROUNDUP((M102/220)*(1+$AA$14)*(1+hora_extra_sábados),2)) -> 0 | AN102: =IF(I102="contrato",0,ROUNDUP((M102/220)*(1+$AA$14)*(1+hora_extra_domingos),2)) -> 0 | AO102: =IF(I102="contrato",0,ROUNDUP(AL102*(1+adicional_noturno),2)) -> 0 | AP102: =IF(I102="contrato",0,ROUNDUP(AM102*(1+adicional_noturno),2)) -> 0 | AQ102: =IF(I102="contrato",0,ROUNDUP(AN102*(1+adicional_noturno),2)) -> 0 | AS102: =IF(H102="Coordenação",0,L102*J102) -> 0 | AT102: =IF(H102="Coordenação",L102*J102,0) -> 0 | AV102: =IF(I102="CLT",IF(L102=0,0,P102*220+N102),(P102*220+N102+(O102/meses_obra))) -> 24208.333 | AW102: =IF(I102="CLT",IF(L102=0,0,((P102*220)+(AE102*AL102)+(AF102*AM102)+(AG102*AN102)+(AH102*AO102)+(AI102*AP102)+(AJ102*AQ102)+N102)),AV102) -> 24208.333 | AX102: =AV102*L102*J102 -> 0
A103: 7 | D103: 7.02 | E103: Ajudante de topografia | H103: mês | I103: Contrato | L103: =meses_obra -> 8 | M103: 1364 | O103: =IF(I103="CLT","N/A",(L103*(M103/12)*2)) -> 1818.6667 | P103: =IF(I103="contrato",AB103,AB103) -> 6.47125 | Q103: =AE103+AF103 -> 0 | R103: =AG103 -> 0 | S103: =Q103*AL103 -> 0 | T103: =R103*AN103 -> 0 | U103: =AW103*L103*J103 -> 0 | Z103: =IF(I103="CLT",(M103/220)*(1+encargos_mensalista),(M103/220)) -> 6.2 | AA103: =Z103*(1+K103) -> 6.2 | AB103: =AA103*(1+((incidência_do_dissídio/meses_obra)*dissídio_coletivo)) -> 6.47125 | AC103: =AB103*(1+(ociosidade_por_dia/9)) -> 6.47125 | AE103: =IF(I103="contrato",0,$N$11*$Q$11*$K$11) -> 0 | AF103: =IF(I103="contrato",0,$N$12*$Q$12*$K$12) -> 0 | AG103: =IF(I103="contrato",0,$N$13*$Q$13*$K$13) -> 0 | AH103: =IF(I103="contrato",0,$N$14*$Q$14*$K$14) -> 0 | AI103: =IF(I103="contrato",0,$N$14*$Q$15*$K$15) -> 0 | AJ103: =IF(I103="contrato",0,$N$14*$Q$16*$K$16) -> 0 | AL103: =IF(I103="contrato",0,ROUNDUP((M103/220)*(1+$AA$14)*(1+hora_extra_dias_úteis),2)) -> 0 | AM103: =IF(I103="contrato",0,ROUNDUP((M103/220)*(1+$AA$14)*(1+hora_extra_sábados),2)) -> 0 | AN103: =IF(I103="contrato",0,ROUNDUP((M103/220)*(1+$AA$14)*(1+hora_extra_domingos),2)) -> 0 | AO103: =IF(I103="contrato",0,ROUNDUP(AL103*(1+adicional_noturno),2)) -> 0 | AP103: =IF(I103="contrato",0,ROUNDUP(AM103*(1+adicional_noturno),2)) -> 0 | AQ103: =IF(I103="contrato",0,ROUNDUP(AN103*(1+adicional_noturno),2)) -> 0 | AS103: =IF(H103="Coordenação",0,L103*J103) -> 0 | AT103: =IF(H103="Coordenação",L103*J103,0) -> 0 | AV103: =IF(I103="CLT",IF(L103=0,0,P103*220+N103),(P103*220+N103+(O103/meses_obra))) -> 1651.0083 | AW103: =IF(I103="CLT",IF(L103=0,0,((P103*220)+(AE103*AL103)+(AF103*AM103)+(AG103*AN103)+(AH103*AO103)+(AI103*AP103)+(AJ103*AQ103)+N103)),AV103) -> 1651.0083 | AX103: =AV103*L103*J103 -> 0
A104: 7 | D104: 7.03 | E104: Consultaria de Fundações | H104: mês | I104: Contrato | L104: =meses_obra -> 8 | O104: =IF(I104="CLT","N/A",(L104*(M104/12)*2)) -> 0 | P104: =IF(I104="contrato",AB104,AB104) -> 0 | Q104: =AE104+AF104 -> 0 | R104: =AG104 -> 0 | S104: =Q104*AL104 -> 0 | T104: =R104*AN104 -> 0 | U104: =AW104*L104*J104 -> 0 | Z104: =IF(I104="CLT",(M104/220)*(1+encargos_mensalista),(M104/220)) -> 0 | AA104: =Z104*(1+K104) -> 0 | AB104: =AA104*(1+((incidência_do_dissídio/meses_obra)*dissídio_coletivo)) -> 0 | AC104: =AB104*(1+(ociosidade_por_dia/9)) -> 0 | AE104: =IF(I104="contrato",0,$N$11*$Q$11*$K$11) -> 0 | AF104: =IF(I104="contrato",0,$N$12*$Q$12*$K$12) -> 0 | AG104: =IF(I104="contrato",0,$N$13*$Q$13*$K$13) -> 0 | AH104: =IF(I104="contrato",0,$N$14*$Q$14*$K$14) -> 0 | AI104: =IF(I104="contrato",0,$N$14*$Q$15*$K$15) -> 0 | AJ104: =IF(I104="contrato",0,$N$14*$Q$16*$K$16) -> 0 | AL104: =IF(I104="contrato",0,ROUNDUP((M104/220)*(1+$AA$14)*(1+hora_extra_dias_úteis),2)) -> 0 | AM104: =IF(I104="contrato",0,ROUNDUP((M104/220)*(1+$AA$14)*(1+hora_extra_sábados),2)) -> 0 | AN104: =IF(I104="contrato",0,ROUNDUP((M104/220)*(1+$AA$14)*(1+hora_extra_domingos),2)) -> 0 | AO104: =IF(I104="contrato",0,ROUNDUP(AL104*(1+adicional_noturno),2)) -> 0 | AP104: =IF(I104="contrato",0,ROUNDUP(AM104*(1+adicional_noturno),2)) -> 0 | AQ104: =IF(I104="contrato",0,ROUNDUP(AN104*(1+adicional_noturno),2)) -> 0 | AS104: =IF(H104="Coordenação",0,L104*J104) -> 0 | AT104: =IF(H104="Coordenação",L104*J104,0) -> 0 | AV104: =IF(I104="CLT",IF(L104=0,0,P104*220+N104),(P104*220+N104+(O104/meses_obra))) -> 0 | AW104: =IF(I104="CLT",IF(L104=0,0,((P104*220)+(AE104*AL104)+(AF104*AM104)+(AG104*AN104)+(AH104*AO104)+(AI104*AP104)+(AJ104*AQ104)+N104)),AV104) -> 0 | AX104: =AV104*L104*J104 -> 0
A105: 7 | D105: 7.04 | L105: =meses_obra -> 8 | O105: =IF(I105="CLT","N/A",(L105*(M105/12)*2)) -> 0 | P105: =IF(I105="contrato",AB105,AB105) -> 0 | Q105: =AE105+AF105 -> 0 | R105: =AG105 -> 0 | S105: =Q105*AL105 -> 0 | T105: =R105*AN105 -> 0 | U105: =AW105*L105*J105 -> 0 | Z105: =IF(I105="CLT",(M105/220)*(1+encargos_mensalista),(M105/220)) -> 0 | AA105: =Z105*(1+K105) -> 0 | AB105: =AA105*(1+((incidência_do_dissídio/meses_obra)*dissídio_coletivo)) -> 0 | AC105: =AB105*(1+(ociosidade_por_dia/9)) -> 0 | AE105: =IF(I105="contrato",0,$N$11*$Q$11*$K$11) -> 0 | AF105: =IF(I105="contrato",0,$N$12*$Q$12*$K$12) -> 0 | AG105: =IF(I105="contrato",0,$N$13*$Q$13*$K$13) -> 0 | AH105: =IF(I105="contrato",0,$N$14*$Q$14*$K$14) -> 0 | AI105: =IF(I105="contrato",0,$N$14*$Q$15*$K$15) -> 0 | AJ105: =IF(I105="contrato",0,$N$14*$Q$16*$K$16) -> 0 | AL105: =IF(I105="contrato",0,ROUNDUP((M105/220)*(1+$AA$14)*(1+hora_extra_dias_úteis),2)) -> 0 | AM105: =IF(I105="contrato",0,ROUNDUP((M105/220)*(1+$AA$14)*(1+hora_extra_sábados),2)) -> 0 | AN105: =IF(I105="contrato",0,ROUNDUP((M105/220)*(1+$AA$14)*(1+hora_extra_domingos),2)) -> 0 | AO105: =IF(I105="contrato",0,ROUNDUP(AL105*(1+adicional_noturno),2)) -> 0 | AP105: =IF(I105="contrato",0,ROUNDUP(AM105*(1+adicional_noturno),2)) -> 0 | AQ105: =IF(I105="contrato",0,ROUNDUP(AN105*(1+adicional_noturno),2)) -> 0 | AS105: =IF(H105="Coordenação",0,L105*J105) -> 0 | AT105: =IF(H105="Coordenação",L105*J105,0) -> 0 | AV105: =IF(I105="CLT",IF(L105=0,0,P105*220+N105),(P105*220+N105+(O105/meses_obra))) -> 0 | AW105: =IF(I105="CLT",IF(L105=0,0,((P105*220)+(AE105*AL105)+(AF105*AM105)+(AG105*AN105)+(AH105*AO105)+(AI105*AP105)+(AJ105*AQ105)+N105)),AV105) -> 0 | AX105: =AV105*L105*J105 -> 0
E107: CUSTO INDIRETO - Mão de obra | I107: Σ = | J107: =SUM(J35:J106) -> 4 | S107: Σ( MDO indireta ) = | T107: =SUMPRODUCT(AB35:AB105,J35:J105,L35:L105)*220-SUMPRODUCT(Z35:Z105,J35:J105,L35:L105)*220 -> 7700 | U107: =SUMIF(A:A,"S",U:U) -> 213033.33 | V107: =((mdo_indireta_valor)/custo_direto) -> 0.036030046 | AV107: =U107-AX107 -> 0 | AW107: =$AX$107-transf_diss_ocio_mdo_indireta -> 205333.33 | AX107: =SUMIF(A:A,"S",AX:AX) -> 213033.33
S108: Σ( MDO direta ) = | T108: =IF((SUMPRODUCT(J22:J26,L22:L26,AC22:AC26)*220-SUMPRODUCT(J22:J26,L22:L26,Z22:Z26)*220)<1000,0,(SUMPRODUCT(J22:J26,L22:L26,AC22:AC26)*220-SUMPRODUCT(J22:J26,L22:L26,Z22:Z26)*220)) -> 124936.98 | U108: =$U$21 -> 2980639.3 | AV108: =U108-AX108 -> 0 | AX108: =$AX$21 -> 2980639.3
S109: Σ = | T109: =SUM(T107:T108) -> 132636.98 | U109: =$U$108+$U$107 -> 3193672.6 | V109: =($AV$109+T109)/custo_direto -> 0.023273943 | AV109: =SUM(AV107:AV108) -> 0 | AX109: =$AX$108+$AX$107 -> 3193672.6
D111: QUADRO 2 - | E111: GERAL - Valor base conforme Convenção Coletiva de Trabalho ( CCT )
K113: Casa X Hotel | N113: Comparativo Transporte Publico X Próprio
...

Sheet F.D.
B2: FATURAMENTO DIRETO | K2: RESUMO - FD
B4: Cód. Insumo | C4: Descrição | D4: Unidade | E4: Qtd Orçada | F4: Unt Insumo | G4: ∑ Insumo | H4: Fornecedor | K4: FORNECEDOR | L4: TOTAL
L6: =SUMIF($H$119:$H$170,K6,$G$119:$G$170) -> 0
B7: 34.45.27 | C7: Piso em porcelanato Firenze Brilhante 64x64 cm - Porto Ferreira | D7: m² | E7: 5303.021 | F7: 60 | G7: 318181.26 | L7: =SUMIF($H$119:$H$170,K7,$G$119:$G$170) -> 0
B8: 34.46.01 | C8: Revestimento Glacial Snow 32x59 cm branco acetinado RET - Incepa | D8: m² | E8: 5215.056 | F8: 60 | G8: 312903.36 | L8: =SUMIF($H$119:$H$170,K8,$G$119:$G$170) -> 0
L9: =SUMIF($H$119:$H$170,K9,$G$119:$G$170) -> 0
L10: =SUMIF($H$119:$H$170,K10,$G$119:$G$170) -> 0
B11: 37.70.89 | C11: Vidro temperado incolor 8 mm | D11: m² | E11: 805.752 | F11: 266.475 | G11: 214712.76
B12: 20.05.80 | C12: Gesso em pó ensacado para revestimento saco de 40 kg | D12: kg | E12: 184062.91 | F12: 0.95975 | G12: 176654.38 | L12: =SUMIF($H$119:$H$170,K12,$G$119:$G$170) -> 0
L13: =SUMIF($H$119:$H$170,K13,$G$119:$G$170) -> 0
B14: 90.06.32 | C14: Caixilho em alumínio anodizado fosco L 25, tipo veneziana, sob medida | D14: m² | E14: 328.428 | F14: 504.68154 | G14: 165751.55 | L14: =SUMIF($H$119:$H$170,K14,$G$119:$G$170) -> 0
L15: =SUMIF($H$119:$H$170,K15,$G$119:$G$170) -> 0
B16: 65.55.02 | C16: Bacia para Caixa Acoplada Deca | Ravena - Branco | D16: un | E16: 220 | F16: 620.9 | G16: 136598 | L16: =SUMIF($H$119:$H$170,K16,$G$119:$G$170) -> 0
L17: =SUMIF($H$119:$H$170,K17,$G$119:$G$170) -> 0
B18: 20.05.03 | C18: Areia média lavada à granel | D18: m³ | E18: 951.84032 | F18: 96 | G18: 91376.671 | L18: =SUMIF($H$119:$H$170,K18,$G$119:$G$170) -> 0
B19: 34.45.97 | C19: Clipe espaçador nivelador em plástico 1 mm para pisos | D19: un | E19: 194822 | F19: 0.46 | G19: 89618.12 | L19: =SUMIF($H$119:$H$170,K19,$G$119:$G$170) -> 0
B20: 20.05.08 | C20: Cimento CPIII-E-32 (sacos de 50 kg) (volume do saco 0,036 m³) | D20: kg | E20: 145495.36 | F20: 0.61 | G20: 88752.17 | L20: =SUMIF($H$119:$H$170,K20,$G$119:$G$170) -> 0
B21: 37.75.20 | C21: Tinta direto sobre gesso e drywall 18 L - diluição de 50% Clássica máxx branco neve Suvinil | D21: l | E21: 4364.6075 | F21: 18.327778 | G21: 79993.556 | L21: =SUMIF($H$119:$H$170,K21,$G$119:$G$170) -> 0
B22: 99.50.21 | C22: Cuba Apoio Quadrada Basic Q6 35x35cm Com Mesa Branco Celite | D22: un | E22: 220 | F22: 359.91 | G22: 79180.2 | L22: =SUMIF($H$119:$H$170,K22,$G$119:$G$170) -> 0
L23: =SUMIF($H$119:$H$170,K23,$G$119:$G$170) -> 0
L24: =SUMIF($H$119:$H$170,K24,$G$119:$G$170) -> 0
B25: 30.02.23 | C25: Folha de porta lisa em madeira sarrafeada para pintura 82x210cm | D25: un | E25: 245 | F25: 270 | G25: 66150 | L25: =SUMIF($H$119:$H$170,K25,$G$119:$G$170) -> 0
B26: 30.01.35 | C26: Batente madeira itauba/garapeira/cedro/angelim 13x3,5cm, vão 52 a 92x210cm | D26: un | E26: 264 | F26: 250 | G26: 66000 | L26: =SUMIF($H$119:$H$170,K26,$G$119:$G$170) -> 0
B27: 39.90.56 | C27: Argamassa química bicomponente para porcelanato, alta resistência química, térmicas e vibrações, AC-III | D27: kg | E27: 26075.28 | F27: 2.45 | G27: 63884.436 | L27: =SUMIF($H$119:$H$170,K27,$G$119:$G$170) -> 0
B28: 98.81.76 | C28: Limpeza e final da obra terceirizado especializado | D28: m² | E28: 5435.72 | F28: 11 | G28: 59792.92 | L28: =SUMIF($H$119:$H$170,K28,$G$119:$G$170) -> 0
B29: 37.75.10 | C29: Massa corrida de base Acrílica - Suvinil/Glasurit, Massa FC (Fusecolor), Massa Especial para fachada (Retinco) ou equivalente | D29: kg | E29: 8834.9333 | F29: 6.76 | G29: 59724.149 | L29: =SUMIF($H$119:$H$170,K29,$G$119:$G$170) -> 0
B30: 34.40.48 | C30: Chapa de gesso acartonado, ref. Gypsum Standard 12.5 mm 1200x1800 mm | D30: m² | E30: 2229.669 | F30: 26.347222 | G30: 58745.585 | L30: =SUMIF($H$119:$H$170,K30,$G$119:$G$170) -> 0
B31: 35.50.72 | C31: Mármore Travertino Nacional; espessura de 2,0 cm colocado | D31: m² | E31: 119.9744 | F31: 482.22 | G31: 57854.055 | L31: =SUMIF($H$119:$H$170,K31,$G$119:$G$170) -> 0
B32: 30.01.37 | C32: Batente madeira itauba/garapeira/cedro/angelim 11x3,5cm, vão 122x210cm | D32: un | E32: 228 | F32: 240 | G32: 54720 | L32: =SUMIF($H$119:$H$170,K32,$G$119:$G$170) -> 0
B33: 30.02.22 | C33: Folha de porta lisa em madeira sarrafeada para pintura 72x210cm | D33: un | E33: 228 | F33: 240 | G33: 54720 | L33: =SUMIF($H$119:$H$170,K33,$G$119:$G$170) -> 0
B34: 37.70.26 | C34: Espelho em vidro cristal liso, espessura de 4 mm, colocado sobre a parede, peças aproximadamente 0,5 a 4,12 m² | D34: m² | E34: 138.2 | F34: 387.52 | G34: 53555.264 | L34: =SUMIF($H$119:$H$170,K34,$G$119:$G$170) -> 0
B35: 39.90.24 | C35: Viaplus 1000 | D35: kg | E35: 14946.64 | F35: 3.4772222 | G35: 51972.789 | L35: =SUMIF($H$119:$H$170,K35,$G$119:$G$170) -> 0
B36: 99.50.93 | C36: Porta toalhas bastão toalheiro docol Trip Cromado | D36: un | E36: 222 | F36: 202.45 | G36: 44943.9 | L36: =SUMIF($H$119:$H$170,K36,$G$119:$G$170) -> 0
... B38: 64.45.03 | C38: Sifão metálico cromado 1´ x 1 1/2´, com tubo de ligação ajustável; ref. Fabrimar, Oriente ou equivalente | D38: un | E38: 235 | F38: 187 | G38: 43945 | L38: =SUMIF($H$119:$H$170,K38,$G$119:$G$170) -> 0
L39: =SUMIF($H$119:$H$170,K39,$G$119:$G$170) -> 0
B40: 31.16.45 | C40: Dobradiça em latão cromado de 3 1/2´ x 3´, ref. La Fonte Dob 90 3 1/2´ x 3´ LT S/P CR, Arouca 346, 3500 da União Mundial ou equivalente | D40: un | E40: 984 | F40: 39.9 | G40: 39261.6 | L40: =SUMIF($H$119:$H$170,K40,$G$119:$G$170) -> 0
B41: 22.25.40 | C41: Bloco cerâmico para vedação 9 x 19 x 29 cm, uso revestido, ± 3,0 MPa | D41: un | E41: 25538.012 | F41: 1.49 | G41: 38051.637 | L41: =SUMIF($H$119:$H$170,K41,$G$119:$G$170) -> 0
B42: 99.50.95 | C42: Papeleira Trip, Docol, Cromado | D42: un | E42: 222 | F42: 170.91 | G42: 37942.02 | L42: =SUMIF($H$119:$H$170,K42,$G$119:$G$170) -> 0
B43: 32.25.14 | C43: Granto Preto São Gabriel, acabamento polido, espessura de 2 cm | D43: m² | E43: 71.688 | F43: 480 | G43: 34410.24 | L43: =SUMIF($H$119:$H$170,K43,$G$119:$G$170) -> 0
L44: =SUMIF($H$119:$H$170,K44,$G$119:$G$170) -> 0
B45: 34.40.31 | C45: Tabica em alumínio pintada branca 48 x 40 x 3000 | D45: m | E45: 3507.46 | F45: 8.5633333 | G45: 30035.549 | L45: =SUMIF($H$119:$H$170,K45,$G$119:$G$170) -> 0
B46: 93.33.44 | C46: Rejunte flexível para porcelanato, aplicada em áreas internas e externas com junta até 3mm, ref. Junta Plus Gold fabricação Eliane ou equivalente | D46: kg | E46: 3719.8702 | F46: 7.99 | G46: 29721.763 | L46: =SUMIF($H$119:$H$170,K46,$G$119:$G$170) -> 0
B47: 31.12.13 | C47: Porta corta-fogo classe P.90 leve 90x210 completa, com maçaneta tipo alavanca e batentes (NBR 11742) | D47: un | E47: 18 | F47: 1609.07 | G47: 28963.26 | L47: =SUMIF($H$119:$H$170,K47,$G$119:$G$170) -> 0
L48: =SUMIF($H$119:$H$170,K48,$G$119:$G$170) -> 0
B49: 39.90.32 | C49: Argamassa colante industrializada flexível, ref. Ligamax Gold, para assentamento em áreas internas e externas, tipo AC-II, conforme NBR 14081 | D49: kg | E49: 23561.45 | F49: 1.15 | G49: 27095.667 | L49: =SUMIF($H$119:$H$170,K49,$G$119:$G$170) -> 0
B50: 99.50.92 | C50: Ralo Linear 10x100cm Grelha Inox | D50: un | E50: 231 | F50: 109.25 | G50: 25236.75 | L50: =SUMIF($H$119:$H$170,K50,$G$119:$G$170) -> 0
B51: 37.75.18 | C51: Selador para tinta acrílica Coral, Suvinil ou equivalente | D51: l | E51: 2793.3488 | F51: 8.8833333 | G51: 24814.249 | L51: =SUMIF($H$119:$H$170,K51,$G$119:$G$170) -> 0
B52: 99.50.96 | C52: Prateleira Acessórios Idea Docol Cromado | D52: un | E52: 222 | F52: 109.9 | G52: 24397.8 | L52: =SUMIF($H$119:$H$170,K52,$G$119:$G$170) -> 0
L53: =SUMIF($H$119:$H$170,K53,$G$119:$G$170) -> 0
B54: 30.01.50 | C54: Guarnição cedrinho de 210 x 100 x 1 x 6,5 cm - Fema | D54: un | E54: 492 | F54: 46.51 | G54: 22882.92 | L54: =SUMIF($H$119:$H$170,K54,$G$119:$G$170) -> 0
B55: 60.05.06 | C55: Tubo em ferro galvanizado, DN= 2´ #14 | D55: m | E55: 371.79 | F55: 58.36 | G55: 21697.664 | L55: =SUMIF($H$119:$H$170,K55,$G$119:$G$170) -> 0
B56: 66.60.28 | C56: Ligação Flexivel Malha Aço cromado 40cm 467.C.040 - Deca | D56: un | E56: 417 | F56: 49.9 | G56: 20808.3 | L56: =SUMIF($H$119:$H$170,K56,$G$119:$G$170) -> 0
B57: 34.40.34 | C57: Perfil enrijecido canaleta para regulador F530 - 46x18 mm 3 m | D57: un | E57: 905.2075 | F57: 21.98 | G57: 19896.461 | L57: =SUMIF($H$119:$H$170,K57,$G$119:$G$170) -> 0
L58: =SUMIF($H$119:$H$170,K58,$G$119:$G$170) -> 0
B59: 80.03.52 | C59: Cortador de Parede 2.000W BRIC 35 - CORTAG-6000 | D59: chp | E59: 1686.7584 | F59: 11.64267 | G59: 19638.371
L60: =SUMIF($H$119:$H$170,K60,$G$119:$G$170) -> 0
B61: 26.67.33 | C61: Parafusos niquelados para sanitários | D61: un | E61: 454 | F61: 39.9 | G61: 18114.6 | L61: =SUMIF($H$119:$H$170,K61,$G$119:$G$170) -> 0
B62: 26.65.13 | C62: Chumbador Fischer Bolt diâmetro = 1/2´ e comprimento = 4´ | D62: un | E62: 892 | F62: 19.89 | G62: 17741.88 | L62: =SUMIF($H$119:$H$170,K62,$G$119:$G$170) -> 0
B63: 99.50.94 | C63: Cabide Trip Banheiro, Cromado 00761706 - Docol | D63: un | E63: 222 | F63: 77.9 | G63: 17293.8 | L63: =SUMIF($H$119:$H$170,K63,$G$119:$G$170) -> 0
B64: 99.50.91 | C64: Acabamento Registro de 1/2, 3/4 e 1 Lift Docol Cromado | D64: un | E64: 132 | F64: 129.9 | G64: 17146.8 | L64: =SUMIF($H$119:$H$170,K64,$G$119:$G$170) -> 0
B65: 32.25.00 | C65: Rodapé em granito; espes. de 3,0 cm, altura de 7,1 a 10 cm, boleado; acabamento: jateado, polido; cor: Andorinha/Mauá/Corumbá/Ubatuba | D65: m | E65: 179.6 | F65: 81.54 | G65: 14644.584
B66: 28.80.16 | C66: Aditivo colante ´Bianco´ (embalagem em balde de 18 kg) | D66: kg | E66: 829.287 | F66: 16.938889 | G66: 14047.2 | L66: =SUMIF($H$119:$H$170,K66,$G$119:$G$170) -> 0
L67: =SUMIF($H$119:$H$170,K67,$G$119:$G$170) -> 0
B68: 49.95.13 | C68: Mão francesa ferro para bancada 48,5cm x 27,5cm Esp. da Chapa: 3 mm | D68: un | E68: 446 | F68: 28.65 | G68: 12777.9 | L68: =SUMIF($H$119:$H$170,K68,$G$119:$G$170) -> 0
B69: 34.45.98 | C69: Cunha Niveladora de piso Cortag | D69: un | E69: 19482.2 | F69: 0.64 | G69: 12468.608 | L69: =SUMIF($H$119:$H$170,K69,$G$119:$G$170) -> 0
B70: 24.40.42 | C70: Disco diamantado contínuo de corte 4´ - cortag turbo (Código:74527) | D70: un | E70: 695.098 | F70: 15.5 | G70: 10774.019 | L70: =SUMIF($H$119:$H$170,K70,$G$119:$G$170) -> 0
L71: =SUMIF($H$119:$H$170,K71,$G$119:$G$170) -> 0
B72: 31.10.06 | C72: Corrimão tubular em aço galvanizado, diâmetro de 1 1/2´ | D72: m | E72: 84 | F72: 119 | G72: 9996 | L72: =SUMIF($H$119:$H$170,K72,$G$119:$G$170) -> 0
B73: 99.50.85 | C73: Kit completo Bacia PCD com caixa acoplada abertura frontal - Acesso Celite | D73: un | E73: 7 | F73: 1424.9 | G73: 9974.3 | L73: =SUMIF($H$119:$H$170,K73,$G$119:$G$170) -> 0
B74: 66.60.53 | C74: Tubo de ligação com canopla para sanitários em PVC cromado - Tigre | D74: un | E74: 227 | F74: 35.9 | G74: 8149.3 | L74: =SUMIF($H$119:$H$170,K74,$G$119:$G$170) -> 0
L75: =SUMIF($H$119:$H$170,K75,$G$119:$G$170) -> 0
L76: =SUMIF($H$119:$H$170,K76,$G$119:$G$170) -> 0
B77: 98.81.00 | C77: Caçamba estacionária 4 m³ credenciada | D77: m³ | E77: 68.08936 | F77: 100 | G77: 6808.936 | L77: =SUMIF($H$119:$H$170,K77,$G$119:$G$170) -> 0
B78: 69.95.55 | C78: Anel borracha expansão para ligação em bacia sifonada, 100 mm (4´) | D78: un | E78: 227 | F78: 29 | G78: 6583 | L78: =SUMIF($H$119:$H$170,K78,$G$119:$G$170) -> 0
B79: 64.40.02 | C79: Válvula de escoamento cromada de 1 1/2', ref. 1606C da Deca ou equivalente | D79: un | E79: 227 | F79: 28.45 | G79: 6458.15 | L79: =SUMIF($H$119:$H$170,K79,$G$119:$G$170) -> 0
B80: 39.90.86 | C80: Placa de sinalização em PVC | D80: un | E80: 492 | F80: 12.9 | G80: 6346.8 | L80: =SUMIF($H$119:$H$170,K80,$G$119:$G$170) -> 0
B81: 80.01.25 | C81: Betoneira reversível com carregador, capac. 320 litros, acionamento do motor combustão interna (diesel e gasolina) ou motor elétrico Alfa 320 -(DER 72.04.02.04) | D81: chp | E81: 2051.6404 | F81: 2.9545455 | G81: 6061.6649 | L81: =SUMIF($H$119:$H$170,K81,$G$119:$G$170) -> 0
B82: 65.55.64 | C82: Lavatório de louça para canto sem coluna para pessoa com mobilidade reduzida, ref. Deca, Coleção Master, cód. L 76.17, ou equivalente | D82: un | E82: 7 | F82: 850.78 | G82: 5955.46 | L82: =SUMIF($H$119:$H$170,K82,$G$119:$G$170) -> 0
L83: =SUMIF($H$119:$H$170,K83,$G$119:$G$170) -> 0
B84: 33.35.03 | C84: Cantoneira em alumínio ´Y´ para massa, espessura de 1,5mm, ref. R-78da Pin-Can, M-1 da Canto Metal ou similiar | D84: m | E84: 398.16 | F84: 12.5 | G84: 4977 | L84: =SUMIF($H$119:$H$170,K84,$G$119:$G$170) -> 0
B85: 38.80.17 | C85: Massa corrida PVA, ref. Massa Corrida Suvinil (Glasurit), Coral, Promar (Sherwin Willians), Concretina (Ypiranga/Akzo) ou equivalente | D85: kg | E85: 1383.0433 | F85: 3.356 | G85: 4641.4934 | L85: =SUMIF($H$119:$H$170,K85,$G$119:$G$170) -> 0
B86: 34.40.35 | C86: Fita telada para drywall R131 100 mm, 50 m | D86: un | E86: 51.267268 | F86: 83.03 | G86: 4256.7213 | L86: =SUMIF($H$119:$H$170,K86,$G$119:$G$170) -> 0
B87: 32.25.10 | C87: Granito Verde Ubatuba, acabamento polido, espessura de 2 cm | D87: m² | E87: 13.2 | F87: 320 | G87: 4224 | L87: =SUMIF($H$119:$H$170,K87,$G$119:$G$170) -> 0
B88: 30.02.24 | C88: Folha de porta lisa em madeira sarrafeada para pintura 92x210cm | D88: un | E88: 13 | F88: 290 | G88: 3770 | L88: =SUMIF($H$119:$H$170,K88,$G$119:$G$170) -> 0
B89: 34.40.49 | C89: Chapa de gesso acartonado, ref. Gypsum RF 12.5 mm 1200x2400 mm | D89: m² | E89: 136.31717 | F89: 25.84375 | G89: 3522.9468 | L89: =SUMIF($H$119:$H$170,K89,$G$119:$G$170) -> 0
B90: 37.75.02 | C90: Tinta esmalte acabamento acetinado ou brilhante, (latas 18 litros), ref. Esmalte (Sherwin Willians), Coralit Esmalte Sintético (Coral), Suvinil Esmalte | D90: l | E90: 62.379 | F90: 55.555556 | G90: 3465.5 | L90: =SUMIF($H$119:$H$170,K90,$G$119:$G$170) -> 0
B91: 34.40.33 | C91: Regulador normal para forro perfil F530 | D91: un | E91: 2000.985 | F91: 1.69 | G91: 3381.6646 | L91: =SUMIF($H$119:$H$170,K91,$G$119:$G$170) -> 0
B92: 34.40.37 | C92: Massa para drywall 15 kg | D92: un | E92: 51.267268 | F92: 60.21 | G92: 3086.8022 | L92: =SUMIF($H$119:$H$170,K92,$G$119:$G$170) -> 0
B93: 92.28.66 | C93: Curva 90° em ferro galvanizado # 13 | D93: un | E93: 79.669286 | F93: 38.5 | G93: 3067.2675 | L93: =SUMIF($H$119:$H$170,K93,$G$119:$G$170) -> 0
B94: 60.05.01 | C94: Tubo em ferro galvanizado, DN= 1/2´ #14 | D94: m | E94: 371.79 | F94: 8.11 | G94: 3015.2169 | L94: =SUMIF($H$119:$H$170,K94,$G$119:$G$170) -> 0
B95: 34.40.43 | C95: Perfil montante formato C aço zincado p/ estrutura parede drywall E=0,5 mm 70 x 30 x 3000 mm (LxC) | D95: m | E95: 257.74042 | F95: 11.576667 | G95: 2983.775 | L95: =SUMIF($H$119:$H$170,K95,$G$119:$G$170) -> 0
... B112: 20.05.05 | C112: Cal líquido (100 ml/ saco de cimento) | D112: kg | E112: 119.49657 | F112: 9.1111111 | G112: 1088.7465 | L112: =SUMIF($H$119:$H$170,K112,$G$119:$G$170) -> 0
B113: 42.22.36 | C113: Apoio para mastro em aço chapa cortada 100 x 100 mm #14 | D113: un | E113: 123.93 | F113: 8.5 | G113: 1053.405
L114: =SUMIF($H$119:$H$170,K114,$G$119:$G$170) -> 0
L115: =SUMIF($H$119:$H$170,K115,$G$119:$G$170) -> 0
L116: =SUMIF($H$119:$H$170,K116,$G$119:$G$170) -> 0
L117: =SUMIF($H$119:$H$170,K117,$G$119:$G$170) -> 0
L118: =SUMIF($H$119:$H$170,K118,$G$119:$G$170) -> 0
L119: =SUMIF($H$119:$H$170,K119,$G$119:$G$170) -> 0
L120: =SUMIF($H$119:$H$170,K120,$G$119:$G$170) -> 0
...

Sheet Bdi CURVA ABC - MAT
B2: BDI CURVA ABC DE MATERIAIS | K2: RESUMO - FD
B4: Cód. Insumo | C4: Descrição | D4: Unidade | E4: Qtd Orçada | F4: Unt Insumo | G4: ∑ Insumo | H4: Fornecedor | K4: FORNECEDOR | L4: TOTAL
K5: {=IFERROR(_xlfn.UNIQUE(H5:H209),"")} -> 0 | L5: =SUMIF($H$5:$H$259,K5,$G$5:$G$259) -> 0
L6: =SUMIF($H$5:$H$259,K6,$G$5:$G$259) -> 0
L7: =SUMIF($H$5:$H$259,K7,$G$5:$G$259) -> 0
L8: =SUMIF($H$5:$H$259,K8,$G$5:$G$259) -> 0
L9: =SUMIF($H$5:$H$259,K9,$G$5:$G$259) -> 0
L10: =SUMIF($H$5:$H$259,K10,$G$5:$G$259) -> 0
L11: =SUMIF($H$5:$H$259,K11,$G$5:$G$259) -> 0
L12: =SUMIF($H$5:$H$259,K12,$G$5:$G$259) -> 0
L13: =SUMIF($H$5:$H$259,K13,$G$5:$G$259) -> 0
L14: =SUMIF($H$5:$H$259,K14,$G$5:$G$259) -> 0
L15: =SUMIF($H$5:$H$259,K15,$G$5:$G$259) -> 0
L16: =SUMIF($H$5:$H$259,K16,$G$5:$G$259) -> 0
L17: =SUMIF($H$5:$H$259,K17,$G$5:$G$259) -> 0
... L209: =SUMIF($H$5:$H$259,K209,$G$5:$G$259) -> 0
B210: TOTAL | H210: =SUM(G5:G205) -> 0 | L210: =SUMIF($H$5:$H$259,K210,$G$5:$G$259) -> 0
L211: =SUMIF($H$5:$H$259,K211,$G$5:$G$259) -> 0
L212: =SUMIF($H$5:$H$259,K212,$G$5:$G$259) -> 0
L213: =SUMIF($H$5:$H$259,K213,$G$5:$G$259) -> 0
L214: =SUMIF($H$5:$H$259,K214,$G$5:$G$259) -> 0
L215: =SUMIF($H$5:$H$259,K215,$G$5:$G$259) -> 0
L216: =SUMIF($H$5:$H$259,K216,$G$5:$G$259) -> 0
L217: =SUMIF($H$5:$H$259,K217,$G$5:$G$259) -> 0
L218: =SUMIF($H$5:$H$259,K218,$G$5:$G$259) -> 0
L219: =SUMIF($H$5:$H$259,K219,$G$5:$G$259) -> 0
K220: TOTAL | L220: =SUM(L5:L217) -> 0

Sheet Adm Central
G2: ADM Central | K2: Materiais = | L2: =materiais -> 3265572.7
G3: =BDI!F3 -> FC ENGENHARIA E CONSULTORIA LTDA | K3: Mão de Obra = | L3: =mdo+hora_extra_mdo_direta+transf_diss_ocio_mdo_direta -> 2433374.6
G4: =BDI!F4 -> julho/19 - Com desoneração da Folha de Pagamento | K4: Σ = | L4: =SUM(L2:L3) -> 5698947.3
D6: Obra: | E6: =" "&nome_da_obra -> BDI_747.xlsx | K6: Data base: | L6: =data_base_da_obra -> 46093
A8: =D8 -> 1 | B8: =D8 -> 1 | D8: 1 | F8: Pessoal: | H8: Base | I8: Tempo (Obra) | J8: Encargos | K8: Benefícios | L8: Total
A9: =IF(OFFSET(A9,-1,0)="",OFFSET(A9,-2,0),OFFSET(A9,-1,0)) -> 1 | B9: =IF(OFFSET(B9,-1,0)>="01",CONCATENATE(,OFFSET(B9,-1,0)+1),CONCATENATE((SUM(OFFSET(B9,-1,0)+1-(OFFSET(B9,-1,0)))))) -> 1 | E9: =IF(B9="1",CONCATENATE(A9,".0",B9),IF(B9="2",CONCATENATE(A9,".0",B9),IF(B9="3",CONCATENATE(A9,".0",B9),IF(B9="4",CONCATENATE(A9,".0",B9),IF(B9="5",CONCATENATE(A9,".0",B9),IF(B9="6",CONCATENATE(A9,".0",B9),IF(B9="7",CONCATENATE(A9,".0",B9),IF(B9="8",CONCATENATE(A9,".0",B9),IF(B9="9",CONCATENATE(A9,".0",B9),CONCATENATE(A9,".",B9)))))))))) -> 1.01 | F9: Diretoria 1 | I9: =meses_obra -> 8 | J9: 0 | K9: 0 | L9: =((H9*J9)+H9+K9)*I9 -> 0
A10: =IF(OFFSET(A10,-1,0)="",OFFSET(A10,-2,0),OFFSET(A10,-1,0)) -> 1 | B10: =IF(OFFSET(B10,-1,0)>="01",CONCATENATE(,OFFSET(B10,-1,0)+1),CONCATENATE((SUM(OFFSET(B10,-1,0)+1-(OFFSET(B10,-1,0)))))) -> 2 | E10: =IF(B10="1",CONCATENATE(A10,".0",B10),IF(B10="2",CONCATENATE(A10,".0",B10),IF(B10="3",CONCATENATE(A10,".0",B10),IF(B10="4",CONCATENATE(A10,".0",B10),IF(B10="5",CONCATENATE(A10,".0",B10),IF(B10="6",CONCATENATE(A10,".0",B10),IF(B10="7",CONCATENATE(A10,".0",B10),IF(B10="8",CONCATENATE(A10,".0",B10),IF(B10="9",CONCATENATE(A10,".0",B10),CONCATENATE(A10,".",B10)))))))))) -> 1.02 | F10: Diretoria 2 | I10: =I$9 -> 8 | J10: 0 | K10: 0 | L10: =((H10*J10)+H10+K10)*I10 -> 0
A11: =IF(OFFSET(A11,-1,0)="",OFFSET(A11,-2,0),OFFSET(A11,-1,0)) -> 1 | B11: =IF(OFFSET(B11,-1,0)>="01",CONCATENATE(,OFFSET(B11,-1,0)+1),CONCATENATE((SUM(OFFSET(B11,-1,0)+1-(OFFSET(B11,-1,0)))))) -> 3 | E11: =IF(B11="1",CONCATENATE(A11,".0",B11),IF(B11="2",CONCATENATE(A11,".0",B11),IF(B11="3",CONCATENATE(A11,".0",B11),IF(B11="4",CONCATENATE(A11,".0",B11),IF(B11="5",CONCATENATE(A11,".0",B11),IF(B11="6",CONCATENATE(A11,".0",B11),IF(B11="7",CONCATENATE(A11,".0",B11),IF(B11="8",CONCATENATE(A11,".0",B11),IF(B11="9",CONCATENATE(A11,".0",B11),CONCATENATE(A11,".",B11)))))))))) -> 1.03 | F11: Diretoria 3 | I11: =I$9 -> 8 | J11: 0.973 | K11: 0 | L11: =((H11*J11)+H11+K11)*I11 -> 0
A12: =IF(OFFSET(A12,-1,0)="",OFFSET(A12,-2,0),OFFSET(A12,-1,0)) -> 1 | B12: =IF(OFFSET(B12,-1,0)>="01",CONCATENATE(,OFFSET(B12,-1,0)+1),CONCATENATE((SUM(OFFSET(B12,-1,0)+1-(OFFSET(B12,-1,0)))))) -> 4 | E12: =IF(B12="1",CONCATENATE(A12,".0",B12),IF(B12="2",CONCATENATE(A12,".0",B12),IF(B12="3",CONCATENATE(A12,".0",B12),IF(B12="4",CONCATENATE(A12,".0",B12),IF(B12="5",CONCATENATE(A12,".0",B12),IF(B12="6",CONCATENATE(A12,".0",B12),IF(B12="7",CONCATENATE(A12,".0",B12),IF(B12="8",CONCATENATE(A12,".0",B12),IF(B12="9",CONCATENATE(A12,".0",B12),CONCATENATE(A12,".",B12)))))))))) -> 1.04 | F12: Diretoria 4 | I12: =I$9 -> 8 | J12: 0 | K12: 0 | L12: =((H12*J12)+H12+K12)*I12 -> 0
A13: =IF(OFFSET(A13,-1,0)="",OFFSET(A13,-2,0),OFFSET(A13,-1,0)) -> 1 | B13: =IF(OFFSET(B13,-1,0)>="01",CONCATENATE(,OFFSET(B13,-1,0)+1),CONCATENATE((SUM(OFFSET(B13,-1,0)+1-(OFFSET(B13,-1,0)))))) -> 5 | E13: =IF(B13="1",CONCATENATE(A13,".0",B13),IF(B13="2",CONCATENATE(A13,".0",B13),IF(B13="3",CONCATENATE(A13,".0",B13),IF(B13="4",CONCATENATE(A13,".0",B13),IF(B13="5",CONCATENATE(A13,".0",B13),IF(B13="6",CONCATENATE(A13,".0",B13),IF(B13="7",CONCATENATE(A13,".0",B13),IF(B13="8",CONCATENATE(A13,".0",B13),IF(B13="9",CONCATENATE(A13,".0",B13),CONCATENATE(A13,".",B13)))))))))) -> 1.05 | F13: Orçamentos 1 | I13: =I$9 -> 8 | J13: 0 | K13: 0 | L13: =((H13*J13)+H13+K13)*I13 -> 0
A14: =IF(OFFSET(A14,-1,0)="",OFFSET(A14,-2,0),OFFSET(A14,-1,0)) -> 1 | B14: =IF(OFFSET(B14,-1,0)>="01",CONCATENATE(,OFFSET(B14,-1,0)+1),CONCATENATE((SUM(OFFSET(B14,-1,0)+1-(OFFSET(B14,-1,0)))))) -> 6 | E14: =IF(B14="1",CONCATENATE(A14,".0",B14),IF(B14="2",CONCATENATE(A14,".0",B14),IF(B14="3",CONCATENATE(A14,".0",B14),IF(B14="4",CONCATENATE(A14,".0",B14),IF(B14="5",CONCATENATE(A14,".0",B14),IF(B14="6",CONCATENATE(A14,".0",B14),IF(B14="7",CONCATENATE(A14,".0",B14),IF(B14="8",CONCATENATE(A14,".0",B14),IF(B14="9",CONCATENATE(A14,".0",B14),CONCATENATE(A14,".",B14)))))))))) -> 1.06 | F14: Orçamentos 2 | I14: =I$9 -> 8 | J14: 0.973 | K14: 0 | L14: =((H14*J14)+H14+K14)*I14 -> 0
A15: =IF(OFFSET(A15,-1,0)="",OFFSET(A15,-2,0),OFFSET(A15,-1,0)) -> 1 | B15: =IF(OFFSET(B15,-1,0)>="01",CONCATENATE(,OFFSET(B15,-1,0)+1),CONCATENATE((SUM(OFFSET(B15,-1,0)+1-(OFFSET(B15,-1,0)))))) -> 7 | E15: =IF(B15="1",CONCATENATE(A15,".0",B15),IF(B15="2",CONCATENATE(A15,".0",B15),IF(B15="3",CONCATENATE(A15,".0",B15),IF(B15="4",CONCATENATE(A15,".0",B15),IF(B15="5",CONCATENATE(A15,".0",B15),IF(B15="6",CONCATENATE(A15,".0",B15),IF(B15="7",CONCATENATE(A15,".0",B15),IF(B15="8",CONCATENATE(A15,".0",B15),IF(B15="9",CONCATENATE(A15,".0",B15),CONCATENATE(A15,".",B15)))))))))) -> 1.07 | F15: Orçamentos 3 | I15: =I$9 -> 8 | J15: 0 | K15: 0 | L15: =((H15*J15)+H15+K15)*I15 -> 0
A16: =IF(OFFSET(A16,-1,0)="",OFFSET(A16,-2,0),OFFSET(A16,-1,0)) -> 1 | B16: =IF(OFFSET(B16,-1,0)>="01",CONCATENATE(,OFFSET(B16,-1,0)+1),CONCATENATE((SUM(OFFSET(B16,-1,0)+1-(OFFSET(B16,-1,0)))))) -> 8 | E16: =IF(B16="1",CONCATENATE(A16,".0",B16),IF(B16="2",CONCATENATE(A16,".0",B16),IF(B16="3",CONCATENATE(A16,".0",B16),IF(B16="4",CONCATENATE(A16,".0",B16),IF(B16="5",CONCATENATE(A16,".0",B16),IF(B16="6",CONCATENATE(A16,".0",B16),IF(B16="7",CONCATENATE(A16,".0",B16),IF(B16="8",CONCATENATE(A16,".0",B16),IF(B16="9",CONCATENATE(A16,".0",B16),CONCATENATE(A16,".",B16)))))))))) -> 1.08 | F16: Planejamento 1 | I16: =I$9 -> 8 | J16: 0 | K16: 0 | L16: =((H16*J16)+H16+K16)*I16 -> 0
A17: =IF(OFFSET(A17,-1,0)="",OFFSET(A17,-2,0),OFFSET(A17,-1,0)) -> 1 | B17: =IF(OFFSET(B17,-1,0)>="01",CONCATENATE(,OFFSET(B17,-1,0)+1),CONCATENATE((SUM(OFFSET(B17,-1,0)+1-(OFFSET(B17,-1,0)))))) -> 9 | E17: =IF(B17="1",CONCATENATE(A17,".0",B17),IF(B17="2",CONCATENATE(A17,".0",B17),IF(B17="3",CONCATENATE(A17,".0",B17),IF(B17="4",CONCATENATE(A17,".0",B17),IF(B17="5",CONCATENATE(A17,".0",B17),IF(B17="6",CONCATENATE(A17,".0",B17),IF(B17="7",CONCATENATE(A17,".0",B17),IF(B17="8",CONCATENATE(A17,".0",B17),IF(B17="9",CONCATENATE(A17,".0",B17),CONCATENATE(A17,".",B17)))))))))) -> 1.09 | F17: Planejamento 2 | I17: =I$9 -> 8 | J17: 0 | K17: 0 | L17: =((H17*J17)+H17+K17)*I17 -> 0
A18: =IF(OFFSET(A18,-1,0)="",OFFSET(A18,-2,0),OFFSET(A18,-1,0)) -> 1 | B18: =IF(OFFSET(B18,-1,0)>="01",CONCATENATE(,OFFSET(B18,-1,0)+1),CONCATENATE((SUM(OFFSET(B18,-1,0)+1-(OFFSET(B18,-1,0)))))) -> 10 | E18: =IF(B18="1",CONCATENATE(A18,".0",B18),IF(B18="2",CONCATENATE(A18,".0",B18),IF(B18="3",CONCATENATE(A18,".0",B18),IF(B18="4",CONCATENATE(A18,".0",B18),IF(B18="5",CONCATENATE(A18,".0",B18),IF(B18="6",CONCATENATE(A18,".0",B18),IF(B18="7",CONCATENATE(A18,".0",B18),IF(B18="8",CONCATENATE(A18,".0",B18),IF(B18="9",CONCATENATE(A18,".0",B18),CONCATENATE(A18,".",B18)))))))))) -> 1.10 | F18: Setor Tecnologia | I18: =I$9 -> 8 | J18: 0 | K18: 0 | L18: =((H18*J18)+H18+K18)*I18 -> 0
A19: =IF(OFFSET(A19,-1,0)="",OFFSET(A19,-2,0),OFFSET(A19,-1,0)) -> 1 | B19: =IF(OFFSET(B19,-1,0)>="01",CONCATENATE(,OFFSET(B19,-1,0)+1),CONCATENATE((SUM(OFFSET(B19,-1,0)+1-(OFFSET(B19,-1,0)))))) -> 11 | E19: =IF(B19="1",CONCATENATE(A19,".0",B19),IF(B19="2",CONCATENATE(A19,".0",B19),IF(B19="3",CONCATENATE(A19,".0",B19),IF(B19="4",CONCATENATE(A19,".0",B19),IF(B19="5",CONCATENATE(A19,".0",B19),IF(B19="6",CONCATENATE(A19,".0",B19),IF(B19="7",CONCATENATE(A19,".0",B19),IF(B19="8",CONCATENATE(A19,".0",B19),IF(B19="9",CONCATENATE(A19,".0",B19),CONCATENATE(A19,".",B19)))))))))) -> 1.11 | F19: Recursos Humanos 1 | I19: =I$9 -> 8 | J19: 0.973 | K19: 0 | L19: =((H19*J19)+H19+K19)*I19 -> 0
A20: =IF(OFFSET(A20,-1,0)="",OFFSET(A20,-2,0),OFFSET(A20,-1,0)) -> 1 | B20: =IF(OFFSET(B20,-1,0)>="01",CONCATENATE(,OFFSET(B20,-1,0)+1),CONCATENATE((SUM(OFFSET(B20,-1,0)+1-(OFFSET(B20,-1,0)))))) -> 12 | E20: =IF(B20="1",CONCATENATE(A20,".0",B20),IF(B20="2",CONCATENATE(A20,".0",B20),IF(B20="3",CONCATENATE(A20,".0",B20),IF(B20="4",CONCATENATE(A20,".0",B20),IF(B20="5",CONCATENATE(A20,".0",B20),IF(B20="6",CONCATENATE(A20,".0",B20),IF(B20="7",CONCATENATE(A20,".0",B20),IF(B20="8",CONCATENATE(A20,".0",B20),IF(B20="9",CONCATENATE(A20,".0",B20),CONCATENATE(A20,".",B20)))))))))) -> 1.12 | F20: Recursos Humanos 2 | I20: =I$9 -> 8 | J20: 0 | K20: 0 | L20: =((H20*J20)+H20+K20)*I20 -> 0
A21: =IF(OFFSET(A21,-1,0)="",OFFSET(A21,-2,0),OFFSET(A21,-1,0)) -> 1 | B21: =IF(OFFSET(B21,-1,0)>="01",CONCATENATE(,OFFSET(B21,-1,0)+1),CONCATENATE((SUM(OFFSET(B21,-1,0)+1-(OFFSET(B21,-1,0)))))) -> 13 | E21: =IF(B21="1",CONCATENATE(A21,".0",B21),IF(B21="2",CONCATENATE(A21,".0",B21),IF(B21="3",CONCATENATE(A21,".0",B21),IF(B21="4",CONCATENATE(A21,".0",B21),IF(B21="5",CONCATENATE(A21,".0",B21),IF(B21="6",CONCATENATE(A21,".0",B21),IF(B21="7",CONCATENATE(A21,".0",B21),IF(B21="8",CONCATENATE(A21,".0",B21),IF(B21="9",CONCATENATE(A21,".0",B21),CONCATENATE(A21,".",B21)))))))))) -> 1.13 | F21: Financeiro 1 | I21: =I$9 -> 8 | J21: 0.973 | K21: 0 | L21: =((H21*J21)+H21+K21)*I21 -> 0
... A35: =IF(OFFSET(A35,-1,0)="",OFFSET(A35,-2,0),OFFSET(A35,-1,0)) -> 1 | B35: =IF(OFFSET(B35,-1,0)>="01",CONCATENATE(,OFFSET(B35,-1,0)+1),CONCATENATE((SUM(OFFSET(B35,-1,0)+1-(OFFSET(B35,-1,0)))))) -> 27 | E35: =IF(B35="1",CONCATENATE(A35,".0",B35),IF(B35="2",CONCATENATE(A35,".0",B35),IF(B35="3",CONCATENATE(A35,".0",B35),IF(B35="4",CONCATENATE(A35,".0",B35),IF(B35="5",CONCATENATE(A35,".0",B35),IF(B35="6",CONCATENATE(A35,".0",B35),IF(B35="7",CONCATENATE(A35,".0",B35),IF(B35="8",CONCATENATE(A35,".0",B35),IF(B35="9",CONCATENATE(A35,".0",B35),CONCATENATE(A35,".",B35)))))))))) -> 1.27 | F35: Projetos 3 | I35: =I$9 -> 8 | J35: 0.973 | K35: 0 | L35: =((H35*J35)+H35+K35)*I35 -> 0
A36: =IF(OFFSET(A36,-1,0)="",OFFSET(A36,-2,0),OFFSET(A36,-1,0)) -> 1 | B36: =IF(OFFSET(B36,-1,0)>="01",CONCATENATE(,OFFSET(B36,-1,0)+1),CONCATENATE((SUM(OFFSET(B36,-1,0)+1-(OFFSET(B36,-1,0)))))) -> 28 | E36: =IF(B36="1",CONCATENATE(A36,".0",B36),IF(B36="2",CONCATENATE(A36,".0",B36),IF(B36="3",CONCATENATE(A36,".0",B36),IF(B36="4",CONCATENATE(A36,".0",B36),IF(B36="5",CONCATENATE(A36,".0",B36),IF(B36="6",CONCATENATE(A36,".0",B36),IF(B36="7",CONCATENATE(A36,".0",B36),IF(B36="8",CONCATENATE(A36,".0",B36),IF(B36="9",CONCATENATE(A36,".0",B36),CONCATENATE(A36,".",B36)))))))))) -> 1.28 | F36: Consultoria | I36: =I$9 -> 8 | L36: =((H36*J36)+H36+K36)*I36 -> 0
A37: =IF(OFFSET(A37,-1,0)="",OFFSET(A37,-2,0),OFFSET(A37,-1,0)) -> 1 | B37: =IF(OFFSET(B37,-1,0)>="01",CONCATENATE(,OFFSET(B37,-1,0)+1),CONCATENATE((SUM(OFFSET(B37,-1,0)+1-(OFFSET(B37,-1,0)))))) -> 29 | E37: =IF(B37="1",CONCATENATE(A37,".0",B37),IF(B37="2",CONCATENATE(A37,".0",B37),IF(B37="3",CONCATENATE(A37,".0",B37),IF(B37="4",CONCATENATE(A37,".0",B37),IF(B37="5",CONCATENATE(A37,".0",B37),IF(B37="6",CONCATENATE(A37,".0",B37),IF(B37="7",CONCATENATE(A37,".0",B37),IF(B37="8",CONCATENATE(A37,".0",B37),IF(B37="9",CONCATENATE(A37,".0",B37),CONCATENATE(A37,".",B37)))))))))) -> 1.29 | I37: =I$47 -> 8 | L37: =((H37*J37)+H37+K37)*I37 -> 0
A38: =IF(OFFSET(A38,-1,0)="",OFFSET(A38,-2,0),OFFSET(A38,-1,0)) -> 1 | B38: =IF(OFFSET(B38,-1,0)>="01",CONCATENATE(,OFFSET(B38,-1,0)+1),CONCATENATE((SUM(OFFSET(B38,-1,0)+1-(OFFSET(B38,-1,0)))))) -> 30 | E38: =IF(B38="1",CONCATENATE(A38,".0",B38),IF(B38="2",CONCATENATE(A38,".0",B38),IF(B38="3",CONCATENATE(A38,".0",B38),IF(B38="4",CONCATENATE(A38,".0",B38),IF(B38="5",CONCATENATE(A38,".0",B38),IF(B38="6",CONCATENATE(A38,".0",B38),IF(B38="7",CONCATENATE(A38,".0",B38),IF(B38="8",CONCATENATE(A38,".0",B38),IF(B38="9",CONCATENATE(A38,".0",B38),CONCATENATE(A38,".",B38)))))))))) -> 1.30 | I38: =I$47 -> 8 | L38: =((H38*J38)+H38+K38)*I38 -> 0
A39: =IF(OFFSET(A39,-1,0)="",OFFSET(A39,-2,0),OFFSET(A39,-1,0)) -> 1 | B39: =IF(OFFSET(B39,-1,0)>="01",CONCATENATE(,OFFSET(B39,-1,0)+1),CONCATENATE((SUM(OFFSET(B39,-1,0)+1-(OFFSET(B39,-1,0)))))) -> 31 | E39: =IF(B39="1",CONCATENATE(A39,".0",B39),IF(B39="2",CONCATENATE(A39,".0",B39),IF(B39="3",CONCATENATE(A39,".0",B39),IF(B39="4",CONCATENATE(A39,".0",B39),IF(B39="5",CONCATENATE(A39,".0",B39),IF(B39="6",CONCATENATE(A39,".0",B39),IF(B39="7",CONCATENATE(A39,".0",B39),IF(B39="8",CONCATENATE(A39,".0",B39),IF(B39="9",CONCATENATE(A39,".0",B39),CONCATENATE(A39,".",B39)))))))))) -> 1.31 | I39: =I$47 -> 8 | L39: =((H39*J39)+H39+K39)*I39 -> 0
A40: =IF(OFFSET(A40,-1,0)="",OFFSET(A40,-2,0),OFFSET(A40,-1,0)) -> 1 | B40: =IF(OFFSET(B40,-1,0)>="01",CONCATENATE(,OFFSET(B40,-1,0)+1),CONCATENATE((SUM(OFFSET(B40,-1,0)+1-(OFFSET(B40,-1,0)))))) -> 32 | E40: =IF(B40="1",CONCATENATE(A40,".0",B40),IF(B40="2",CONCATENATE(A40,".0",B40),IF(B40="3",CONCATENATE(A40,".0",B40),IF(B40="4",CONCATENATE(A40,".0",B40),IF(B40="5",CONCATENATE(A40,".0",B40),IF(B40="6",CONCATENATE(A40,".0",B40),IF(B40="7",CONCATENATE(A40,".0",B40),IF(B40="8",CONCATENATE(A40,".0",B40),IF(B40="9",CONCATENATE(A40,".0",B40),CONCATENATE(A40,".",B40)))))))))) -> 1.32 | I40: =I$47 -> 8 | L40: =((H40*J40)+H40+K40)*I40 -> 0
A41: =IF(OFFSET(A41,-1,0)="",OFFSET(A41,-2,0),OFFSET(A41,-1,0)) -> 1 | B41: =IF(OFFSET(B41,-1,0)>="01",CONCATENATE(,OFFSET(B41,-1,0)+1),CONCATENATE((SUM(OFFSET(B41,-1,0)+1-(OFFSET(B41,-1,0)))))) -> 33 | E41: =IF(B41="1",CONCATENATE(A41,".0",B41),IF(B41="2",CONCATENATE(A41,".0",B41),IF(B41="3",CONCATENATE(A41,".0",B41),IF(B41="4",CONCATENATE(A41,".0",B41),IF(B41="5",CONCATENATE(A41,".0",B41),IF(B41="6",CONCATENATE(A41,".0",B41),IF(B41="7",CONCATENATE(A41,".0",B41),IF(B41="8",CONCATENATE(A41,".0",B41),IF(B41="9",CONCATENATE(A41,".0",B41),CONCATENATE(A41,".",B41)))))))))) -> 1.33 | I41: =I$47 -> 8 | L41: =((H41*J41)+H41+K41)*I41 -> 0
A42: =IF(OFFSET(A42,-1,0)="",OFFSET(A42,-2,0),OFFSET(A42,-1,0)) -> 1 | B42: =IF(OFFSET(B42,-1,0)>="01",CONCATENATE(,OFFSET(B42,-1,0)+1),CONCATENATE((SUM(OFFSET(B42,-1,0)+1-(OFFSET(B42,-1,0)))))) -> 34 | E42: =IF(B42="1",CONCATENATE(A42,".0",B42),IF(B42="2",CONCATENATE(A42,".0",B42),IF(B42="3",CONCATENATE(A42,".0",B42),IF(B42="4",CONCATENATE(A42,".0",B42),IF(B42="5",CONCATENATE(A42,".0",B42),IF(B42="6",CONCATENATE(A42,".0",B42),IF(B42="7",CONCATENATE(A42,".0",B42),IF(B42="8",CONCATENATE(A42,".0",B42),IF(B42="9",CONCATENATE(A42,".0",B42),CONCATENATE(A42,".",B42)))))))))) -> 1.34 | F42: =IF(F41="","para inserir linha: copie a linha acima","") -> para inserir linha: copie a linha acima | I42: =I$47 -> 8 | L42: =((H42*J42)+H42+K42)*I42 -> 0
A43: =IF(OFFSET(A43,-1,0)="",OFFSET(A43,-2,0),OFFSET(A43,-1,0)) -> 1 | B43: =IF(OFFSET(B43,-1,0)>="01",CONCATENATE(,OFFSET(B43,-1,0)+1),CONCATENATE((SUM(OFFSET(B43,-1,0)+1-(OFFSET(B43,-1,0)))))) -> 35 | E43: =IF(B43="1",CONCATENATE(A43,".0",B43),IF(B43="2",CONCATENATE(A43,".0",B43),IF(B43="3",CONCATENATE(A43,".0",B43),IF(B43="4",CONCATENATE(A43,".0",B43),IF(B43="5",CONCATENATE(A43,".0",B43),IF(B43="6",CONCATENATE(A43,".0",B43),IF(B43="7",CONCATENATE(A43,".0",B43),IF(B43="8",CONCATENATE(A43,".0",B43),IF(B43="9",CONCATENATE(A43,".0",B43),CONCATENATE(A43,".",B43)))))))))) -> 1.35 | F43: Subtotal 1 | L43: =SUM($L$9:$L$42) -> 0
A44: =IF(OFFSET(A44,-1,0)="",OFFSET(A44,-2,0),OFFSET(A44,-1,0)) -> 1 | B44: =IF(OFFSET(B44,-1,0)>="01",CONCATENATE(,OFFSET(B44,-1,0)+1),CONCATENATE((SUM(OFFSET(B44,-1,0)+1-(OFFSET(B44,-1,0)))))) -> 36 | E44: =IF(B44="1",CONCATENATE(A44,".0",B44),IF(B44="2",CONCATENATE(A44,".0",B44),IF(B44="3",CONCATENATE(A44,".0",B44),IF(B44="4",CONCATENATE(A44,".0",B44),IF(B44="5",CONCATENATE(A44,".0",B44),IF(B44="6",CONCATENATE(A44,".0",B44),IF(B44="7",CONCATENATE(A44,".0",B44),IF(B44="8",CONCATENATE(A44,".0",B44),IF(B44="9",CONCATENATE(A44,".0",B44),CONCATENATE(A44,".",B44)))))))))) -> 1.36 | F44: Rateio / Incidências sobre ESTA OBRA | L44: 1
A45: =IF(OFFSET(A45,-1,0)="",OFFSET(A45,-2,0),OFFSET(A45,-1,0)) -> 1 | B45: =IF(OFFSET(B45,-1,0)>="01",CONCATENATE(,OFFSET(B45,-1,0)+1),CONCATENATE((SUM(OFFSET(B45,-1,0)+1-(OFFSET(B45,-1,0)))))) -> 37 | E45: =IF(B45="1",CONCATENATE(A45,".0",B45),IF(B45="2",CONCATENATE(A45,".0",B45),IF(B45="3",CONCATENATE(A45,".0",B45),IF(B45="4",CONCATENATE(A45,".0",B45),IF(B45="5",CONCATENATE(A45,".0",B45),IF(B45="6",CONCATENATE(A45,".0",B45),IF(B45="7",CONCATENATE(A45,".0",B45),IF(B45="8",CONCATENATE(A45,".0",B45),IF(B45="9",CONCATENATE(A45,".0",B45),CONCATENATE(A45,".",B45)))))))))) -> 1.37 | F45: =CONCATENATE("Subtotal parcial"," ",$F$8) -> Subtotal parcial Pessoal: | L45: =L43*L44 -> 0
A46: =D46 -> 2 | B46: =D46 -> 2 | D46: 2 | F46: Predial: | H46: Base | I46: Tempo (Obra) | J46: Valor | K46: Margem Erro | L46: Total
A47: =IF(OFFSET(A47,-1,0)="",OFFSET(A47,-2,0),OFFSET(A47,-1,0)) -> 2 | B47: =IF(OFFSET(B47,-1,0)>="01",CONCATENATE(,OFFSET(B47,-1,0)+1),CONCATENATE((SUM(OFFSET(B47,-1,0)+1-(OFFSET(B47,-1,0)))))) -> 1 | E47: =IF(B47="1",CONCATENATE(A47,".0",B47),IF(B47="2",CONCATENATE(A47,".0",B47),IF(B47="3",CONCATENATE(A47,".0",B47),IF(B47="4",CONCATENATE(A47,".0",B47),IF(B47="5",CONCATENATE(A47,".0",B47),IF(B47="6",CONCATENATE(A47,".0",B47),IF(B47="7",CONCATENATE(A47,".0",B47),IF(B47="8",CONCATENATE(A47,".0",B47),IF(B47="9",CONCATENATE(A47,".0",B47),CONCATENATE(A47,".",B47)))))))))) -> 2.01 | F47: Aluguel predial + IPTU | H47: mensal | I47: =I9 -> 8 | J47: 0 | K47: 0.5 | L47: =(I47*J47)+K47*(I47*J47) -> 0
A48: =IF(OFFSET(A48,-1,0)="",OFFSET(A48,-2,0),OFFSET(A48,-1,0)) -> 2 | B48: =IF(OFFSET(B48,-1,0)>="01",CONCATENATE(,OFFSET(B48,-1,0)+1),CONCATENATE((SUM(OFFSET(B48,-1,0)+1-(OFFSET(B48,-1,0)))))) -> 2 | E48: =IF(B48="1",CONCATENATE(A48,".0",B48),IF(B48="2",CONCATENATE(A48,".0",B48),IF(B48="3",CONCATENATE(A48,".0",B48),IF(B48="4",CONCATENATE(A48,".0",B48),IF(B48="5",CONCATENATE(A48,".0",B48),IF(B48="6",CONCATENATE(A48,".0",B48),IF(B48="7",CONCATENATE(A48,".0",B48),IF(B48="8",CONCATENATE(A48,".0",B48),IF(B48="9",CONCATENATE(A48,".0",B48),CONCATENATE(A48,".",B48)))))))))) -> 2.02 | F48: Energia Elétrica | H48: mensal | I48: =I$47 -> 8 | J48: 0 | K48: 0.5 | L48: =(I48*J48)+K48*(I48*J48) -> 0
A49: =IF(OFFSET(A49,-1,0)="",OFFSET(A49,-2,0),OFFSET(A49,-1,0)) -> 2 | B49: =IF(OFFSET(B49,-1,0)>="01",CONCATENATE(,OFFSET(B49,-1,0)+1),CONCATENATE((SUM(OFFSET(B49,-1,0)+1-(OFFSET(B49,-1,0)))))) -> 3 | E49: =IF(B49="1",CONCATENATE(A49,".0",B49),IF(B49="2",CONCATENATE(A49,".0",B49),IF(B49="3",CONCATENATE(A49,".0",B49),IF(B49="4",CONCATENATE(A49,".0",B49),IF(B49="5",CONCATENATE(A49,".0",B49),IF(B49="6",CONCATENATE(A49,".0",B49),IF(B49="7",CONCATENATE(A49,".0",B49),IF(B49="8",CONCATENATE(A49,".0",B49),IF(B49="9",CONCATENATE(A49,".0",B49),CONCATENATE(A49,".",B49)))))))))) -> 2.03 | F49: Água | H49: mensal | I49: =I$47 -> 8 | J49: 0 | K49: 0.5 | L49: =(I49*J49)+K49*(I49*J49) -> 0
A50: =IF(OFFSET(A50,-1,0)="",OFFSET(A50,-2,0),OFFSET(A50,-1,0)) -> 2 | B50: =IF(OFFSET(B50,-1,0)>="01",CONCATENATE(,OFFSET(B50,-1,0)+1),CONCATENATE((SUM(OFFSET(B50,-1,0)+1-(OFFSET(B50,-1,0)))))) -> 4 | E50: =IF(B50="1",CONCATENATE(A50,".0",B50),IF(B50="2",CONCATENATE(A50,".0",B50),IF(B50="3",CONCATENATE(A50,".0",B50),IF(B50="4",CONCATENATE(A50,".0",B50),IF(B50="5",CONCATENATE(A50,".0",B50),IF(B50="6",CONCATENATE(A50,".0",B50),IF(B50="7",CONCATENATE(A50,".0",B50),IF(B50="8",CONCATENATE(A50,".0",B50),IF(B50="9",CONCATENATE(A50,".0",B50),CONCATENATE(A50,".",B50)))))))))) -> 2.04 | F50: Manutenção Predial (Faxina/Limpeza/Reformas) | H50: mensal | I50: =I$47 -> 8 | J50: 0 | K50: 0.5 | L50: =(I50*J50)+K50*(I50*J50) -> 0
A51: =IF(OFFSET(A51,-1,0)="",OFFSET(A51,-2,0),OFFSET(A51,-1,0)) -> 2 | B51: =IF(OFFSET(B51,-1,0)>="01",CONCATENATE(,OFFSET(B51,-1,0)+1),CONCATENATE((SUM(OFFSET(B51,-1,0)+1-(OFFSET(B51,-1,0)))))) -> 5 | E51: =IF(B51="1",CONCATENATE(A51,".0",B51),IF(B51="2",CONCATENATE(A51,".0",B51),IF(B51="3",CONCATENATE(A51,".0",B51),IF(B51="4",CONCATENATE(A51,".0",B51),IF(B51="5",CONCATENATE(A51,".0",B51),IF(B51="6",CONCATENATE(A51,".0",B51),IF(B51="7",CONCATENATE(A51,".0",B51),IF(B51="8",CONCATENATE(A51,".0",B51),IF(B51="9",CONCATENATE(A51,".0",B51),CONCATENATE(A51,".",B51)))))))))) -> 2.05 | F51: Alimentação (Cafés e aniversários - 1 bolo + 2 ref. + 1 cento sal) + Confraternização Final de ano ( carne - 160,00, refri - 100,00 - cerveja 100,00) | H51: mensal | I51: =I$47 -> 8 | J51: 0 | K51: 0.5 | L51: =(I51*J51)+K51*(I51*J51) -> 0
A52: =IF(OFFSET(A52,-1,0)="",OFFSET(A52,-2,0),OFFSET(A52,-1,0)) -> 2 | B52: =IF(OFFSET(B52,-1,0)>="01",CONCATENATE(,OFFSET(B52,-1,0)+1),CONCATENATE((SUM(OFFSET(B52,-1,0)+1-(OFFSET(B52,-1,0)))))) -> 6 | E52: =IF(B52="1",CONCATENATE(A52,".0",B52),IF(B52="2",CONCATENATE(A52,".0",B52),IF(B52="3",CONCATENATE(A52,".0",B52),IF(B52="4",CONCATENATE(A52,".0",B52),IF(B52="5",CONCATENATE(A52,".0",B52),IF(B52="6",CONCATENATE(A52,".0",B52),IF(B52="7",CONCATENATE(A52,".0",B52),IF(B52="8",CONCATENATE(A52,".0",B52),IF(B52="9",CONCATENATE(A52,".0",B52),CONCATENATE(A52,".",B52)))))))))) -> 2.06 | F52: Computadores (Seguros/Manutenção Técnica) | H52: mensal | I52: =I$47 -> 8 | J52: 0 | K52: 0.5 | L52: =(I52*J52)+K52*(I52*J52) -> 0
A53: =IF(OFFSET(A53,-1,0)="",OFFSET(A53,-2,0),OFFSET(A53,-1,0)) -> 2 | B53: =IF(OFFSET(B53,-1,0)>="01",CONCATENATE(,OFFSET(B53,-1,0)+1),CONCATENATE((SUM(OFFSET(B53,-1,0)+1-(OFFSET(B53,-1,0)))))) -> 7 | E53: =IF(B53="1",CONCATENATE(A53,".0",B53),IF(B53="2",CONCATENATE(A53,".0",B53),IF(B53="3",CONCATENATE(A53,".0",B53),IF(B53="4",CONCATENATE(A53,".0",B53),IF(B53="5",CONCATENATE(A53,".0",B53),IF(B53="6",CONCATENATE(A53,".0",B53),IF(B53="7",CONCATENATE(A53,".0",B53),IF(B53="8",CONCATENATE(A53,".0",B53),IF(B53="9",CONCATENATE(A53,".0",B53),CONCATENATE(A53,".",B53)))))))))) -> 2.07 | F53: Impressoras (Impressões/papeis/plotagens) | H53: mensal | I53: =I$47 -> 8 | J53: 0 | K53: 0.5 | L53: =(I53*J53)+K53*(I53*J53) -> 0
A54: =IF(OFFSET(A54,-1,0)="",OFFSET(A54,-2,0),OFFSET(A54,-1,0)) -> 2 | B54: =IF(OFFSET(B54,-1,0)>="01",CONCATENATE(,OFFSET(B54,-1,0)+1),CONCATENATE((SUM(OFFSET(B54,-1,0)+1-(OFFSET(B54,-1,0)))))) -> 8 | E54: =IF(B54="1",CONCATENATE(A54,".0",B54),IF(B54="2",CONCATENATE(A54,".0",B54),IF(B54="3",CONCATENATE(A54,".0",B54),IF(B54="4",CONCATENATE(A54,".0",B54),IF(B54="5",CONCATENATE(A54,".0",B54),IF(B54="6",CONCATENATE(A54,".0",B54),IF(B54="7",CONCATENATE(A54,".0",B54),IF(B54="8",CONCATENATE(A54,".0",B54),IF(B54="9",CONCATENATE(A54,".0",B54),CONCATENATE(A54,".",B54)))))))))) -> 2.08 | F54: Mat. Escritório | H54: mensal | I54: =I$47 -> 8 | J54: 0 | K54: 0.5 | L54: =(I54*J54)+K54*(I54*J54) -> 0
A55: =IF(OFFSET(A55,-1,0)="",OFFSET(A55,-2,0),OFFSET(A55,-1,0)) -> 2 | B55: =IF(OFFSET(B55,-1,0)>="01",CONCATENATE(,OFFSET(B55,-1,0)+1),CONCATENATE((SUM(OFFSET(B55,-1,0)+1-(OFFSET(B55,-1,0)))))) -> 9 | E55: =IF(B55="1",CONCATENATE(A55,".0",B55),IF(B55="2",CONCATENATE(A55,".0",B55),IF(B55="3",CONCATENATE(A55,".0",B55),IF(B55="4",CONCATENATE(A55,".0",B55),IF(B55="5",CONCATENATE(A55,".0",B55),IF(B55="6",CONCATENATE(A55,".0",B55),IF(B55="7",CONCATENATE(A55,".0",B55),IF(B55="8",CONCATENATE(A55,".0",B55),IF(B55="9",CONCATENATE(A55,".0",B55),CONCATENATE(A55,".",B55)))))))))) -> 2.09 | F55: Internet banda larga | H55: mensal | I55: =I$47 -> 8 | J55: 0 | K55: 0.5 | L55: =(I55*J55)+K55*(I55*J55) -> 0
A56: =IF(OFFSET(A56,-1,0)="",OFFSET(A56,-2,0),OFFSET(A56,-1,0)) -> 2 | B56: =IF(OFFSET(B56,-1,0)>="01",CONCATENATE(,OFFSET(B56,-1,0)+1),CONCATENATE((SUM(OFFSET(B56,-1,0)+1-(OFFSET(B56,-1,0)))))) -> 10 | E56: =IF(B56="1",CONCATENATE(A56,".0",B56),IF(B56="2",CONCATENATE(A56,".0",B56),IF(B56="3",CONCATENATE(A56,".0",B56),IF(B56="4",CONCATENATE(A56,".0",B56),IF(B56="5",CONCATENATE(A56,".0",B56),IF(B56="6",CONCATENATE(A56,".0",B56),IF(B56="7",CONCATENATE(A56,".0",B56),IF(B56="8",CONCATENATE(A56,".0",B56),IF(B56="9",CONCATENATE(A56,".0",B56),CONCATENATE(A56,".",B56)))))))))) -> 2.10 | F56: Tecnologias (SIENG/Lince/DROPBOX/ MAIL CORP/) | H56: mensal | I56: =I$47 -> 8 | J56: 0 | K56: 0.5 | L56: =(I56*J56)+K56*(I56*J56) -> 0
A57: =IF(OFFSET(A57,-1,0)="",OFFSET(A57,-2,0),OFFSET(A57,-1,0)) -> 2 | B57: =IF(OFFSET(B57,-1,0)>="01",CONCATENATE(,OFFSET(B57,-1,0)+1),CONCATENATE((SUM(OFFSET(B57,-1,0)+1-(OFFSET(B57,-1,0)))))) -> 11 | E57: =IF(B57="1",CONCATENATE(A57,".0",B57),IF(B57="2",CONCATENATE(A57,".0",B57),IF(B57="3",CONCATENATE(A57,".0",B57),IF(B57="4",CONCATENATE(A57,".0",B57),IF(B57="5",CONCATENATE(A57,".0",B57),IF(B57="6",CONCATENATE(A57,".0",B57),IF(B57="7",CONCATENATE(A57,".0",B57),IF(B57="8",CONCATENATE(A57,".0",B57),IF(B57="9",CONCATENATE(A57,".0",B57),CONCATENATE(A57,".",B57)))))))))) -> 2.11 | F57: Telefonias fixas e Rede interna (do Escritório) | H57: mensal | I57: =I$47 -> 8 | J57: 0 | K57: 0.5 | L57: =(I57*J57)+K57*(I57*J57) -> 0
A58: =IF(OFFSET(A58,-1,0)="",OFFSET(A58,-2,0),OFFSET(A58,-1,0)) -> 2 | B58: =IF(OFFSET(B58,-1,0)>="01",CONCATENATE(,OFFSET(B58,-1,0)+1),CONCATENATE((SUM(OFFSET(B58,-1,0)+1-(OFFSET(B58,-1,0)))))) -> 12 | E58: =IF(B58="1",CONCATENATE(A58,".0",B58),IF(B58="2",CONCATENATE(A58,".0",B58),IF(B58="3",CONCATENATE(A58,".0",B58),IF(B58="4",CONCATENATE(A58,".0",B58),IF(B58="5",CONCATENATE(A58,".0",B58),IF(B58="6",CONCATENATE(A58,".0",B58),IF(B58="7",CONCATENATE(A58,".0",B58),IF(B58="8",CONCATENATE(A58,".0",B58),IF(B58="9",CONCATENATE(A58,".0",B58),CONCATENATE(A58,".",B58)))))))))) -> 2.12 | F58: Gasolina (se não estiver incluso no Item 1) | H58: mensal | I58: =I$47 -> 8 | J58: 0 | K58: 0.5 | L58: =(I58*J58)+K58*(I58*J58) -> 0
A59: =IF(OFFSET(A59,-1,0)="",OFFSET(A59,-2,0),OFFSET(A59,-1,0)) -> 2 | B59: =IF(OFFSET(B59,-1,0)>="01",CONCATENATE(,OFFSET(B59,-1,0)+1),CONCATENATE((SUM(OFFSET(B59,-1,0)+1-(OFFSET(B59,-1,0)))))) -> 13 | E59: =IF(B59="1",CONCATENATE(A59,".0",B59),IF(B59="2",CONCATENATE(A59,".0",B59),IF(B59="3",CONCATENATE(A59,".0",B59),IF(B59="4",CONCATENATE(A59,".0",B59),IF(B59="5",CONCATENATE(A59,".0",B59),IF(B59="6",CONCATENATE(A59,".0",B59),IF(B59="7",CONCATENATE(A59,".0",B59),IF(B59="8",CONCATENATE(A59,".0",B59),IF(B59="9",CONCATENATE(A59,".0",B59),CONCATENATE(A59,".",B59)))))))))) -> 2.13 | F59: Movelaria / Eletro domesticos - Aquisição | H59: mensal | I59: =I$47 -> 8 | J59: 0 | K59: 0.5 | L59: =(I59*J59)+K59*(I59*J59) -> 0
... A68: =IF(OFFSET(A68,-1,0)="",OFFSET(A68,-2,0),OFFSET(A68,-1,0)) -> 2 | B68: =IF(OFFSET(B68,-1,0)>="01",CONCATENATE(,OFFSET(B68,-1,0)+1),CONCATENATE((SUM(OFFSET(B68,-1,0)+1-(OFFSET(B68,-1,0)))))) -> 22 | E68: =IF(B68="1",CONCATENATE(A68,".0",B68),IF(B68="2",CONCATENATE(A68,".0",B68),IF(B68="3",CONCATENATE(A68,".0",B68),IF(B68="4",CONCATENATE(A68,".0",B68),IF(B68="5",CONCATENATE(A68,".0",B68),IF(B68="6",CONCATENATE(A68,".0",B68),IF(B68="7",CONCATENATE(A68,".0",B68),IF(B68="8",CONCATENATE(A68,".0",B68),IF(B68="9",CONCATENATE(A68,".0",B68),CONCATENATE(A68,".",B68)))))))))) -> 2.22 | F68: Segurança patrimonial | H68: mensal | I68: =I$47 -> 8 | J68: 0 | K68: 0.5 | L68: =(I68*J68)+K68*(I68*J68) -> 0
A69: =IF(OFFSET(A69,-1,0)="",OFFSET(A69,-2,0),OFFSET(A69,-1,0)) -> 2 | B69: =IF(OFFSET(B69,-1,0)>="01",CONCATENATE(,OFFSET(B69,-1,0)+1),CONCATENATE((SUM(OFFSET(B69,-1,0)+1-(OFFSET(B69,-1,0)))))) -> 23 | E69: =IF(B69="1",CONCATENATE(A69,".0",B69),IF(B69="2",CONCATENATE(A69,".0",B69),IF(B69="3",CONCATENATE(A69,".0",B69),IF(B69="4",CONCATENATE(A69,".0",B69),IF(B69="5",CONCATENATE(A69,".0",B69),IF(B69="6",CONCATENATE(A69,".0",B69),IF(B69="7",CONCATENATE(A69,".0",B69),IF(B69="8",CONCATENATE(A69,".0",B69),IF(B69="9",CONCATENATE(A69,".0",B69),CONCATENATE(A69,".",B69)))))))))) -> 2.23 | F69: Sistema de CFTV | H69: mensal | I69: =I$47 -> 8 | J69: 0 | K69: 0.03 | L69: =J69/I69 -> 0
A70: =IF(OFFSET(A70,-1,0)="",OFFSET(A70,-2,0),OFFSET(A70,-1,0)) -> 2 | B70: =IF(OFFSET(B70,-1,0)>="01",CONCATENATE(,OFFSET(B70,-1,0)+1),CONCATENATE((SUM(OFFSET(B70,-1,0)+1-(OFFSET(B70,-1,0)))))) -> 24 | E70: =IF(B70="1",CONCATENATE(A70,".0",B70),IF(B70="2",CONCATENATE(A70,".0",B70),IF(B70="3",CONCATENATE(A70,".0",B70),IF(B70="4",CONCATENATE(A70,".0",B70),IF(B70="5",CONCATENATE(A70,".0",B70),IF(B70="6",CONCATENATE(A70,".0",B70),IF(B70="7",CONCATENATE(A70,".0",B70),IF(B70="8",CONCATENATE(A70,".0",B70),IF(B70="9",CONCATENATE(A70,".0",B70),CONCATENATE(A70,".",B70)))))))))) -> 2.24 | F70: SINDUSCON (sindicato patronal) pagamento não obrigatório | H70: mensal | I70: =I$47 -> 8 | J70: 0 | K70: 0.5 | L70: =(I70*J70)+K70*(I70*J70) -> 0
A71: =IF(OFFSET(A71,-1,0)="",OFFSET(A71,-2,0),OFFSET(A71,-1,0)) -> 2 | B71: =IF(OFFSET(B71,-1,0)>="01",CONCATENATE(,OFFSET(B71,-1,0)+1),CONCATENATE((SUM(OFFSET(B71,-1,0)+1-(OFFSET(B71,-1,0)))))) -> 25 | E71: =IF(B71="1",CONCATENATE(A71,".0",B71),IF(B71="2",CONCATENATE(A71,".0",B71),IF(B71="3",CONCATENATE(A71,".0",B71),IF(B71="4",CONCATENATE(A71,".0",B71),IF(B71="5",CONCATENATE(A71,".0",B71),IF(B71="6",CONCATENATE(A71,".0",B71),IF(B71="7",CONCATENATE(A71,".0",B71),IF(B71="8",CONCATENATE(A71,".0",B71),IF(B71="9",CONCATENATE(A71,".0",B71),CONCATENATE(A71,".",B71)))))))))) -> 2.25 | F71: Expansão do Escritório | H71: mensal | I71: =I$47 -> 8 | J71: 0 | K71: 0.5 | L71: =(I71*J71)+K71*(I71*J71) -> 0
A72: =IF(OFFSET(A72,-1,0)="",OFFSET(A72,-2,0),OFFSET(A72,-1,0)) -> 2 | B72: =IF(OFFSET(B72,-1,0)>="01",CONCATENATE(,OFFSET(B72,-1,0)+1),CONCATENATE((SUM(OFFSET(B72,-1,0)+1-(OFFSET(B72,-1,0)))))) -> 26 | E72: =IF(B72="1",CONCATENATE(A72,".0",B72),IF(B72="2",CONCATENATE(A72,".0",B72),IF(B72="3",CONCATENATE(A72,".0",B72),IF(B72="4",CONCATENATE(A72,".0",B72),IF(B72="5",CONCATENATE(A72,".0",B72),IF(B72="6",CONCATENATE(A72,".0",B72),IF(B72="7",CONCATENATE(A72,".0",B72),IF(B72="8",CONCATENATE(A72,".0",B72),IF(B72="9",CONCATENATE(A72,".0",B72),CONCATENATE(A72,".",B72)))))))))) -> 2.26 | F72: Taxa de Fiscalização de Estabelecimento | H72: anual | I72: =I$47 -> 8 | J72: 0 | K72: 0.5 | L72: =((I72*J72)+K72*(I72*J72))/12 -> 0
A73: =IF(OFFSET(A73,-1,0)="",OFFSET(A73,-2,0),OFFSET(A73,-1,0)) -> 2 | B73: =IF(OFFSET(B73,-1,0)>="01",CONCATENATE(,OFFSET(B73,-1,0)+1),CONCATENATE((SUM(OFFSET(B73,-1,0)+1-(OFFSET(B73,-1,0)))))) -> 27 | E73: =IF(B73="1",CONCATENATE(A73,".0",B73),IF(B73="2",CONCATENATE(A73,".0",B73),IF(B73="3",CONCATENATE(A73,".0",B73),IF(B73="4",CONCATENATE(A73,".0",B73),IF(B73="5",CONCATENATE(A73,".0",B73),IF(B73="6",CONCATENATE(A73,".0",B73),IF(B73="7",CONCATENATE(A73,".0",B73),IF(B73="8",CONCATENATE(A73,".0",B73),IF(B73="9",CONCATENATE(A73,".0",B73),CONCATENATE(A73,".",B73)))))))))) -> 2.27 | F73: =IF(F71="","para inserir linha: copie a linha acima","") | H73: mensal | I73: =I$47 -> 8 | J73: 0 | K73: 0.5 | L73: =(I73*J73)+K73*(I73*J73) -> 0
A74: =IF(OFFSET(A74,-1,0)="",OFFSET(A74,-2,0),OFFSET(A74,-1,0)) -> 2 | B74: =IF(OFFSET(B74,-1,0)>="01",CONCATENATE(,OFFSET(B74,-1,0)+1),CONCATENATE((SUM(OFFSET(B74,-1,0)+1-(OFFSET(B74,-1,0)))))) -> 28 | E74: =IF(B74="1",CONCATENATE(A74,".0",B74),IF(B74="2",CONCATENATE(A74,".0",B74),IF(B74="3",CONCATENATE(A74,".0",B74),IF(B74="4",CONCATENATE(A74,".0",B74),IF(B74="5",CONCATENATE(A74,".0",B74),IF(B74="6",CONCATENATE(A74,".0",B74),IF(B74="7",CONCATENATE(A74,".0",B74),IF(B74="8",CONCATENATE(A74,".0",B74),IF(B74="9",CONCATENATE(A74,".0",B74),CONCATENATE(A74,".",B74)))))))))) -> 2.28 | F74: Subtotal 2 | L74: =SUM(L47:L73) -> 0
A75: =IF(OFFSET(A75,-1,0)="",OFFSET(A75,-2,0),OFFSET(A75,-1,0)) -> 2 | B75: =IF(OFFSET(B75,-1,0)>="01",CONCATENATE(,OFFSET(B75,-1,0)+1),CONCATENATE((SUM(OFFSET(B75,-1,0)+1-(OFFSET(B75,-1,0)))))) -> 29 | E75: =IF(B75="1",CONCATENATE(A75,".0",B75),IF(B75="2",CONCATENATE(A75,".0",B75),IF(B75="3",CONCATENATE(A75,".0",B75),IF(B75="4",CONCATENATE(A75,".0",B75),IF(B75="5",CONCATENATE(A75,".0",B75),IF(B75="6",CONCATENATE(A75,".0",B75),IF(B75="7",CONCATENATE(A75,".0",B75),IF(B75="8",CONCATENATE(A75,".0",B75),IF(B75="9",CONCATENATE(A75,".0",B75),CONCATENATE(A75,".",B75)))))))))) -> 2.29 | F75: Rateio / Incidências sobre ESTA OBRA | L75: 1
A76: =IF(OFFSET(A76,-1,0)="",OFFSET(A76,-2,0),OFFSET(A76,-1,0)) -> 2 | B76: =IF(OFFSET(B76,-1,0)>="01",CONCATENATE(,OFFSET(B76,-1,0)+1),CONCATENATE((SUM(OFFSET(B76,-1,0)+1-(OFFSET(B76,-1,0)))))) -> 30 | E76: =IF(B76="1",CONCATENATE(A76,".0",B76),IF(B76="2",CONCATENATE(A76,".0",B76),IF(B76="3",CONCATENATE(A76,".0",B76),IF(B76="4",CONCATENATE(A76,".0",B76),IF(B76="5",CONCATENATE(A76,".0",B76),IF(B76="6",CONCATENATE(A76,".0",B76),IF(B76="7",CONCATENATE(A76,".0",B76),IF(B76="8",CONCATENATE(A76,".0",B76),IF(B76="9",CONCATENATE(A76,".0",B76),CONCATENATE(A76,".",B76)))))))))) -> 2.30 | F76: =CONCATENATE("Subtotal parcial"," ",$F$46) -> Subtotal parcial Predial: | L76: =L74*L75 -> 0
D77: 3 | F77: FATURAMENTO ANUAL | K77: 10000000
F78: Custo do período | K78: =$L$76+$L$45 -> 0
D79: 4 | F79: CUSTO RELATIVO PARA ESTA OBRA | L79: 0.04
D81: 2 - Para rastrear células específicas Ctrl+G

Sheet Despesas Financeiras
D2: Despesas Financeiras | F2: Materiais = | G2: =materiais -> 3265572.7
E3: =BDI!F3 -> FC ENGENHARIA E CONSULTORIA LTDA | F3: Mão de Obra = | G3: =mdo+hora_extra_mdo_direta+transf_diss_ocio_mdo_direta -> 2433374.6
E4: =BDI!F4 -> julho/19 - Com desoneração da Folha de Pagamento | F4: Σ = | G4: =SUM(G2:G3) -> 5698947.3
B6: Obra: | C6: =" "&nome_da_obra -> BDI_747.xlsx | F6: Data base: | G6: =data_base_da_obra -> 46093
C8: Taxa de custo financeiro sobre o valor desembolsado | F8: f= | G8: =D11/D10 -> 5.2641301e-11 | K8: Calcular pagamentos mensais para liquidar uma dívida no cartão de crédito | Q8: 1º | R8: 2º | S8: 3º | T8: 4º | U8: 5º | V8: 6º | W8: 7º | X8: 8º | Y8: 9º | Z8: 10º | AA8: 11º | AB8: 12º | AC8: 13º | AD8: 14º | AE8: 15º | AF8: 16º | AG8: 17º | AH8: 18º | AI8: 19º | AJ8: 20º | AK8: 21º | AL8: 22º | AM8: 23º | AN8: 24º | AO8: 25º | AP8: 26º
L9: a.a. | M9: a.m.
C10: Custo Direto= | D10: =custo_direto_com_desconto_eventual -> 5698947.3 | K10: TAXA = | L10: 0.108 | M10: =L10/12 -> 0.009 | O10: -16397.962 | U10: 27266.978 | V10: 27266.978 | W10: 27266.978 | X10: 27266.978 | Y10: 27266.978 | Z10: 27266.978 | AA10: 27266.978 | AB10: 27266.978 | AC10: 27266.978 | AD10: 27266.978 | AE10: 27266.978 | AF10: 27266.978
C11: ΣMj= | D11: =(G26-D28) -> 0.0003 | K11: ( VALOR ESPERADO ) VP = | L11: -458399.06 | O11: -10575.925 | W11: 17585.937 | X11: 17585.937 | Y11: 17585.937 | Z11: 17585.937 | AA11: 17585.937 | AB11: 17585.937 | AC11: 17585.937 | AD11: 17585.937 | AE11: 17585.937 | AF11: 17585.937 | AG11: 17585.937 | AH11: 17585.937
K12: Nº ANOS = | L12: 1 | O12: -11989.264 | Y12: 19936.075 | Z12: 19936.075 | AA12: 19936.075 | AB12: 19936.075 | AC12: 19936.075 | AD12: 19936.075 | AE12: 19936.075 | AF12: 19936.075 | AG12: 19936.075 | AH12: 19936.075 | AI12: 19936.075 | AJ12: 19936.075
K13: ( VALOR FINAL ) FV = | L13: =-L15*L12*12 -> -485655.81 | O13: -1597.741 | AA13: 2656.7673 | AB13: 2656.7673 | AC13: 2656.7673 | AD13: 2656.7673 | AE13: 2656.7673 | AF13: 2656.7673 | AG13: 2656.7673 | AH13: 2656.7673 | AI13: 2656.7673 | AJ13: 2656.7673 | AK13: 2656.7673 | AL13: 2656.7673
C14: Taxa de custo financeiro - Base de cálculo | F14: f= | G14: =(((1+D16)^(D18/30))*((1+D17)^(D18/30)))-1 -> 0.03 | I14: INCC - Atualizado | K14: VALOR JUROS = | L14: =L13-L11 -> -27256.75 | O14: =SUM(O10:O13) -> -40560.892
K15: VALOR DAS PARCELAS = | L15: =PMT(M10,L12*12,L11,0) -> 40471.318 | P15: Parcelas: | U15: =SUM(U10:U14) -> 27266.978 | V15: =SUM(V10:V14) -> 27266.978 | W15: =SUM(W10:W14) -> 44852.914 | X15: =SUM(X10:X14) -> 44852.914 | Y15: =SUM(Y10:Y14) -> 64788.989 | Z15: =SUM(Z10:Z14) -> 64788.989 | AA15: =SUM(AA10:AA14) -> 67445.756 | AB15: =SUM(AB10:AB14) -> 67445.756 | ... AL15: =SUM(AL10:AL14) -> 2656.7673
C16: i = | D16: 0
C17: j a.m. = | D17: 0.03 | K17: Valor meta considerando rendimentos e aportes iguais:
C18: n = | D18: 30 | L18: a.a. | M18: a.m.
K19: TAXA = | L19: 0.015 | M19: =L19/12 -> 0.00125
C20: Legenda: | K20: ( VALOR ESPERADO ) FV = | L20: -8500
B21: i - | C21: Taxa de inflação média (atual) - INCC; | I21: Juros - Atualizado | K21: Nº ANOS = | L21: 3
B22: j - | C22: Juro mensal financimento capital de giro cobrado pelas instituições financeiras; | K22: VALOR INICIAL = | L22: 0
B23: n - | C23: Número de dias decorridos até o recebimento; | K23: VALOR DAS PARCELAS = | L23: =PMT(M19,L21*12,L22,L20,0) -> 230.98597
B24: f - | C24: Taxa de custo finaceiro;
K25: Quanto tempo levará para liquidar um empréstimo pessoal:
C26: Montante - Base de cálculo (Valor Futuro) com Juros Compostos | F26: VF= | G26: =$D$28*(1+$G$14) -> 0.0103 | L26: a.a. | M26: a.m.
K27: TAXA = | L27: 0.03 | M27: =L27/12 -> 0.0025
B28: CI-08 | C28: VP = | D28: 0.01 | K28: ( PAGAMENTO MENSAL ) PMT = | L28: -300
C29: f = | D29: =taxa_financeira -> 0.03 | K29: ( VALOR DO EMPRÉSTIMO ) VP = | L29: 2500
C30: j(total) = | D30: =G26-D28 -> 0.0003 | K30: MESES PARA QUITAÇÃO = | L30: =NPER(M27,L28,L29) -> 8.431886
C32: Legenda | K32: Compreender uma entrada:
B33: PV - | C33: Valor Presente ou Capital Inicial para custeio do empreendimento; | L33: a.a. | M33: a.m.
B34: VF - | C34: Valor Futuro ou Montante; | K34: TAXA = | L34: 0.029 | M34: =L34/12 -> 0.0024166667
B35: f - | C35: Taxa de custo finaceiro; | K35: ( PAGAMENTO MENSAL ) PMT = | L35: -350
B36: j(total) - | C36: Juros total a ser pago ou rendimento em um aplicação; | K36: Nº ANOS = | L36: 3
K37: VALOR DO FINANCIAMENTO = | L37: 19000
K38: VALOR DA ENTRADA = | L38: =L37-PV(M34,L36*12,L35) -> 6946.4796
B39: 2 - Para rastrear células específicas Ctrl+G
K41: Quanto sua poupança vai render até ao longo do tempo:
B42: Índice do mês (em %) | C42: Índice acumulado no ano (em %) | D42: Índice acumulado nos últimos 12 meses (em %) | E42: Número índice acumulado a partir de Jan/93 | L42: a.a. | M42: a.m.
B43: 43831 | C43: 0.26 | D43: 0.26 | E43: 3.9878 | F43: 2698.0045 | K43: TAXA = | L43: 0.015 | M43: =L43/12 -> 0.00125
B44: 43800 | C44: 0.14 | D44: 4.133 | E44: 4.133 | F44: 2691.0079 | K44: ( PAGAMENTO MENSAL ) PMT = | L44: -200
B45: 43770 | C45: 0.15 | D45: 3.9874 | E45: 4.1226 | F45: 2687.2458 | K45: Nº MESES = | L45: 12
B46: 43739 | C46: 0.12 | D46: 3.8317 | E46: 4.237 | F46: 2683.221 | K46: VALOR INICIAL = | L46: -500
B47: 43709 | C47: 0.6 | D47: 3.7072 | E47: 4.4556 | F47: 2680.005 | K47: VALOR DA ENTRADA = | L47: =FV(M43,L45,L44,L46) -> 2924.1207
B48: 43678 | C48: 0.34 | D48: 3.0887 | E48: 4.0091 | F48: 2664.0209 | K48: RENDIMENTO NO PERÍODO = | L48: =L47-(-L46-L44*L45) -> 24.120722
B49: 43647 | C49: 0.91 | D49: 2.7394 | E49: 3.9677 | F49: 2654.9939
B50: 43617 | C50: 0.44 | D50: 1.8129 | E50: 3.7719 | F50: 2631.0513
C52: =AVERAGE(C43:C50) -> 0.37 | D52: =D44-D50 -> 2.3201 | E52: %
D53: =D52/7 -> 0.33144286 | E53: %
D54: 7 | E54: meses
D55: =D53*D54 -> 2.3201 | E55: % - previsão da correção monetária para daqui a 10 meses
E56: indice ainda não considerado; favor avaliar essa consideração;

Sheet CHP - Auxiliar
G2: Custo Horário Produtivo - Equipamentos | Z2: Materiais = | AA2: =materiais -> 3265572.7
G3: Julio Ferraz Projetos e Obras Ltda. | Z3: Mão de Obra = | AA3: =mdo+hora_extra_mdo_direta+transf_diss_ocio_mdo_direta -> 2433374.6
G4: =BDI!F4 -> julho/19 - Com desoneração da Folha de Pagamento | Z4: Σ = | AA4: =SUM(AA2:AA3) -> 5698947.3
D6: Obra: | E6: =nome_da_obra -> BDI_747.xlsx | Z6: Data base: | AA6: =data_base_da_obra -> 46093
D8: 1 | E8: Custo horário de utilização de Equipamentos - Base de Cálculo
D9: base de cálculos e procedimentos de acordo com os critérios da norma técnica ABNT NBR 7024 | H9: Depreciação: | L9: Juros: | O9: Manutenção: | Z9: Valor Diesel = | AA9: 5.85
Z10: Valor Gasolina = | AA10: 6.85
H11: Pneus: | L11: Combustíveis: | O11: Lubrific. máquinas: | R11: Lubrific. veículos: | Z11: Valor Etanol= | AA11: 5.31
Z12: Valor óleo fino = | AA12: 38.5
Z13: Oleo hidráulico = | AA13: =304/20 -> 15.2
H15: Valor de aquisição (Va) | I15: Valor residual (Vr) | J15: Potência (HP) | K15: Vida util (anos) | L15: H. de trabalho ano (H) | M15: Valor pneu Dianteiro (P1) | N15: Valor pneu Trazeiro (P2) | O15: Fator de manut (Fm) | P15: Fator de consumo (Fc) | Q15: PROPRIEDADE | T15: OPERAÇÃO | X15: CUSTO HORÁRIO | Z15: CUSTO | AA15: CUSTO
D16: Item | F16: Descrição | Q16: Depreciação | R16: Juros | S16: Manutenção | T16: Pneus | U16: Combustíveis | V16: Lubrificantes | W16: Mão De Obra | X16: Prod. | Y16: Improd. | Z16: Mensal | AA16: Diária
A17: =E17 -> 1 | B17: =E17 -> 1 | E17: 1 | F17: Equipamentos - Infra estrutura
